Workbook

Sheet AGENDA GENERAL CON CANDIDATOS
A1: BOGOTÁ | B1: LOCALIDAD | C1: SEDE | D1: HORA | E1: ACTIVIDAD | F1: ESTRATEGIA | G1: MES | H1: DIA | I1: FECHA CAMPAÑA | J1: DETALLE DE LA ACTIVIDAD | K1: LOGROS JUSTIFICACION | L1: DIRECCIÓN | M1: LINK DE GOOGLE MAPS | N1: COORDENADAS | O1: BARRIO | P1: BENEFICIARIOS O ASISTENTES | Q1: LÍDER Y CELULAR | R1: LOGISTICA (Vecinos contactados, espacio, sillas, publicidad, refrigerios)
A2: SUR | B2: BOGOTA. D.C. - LOCALIDAD 8 KENNEDY | C2: Kennedy Central | D2: 10:00 AM | E2: TERRITORIO | F2: POLITICO COMUNITARIA | G2: Diciembre | H2: =TEXT(I2,"dddd") -> lunes | I2: 45999 | J2: Lanzamiento de campaña en Kennedy | L2: Templo Kennedy Central
A3: SUR | B3: BOGOTA. D.C. - LOCALIDAD 8 KENNEDY | C3: Class | D3: 10:00 AM | E3: TERRITORIO | F3: POLITICO COMUNITARIA | G3: Diciembre | H3: =TEXT(I3,"dddd") -> lunes | I3: 45999 | J3: Lanzamiento de campaña en Kennedy | L3: Templo Class
A4: SUR | B4: BOGOTA. D.C. - LOCALIDAD 8 KENNEDY | C4: Patio Bonito | D4: 10:00 AM | E4: TERRITORIO | F4: POLITICO COMUNITARIA | G4: Diciembre | H4: =TEXT(I4,"dddd") -> lunes | I4: 45999 | J4: Lanzamiento de campaña en Kennedy | L4: Templo Patio Bonito
A5: SUR | B5: BOGOTA. D.C. - LOCALIDAD 8 KENNEDY | C5: Patio Bonito | D5: 8:00 PM | E5: SEGUIMIENTO | F5: POLITICO COMUNITARIA | G5: Diciembre | H5: =TEXT(I5,"dddd") -> jueves | I5: 45995 | J5: Reunión con líderes Patio Bonito para seguimiento de preparativos de reuniones campaña 13 de diciembre | K5: Reunión con líderes Patio Bonito para seguimiento de preparativos de reuniones campaña 13 de diciembre | L5: Virtual | M5: Virtual | N5: Virtual | O5: Virtual | P5: 0 | Q5: Hamilton Liz (Delegado Político)
A6: SUR | B6: BOGOTA. D.C. - LOCALIDAD 8 KENNEDY | C6: Kennedy Central | D6: 9:00 PM | E6: SEGUIMIENTO | F6: POLITICO COMUNITARIA | G6: Diciembre | H6: =TEXT(I6,"dddd") -> jueves | I6: 45995 | J6: Reunión con líderes Kennedy Central para seguimiento de preparativos de reuniones campaña 14 de diciembre | K6: Reunión con líderes Kennedy Central para seguimiento de preparativos de reuniones campaña 14 de diciembre | L6: Virtual | M6: Virtual | N6: Virtual | O6: Virtual | P6: 0 | Q6: Jenny García (Delegado Político)
A7: SUR | B7: BOGOTA. D.C. - LOCALIDAD 8 KENNEDY | C7: Carvajal | D7: 8:00 PM | E7: SEGUIMIENTO | F7: POLITICO COMUNITARIA | G7: Diciembre | H7: =TEXT(I7,"dddd") -> martes | I7: 46000 | J7: Reunión con líderes Carvajal para seguimiento de preparativos de reuniones campaña 16 de diciembre | K7: Reunión con líderes Kennedy Central para seguimiento de preparativos de reuniones campaña 16 de diciembre | L7: Virtual | M7: Virtual | N7: Virtual | O7: Virtual | P7: 0 | Q7: Sergio Osorio (Delagado Político)
A8: SUR | B8: BOGOTA. D.C. - LOCALIDAD 8 KENNEDY | C8: Patio Bonito | D8: 11:00AM | E8: TERRITORIO | F8: POLITICO COMUNITARIA | G8: Diciembre | H8: =TEXT(I8,"dddd") -> sábado | I8: 46004 | J8: MT - VILLA HERMOSA MALLA VIAL (3822) Reunión con vecinos del sector + MT - VILLA HERMOSA TAPAS TELECOMUNICACIONES | K8: 1. La vía fue incluida en un contrato para mantenimiento. 2. Se realiza intervención con jornada de embellecimiento para mitigar el punto critico, con el apoyo de la Alcaldía Local de Kennedy. 3, Se logro colocar tapa de comunicaciones que llevaba muhchos años, geneando gran riesgo | L8: Cra. 87f #40-28 | M8: google.com/maps/place/Casa+Hamilton/@4.6348379,-74.168413,3a,75y,207.37h,90t/data=!3m5!1e1!3m3!1sYHLoVj54sjcWE-C48KDXpQ!2e0!6shttps:%2F%2Fstreetviewpixels-pa.googleapis.com%2Fv1%2Fthumbnail%3Fcb_client%3Dmaps_sv.tactile%26w%3D900%26h%3D600%26pitch%3D0%26panoid%3DYHLoVj54sjcWE-C48KDXpQ%26yaw%3D207.36768!4m14!1m7!3m6!1s0x8e3f9d766b7b07b1:0x84c12dc578b81adc!2sCasa+Hamilton!8m2!3d4.6348284!4d-74.168418!16s%2Fg%2F11fl0wbbvf!3m5!1s0x8e3f9d766b7b07b1:0x84c12dc578b81adc!8m2!3d4.6348284!4d-74.168418!16s%2Fg%2F11fl0wbbvf?entry=ttu&g_ep=EgoyMDI1MTEyMy4xIKXMDSoASAFQAw%3D%3D | N8: 4.635074351599803, -74.16845019045742 | O8: Villa Hermosa | P8: 25 | Q8: Paula Alarcón (3504846700)
A9: SUR | B9: BOGOTA. D.C. - LOCALIDAD 8 KENNEDY | C9: Patio Bonito | D9: 12:30 M | E9: ALMUERZO | F9: N/A | G9: Diciembre | H9: =TEXT(I9,"dddd") -> sábado | I9: 46004 | J9: Almuerzo | K9: Restaurante desayunadero de la 87 en el segundo piso (al frente del CAI Patio Bonito) | L9: calle 26 sur con carrera 87 | M9: https://www.google.com/maps/@4.6389535,-74.1608905,3a,22.8y,177.68h,99.58t/data=!3m7!1e1!3m5!1sGuilCb6sP05z17gXhzckHQ!2e0!6shttps:%2F%2Fstreetviewpixels-pa.googleapis.com%2Fv1%2Fthumbnail%3Fcb_client%3Dmaps_sv.tactile%26w%3D900%26h%3D600%26pitch%3D-9.575314414106757%26panoid%3DGuilCb6sP05z17gXhzckHQ%26yaw%3D177.68235465223438!7i16384!8i8192?entry=ttu&g_ep=EgoyMDI1MTEyMy4xIKXMDSoASAFQAw%3D%3D | N9: 4.638945840164796, -74.1609951750653 | O9: Patio Bonito | Q9: Hamilton Liz (Delegado Político)
A10: SUR | B10: BOGOTA. D.C. - LOCALIDAD 8 KENNEDY | C10: Patio Bonito | D10: 2:00PM | E10: TERRITORIO | F10: POLITICO COMUNITARIA | G10: Diciembre | H10: =TEXT(I10,"dddd") -> sábado | I10: 46004 | J10: MT - CIUDADELA PRIMAVERA MALLA VIAL Y CANCHA (248) | K10: 1. Calle 6ta 2. Mantenimiento de cancha | L10: Cra. 91c #2-90 | M10: https://www.google.com/maps/@4.6389535,-74.1608905,3a,22.8y,177.68h,99.58t/data=!3m7!1e1!3m5!1sGuilCb6sP05z17gXhzckHQ!2e0!6shttps:%2F%2Fstreetviewpixels-pa.googleapis.com%2Fv1%2Fthumbnail%3Fcb_client%3Dmaps_sv.tactile%26w%3D900%26h%3D600%26pitch%3D-9.575314414106757%26panoid%3DGuilCb6sP05z17gXhzckHQ%26yaw%3D177.68235465223438!7i16384!8i8192?entry=ttu&g_ep=EgoyMDI1MTEyMy4xIKXMDSoASAFQAw%3D%3D | N10: 4.638945840164796, -74.1609951750653 | O10: Ciudadela Primavera | P10: 30 | Q10: Ana Temilda Guerrero (3124899155)
A11: SUR | B11: BOGOTA. D.C. - LOCALIDAD 8 KENNEDY | C11: Patio Bonito | D11: 4:00PM | E11: TERRITORIO | F11: POLITICO COMUNITARIA | G11: Diciembre | H11: =TEXT(I11,"dddd") -> sábado | I11: 46004 | J11: MT - TINTAL BASURAS PUNTO CRITICO (2738) | K11: 1. Se realiza intervención con jornada de embellecimiento para mitigar el punto critico, con el apoyo de la Alcaldía Local de Kennedy. 2, Jornada Opam con más de 60 beneficiados | L11: Calle 6d # 88d - 82 Salon Santa Fe 2 | M11: https://www.google.com/maps/place/Centro+Comercial+Ciudad+Tintal/@4.6484322,-74.1566005,3a,75y,259.88h,91.84t/data=!3m7!1e1!3m5!1sPvz2ZZ_LEPMtw1hCPni5xw!2e0!6shttps:%2F%2Fstreetviewpixels-pa.googleapis.com%2Fv1%2Fthumbnail%3Fcb_client%3Dmaps_sv.tactile%26w%3D900%26h%3D600%26pitch%3D-1.8368268512086843%26panoid%3DPvz2ZZ_LEPMtw1hCPni5xw%26yaw%3D259.882344672206!7i16384!8i8192!4m10!1m2!2m1!1sciudad+tintal!3m6!1s0x8e3f9c48a6b9e475:0xb493c62a8721eed2!8m2!3d4.6525882!4d-74.1601199!15sCg1jaXVkYWQgdGludGFskgEPc2hvcHBpbmdfY2VudGVy4AEA!16s%2Fg%2F1ptxhhfkq?entry=ttu&g_ep=EgoyMDI1MTEyMy4xIKXMDSoASAFQAw%3D%3D | N11: 4.652533182459536, -74.15123604371226 | O11: Tintal | P11: 20 | Q11: Luz Elena Garzón ( 3144359628)
A12: SUR | B12: BOGOTA. D.C. - LOCALIDAD 8 KENNEDY | C12: Kennedy Central | D12: 8:00 AM | E12: ENSEÑANZA | F12: AFINIDAD | G12: Diciembre | H12: Domingo | I12: 46005 | J12: Reunion de Afinidad Objetivo Que los hnos puedan compartir con nuestros representantes, y ellos puedan motivarlos a activar sus referidos y a participar activamente del bingo Logística Invitar a los hnos para que al finalizar el culto suban, Enviaremos una invitación a los líderes que tienen menos de 5 referidos para que asistan Contaremos con sonido y cabina con micrófono En el televisor se proyectarán videos de la leyes del partido, para que mientras nuestros representantes suban puedan los asistentes verlos Activación de líderes, en info mira | L12: AV CR 80 NO 42C 83 SUR | M12: 4.622006495658455, -74.16497448186743 | N12: google.com/maps/place/Iglesia+de+Dios+Ministerial+de+Jesucristo+Internacional+-+IDMJI+-+CGMJI+BTA+EL+OLIVO/@4.6215758,-74.164928,3a,75y,316.8h,90t/data=!3m7!1e1!3m5!1sJwIftdN6Rl-LMLqtdi_3Nw!2e0!6shttps:%2F%2Fstreetviewpixels-pa.googleapis.com%2Fv1%2Fthumbnail%3Fcb_client%3Dmaps_sv.tactile%26w%3D900%26h%3D600%26pitch%3D0%26panoid%3DJwIftdN6Rl-LMLqtdi_3Nw%26yaw%3D316.80283!7i16384!8i8192!4m14!1m7!3m6!1s0x8e3f9e842a6a8335:0xe8f39c19a9ab6da3!2sIglesia+de+Dios+Ministerial+de+Jesucristo+Internacional+-+IDMJI+-+CGMJI+BTA+EL+OLIVO!8m2!3d4.6216536!4d-74.1650013!16s%2Fg%2F1tdksvtw!3m5!1s0x8e3f9e842a6a8335:0xe8f39c19a9ab6da3!8m2!3d4.6216536!4d-74.1650013!16s%2Fg%2F1tdksvtw?entry=ttu&g_ep=EgoyMDI1MTEwOS4wIKXMDSoASAFQAw%3D%3D | P12: Pendiente confirmar con delegado
A13: SUR | B13: BOGOTA. D.C. - LOCALIDAD 8 KENNEDY | C13: Kennedy Central | D13: 11:00 AM | E13: ENSEÑANZA | F13: AFINIDAD | G13: Diciembre | H13: Domingo | I13: 46005 | J13: Reunion de Afinidad Objetivo Que los hnos puedan compartir con nuestros representantes, y ellos puedan motivarlos a activar sus referidos y a participar activamente del bingo Logística Invitar a los hnos para que al finalizar el culto suban, Enviaremos una invitación a los líderes que tienen menos de 5 referidos para que asistan Contaremos con sonido y cabina con micrófono En el televisor se proyectarán videos de la leyes del partido, para que mientras nuestros representantes suban puedan los asistentes verlos Activación de líderes, en info mira | L13: AV CR 80 NO 42C 83 SUR | M13: 4.622006495658455, -74.16497448186743 | N13: google.com/maps/place/Iglesia+de+Dios+Ministerial+de+Jesucristo+Internacional+-+IDMJI+-+CGMJI+BTA+EL+OLIVO/@4.6215758,-74.164928,3a,75y,316.8h,90t/data=!3m7!1e1!3m5!1sJwIftdN6Rl-LMLqtdi_3Nw!2e0!6shttps:%2F%2Fstreetviewpixels-pa.googleapis.com%2Fv1%2Fthumbnail%3Fcb_client%3Dmaps_sv.tactile%26w%3D900%26h%3D600%26pitch%3D0%26panoid%3DJwIftdN6Rl-LMLqtdi_3Nw%26yaw%3D316.80283!7i16384!8i8192!4m14!1m7!3m6!1s0x8e3f9e842a6a8335:0xe8f39c19a9ab6da3!2sIglesia+de+Dios+Ministerial+de+Jesucristo+Internacional+-+IDMJI+-+CGMJI+BTA+EL+OLIVO!8m2!3d4.6216536!4d-74.1650013!16s%2Fg%2F1tdksvtw!3m5!1s0x8e3f9e842a6a8335:0xe8f39c19a9ab6da3!8m2!3d4.6216536!4d-74.1650013!16s%2Fg%2F1tdksvtw?entry=ttu&g_ep=EgoyMDI1MTEwOS4wIKXMDSoASAFQAw%3D%3D | P13: Pendiente confirmar con delegado
A14: SUR | B14: BOGOTA. D.C. - LOCALIDAD 8 KENNEDY | C14: Kennedy Central | D14: 1:30 PM | E14: ALMUERZO | F14: N/A | G14: Diciembre | H14: Domingo | I14: 46005 | J14: En la sede | K14: N/A | O14: Kennedy | P14: Definir por congreso y Concejo nùmero de asistentes para confirmar a la lìder | Q14: Jenny García - Delegada Política 3108524285 | R14: Definir por congreso y Concejo nùmero de asistentes para confirmar a la lìder
A15: SUR | B15: BOGOTA. D.C. - LOCALIDAD 8 KENNEDY | C15: Kennedy Central | D15: 3:00 PM | E15: TERRITORIO | F15: POLITICO COMUNITARIA | G15: Diciembre | H15: Domingo | I15: 46005 | J15: MT - ROMA IV 1ER SECTOR MALLA VIAL (1969) Reunión con sector comercial y habitantes de Roma + MT - CASABLANCA JORNADA OPAM (5646) | K15: 1. En este sector se está gestionando arreglo de 3 segmentos viales, del cual 1 la Alcaldía ya està ejecutando su arreglo 2. Jornada Opam 3. Visita con Secretaría de Movilidad para abordar problemáticas de movilidad 4. Jornada de OPAM 5. Arreglo de paradero del SITP | L15: Calle 58C#78K21 Salón comunal rubí 2 | M15: https://maps.app.goo.gl/jzrd7SQfeCSpVLPRA | O15: Roma | P15: 40
A16: SUR | B16: BOGOTA. D.C. - LOCALIDAD 8 KENNEDY | C16: Kennedy Central | D16: 5.30 PM | E16: TERRITORIO | F16: POLITICO COMUNITARIA | G16: Diciembre | H16: Domingo | I16: 46005 | J16: MT - LAS MARGARITAS ZONAS DE CESION (4329) | K16: 1. Trabajo en entrega de zonas de cesión, se logrò un parque 2. Embellecimiento de parque 3. Jornada personalización del SITP | L16: Cra 89a No 46-45 sur | M16: 4.634426583502856, -74.17797154061991 | N16: https://www.google.com/maps/@4.6341727,-74.1779911,3a,75y,356.8h,87.57t/data=!3m7!1e1!3m5!1sMhvKblnUolqsI7uZqgsS9g!2e0!6shttps:%2F%2Fstreetviewpixels-pa.googleapis.com%2Fv1%2Fthumbnail%3Fcb_client%3Dmaps_sv.tactile%26w%3D900%26h%3D600%26pitch%3D2.4308615552782413%26panoid%3DMhvKblnUolqsI7uZqgsS9g%26yaw%3D356.7964580580785!7i16384!8i8192?entry=ttu&g_ep=EgoyMDI1MTEyMy4xIKXMDSoASAFQAw%3D%3D | O16: Las Margaritas | P16: 40 | Q16: Rafael Gutierrez (3114901573)
A17: SUR | B17: BOGOTA. D.C. - LOCALIDAD 8 KENNEDY | C17: Carvajal | D17: 7:00 AM | E17: ALABANZA | F17: AFINIDAD | G17: Diciembre | H17: Martes | I17: 46007 | J17: REUNION EN EL SEGUNDO PISO CON LIDERES QUE NO TIENEN REFERIDOS Y CON LOS QUE SOLO TIENEN 5 REFERIDOS | K17: 1. Saludo de los representantes 2..contar que se ha hecho en territorio y motivar a los lideres a activar sus referidos. 3. Explicacion de como votar, inscripciones de cedulas, presentacion de publicidad de candidatos | L17: Av. Boyacá #25 Sur NO 35 | M17: 4.616503452100983, -74.14045373278768 | N17: google.com/maps/place/Iglesia+De+Dios+Ministerial+De+Jesucristo+Internacional+-+IDMJI+-CARVAJAL/@4.6162521,-74.1430179,17z/data=!3m1!4b1!4m6!3m5!1s0x8e3f9ebb73ed00eb:0x84ff2c16af65e299!8m2!3d4.6162468!4d-74.140443!16s%2Fg%2F1ptwb97lz?entry=ttu&g_ep=EgoyMDI1MTEyMy4xIKXMDSoASAFQAw%3D%3D | O17: Carvajal | Q17: Sergio Osorio (Delagado Político) 3505621182
A18: SUR | B18: BOGOTA. D.C. - LOCALIDAD 8 KENNEDY | C18: Carvajal | D18: 10:00 AM | E18: TERRITORIO | F18: POLITICO COMUNITARIA | G18: Diciembre | H18: Martes | I18: 46007 | J18: MT - CARVAJAL PARE ACOSTADO MAL PARQUEO PARQUE MARACANA | K18: 1. Arreglo de pare 2, ARREGLO TAPA TELCOMUNCIACIONES 3, Arrglo de arreglo vanti en el Parque | L18: Cra 72 p #37b-10 sur carvajal | M18: https://maps.app.goo.gl/xS5efNYhdefHghuv9 | N18: 4.615524863281549, -74.1456626069883 | O18: Carvajal | P18: 20 | Q18: Carmen Garzón
A19: SUR | B19: BOGOTA. D.C. - LOCALIDAD 8 KENNEDY | C19: Carvajal | D19: 12:00 M | E19: ALMUERZO | F19: N/A | G19: Diciembre | H19: Martes | I19: 46007 | J19: Almuerzo
A20: SUR | B20: BOGOTA. D.C. - LOCALIDAD 8 KENNEDY | C20: Carvajal | D20: 2:00 PM | E20: TERRITORIO | F20: POLITICO COMUNITARIA | G20: Diciembre | H20: Martes | I20: 46007 | J20: MT - AMERICAS CLÍNICA OCCIDENTE MALLA VIAL (2052) | K20: 1. Arreglo de 2 hundimientos | L20: carrera 71a bis #5a25 | M20: https://maps.app.goo.gl/VxzbReTCnYvUc91L7 | N20: 4.628287390266298, -74.13407056035354 | O20: Americas Central | P20: 20 | Q20: Gloria Rincón
A21: SUR | B21: BOGOTA. D.C. - LOCALIDAD 8 KENNEDY | C21: Carvajal | D21: 4:00 PM | E21: TERRITORIO | F21: POLITICO COMUNITARIA | G21: Diciembre | H21: Martes | I21: 46007 | J21: MT - MANDALAY OBRAS DE RENOVACIÓN EAAB (3269) | K21: 1. Nivelaciòn de vìa tras arreglo de Acueducto | L21: Avenida De Las Américas # 73 – 67 | M21: https://maps.app.goo.gl/gc1LMZ72Lqdxi2nT6 | N21: 4.630632908010167, -74.14153391665295 | O21: Mandalay | P21: 20 | Q21: Jimmy Gutierrez
A22: SUR | B22: BOGOTA. D.C. - LOCALIDAD 8 KENNEDY | C22: Carvajal | D22: 6:00 PM | E22: ALABANZA | F22: AFINIDAD | G22: Diciembre | H22: Martes | I22: 46007 | J22: REUNION EN EL SEGUNDO PISO CON LIDERES QUE NO TIENEN REFERIDOS Y CON LOS QUE SOLO TIENEN 5 REFERIDOS | K22: 1. Saludo de los representantes 2..contar que se ha hecho en territorio y motivar a los lideres a activar sus referidos. 3. Explicacion de como votar, inscripciones de cedulas, presentacion de publicidad de candidatos | L22: Av. Boyacá #25 Sur NO 35 | M22: 4.616503452100983, -74.14045373278768 | N22: google.com/maps/place/Iglesia+De+Dios+Ministerial+De+Jesucristo+Internacional+-+IDMJI+-CARVAJAL/@4.6162521,-74.1430179,17z/data=!3m1!4b1!4m6!3m5!1s0x8e3f9ebb73ed00eb:0x84ff2c16af65e299!8m2!3d4.6162468!4d-74.140443!16s%2Fg%2F1ptwb97lz?entry=ttu&g_ep=EgoyMDI1MTEyMy4xIKXMDSoASAFQAw%3D%3D | O22: Carvajal | Q22: Sergio Osorio (Delagado Político) 3505621182
A23: SUR | B23: BOGOTA. D.C. - LOCALIDAD 8 KENNEDY | C23: Carvajal | D23: 8:00 PM | E23: TERRITORIO | F23: POLITICO COMUNITARIA | G23: Diciembre | H23: =TEXT(I23,"dddd") -> viernes | I23: 46010 | J23: Reunión con DP para seguimiento de preparativos de reuniones campaña enero | K23: Reunión con DP para seguimiento de preparativos de reuniones campaña enero | L23: Virtual | M23: Virtual | N23: Virtual | O23: Virtual | Q23: Fernando Zamora - Lorena Garzón
A24: SUR | B24: BOGOTA. D.C. - LOCALIDAD 8 KENNEDY | C24: Carvajal | D24: 8:00 am | E24: BINGO | F24: AFINIDAD | G24: Diciembre | H24: sábado | I24: 46011 | J24: Bingo | K24: Bingo | L24: Av. Boyacá #25 Sur NO 35 | M24: google.com/maps/place/Iglesia+De+Dios+Ministerial+De+Jesucristo+Internacional+-+IDMJI+-CARVAJAL/@4.6162521,-74.1430179,17z/data=!3m1!4b1!4m6!3m5!1s0x8e3f9ebb73ed00eb:0x84ff2c16af65e299!8m2!3d4.6162468!4d-74.140443!16s%2Fg%2F1ptwb97lz?entry=ttu&g_ep=EgoyMDI1MTEyMy4xIKXMDSoASAFQAw%3D%3D | N24: 4.616503452100983, -74.14045373278768 | O24: Carvajal | P24: 100 | Q24: Sergio Osorio (Delagado Político) 3505621182
A25: SUR | B25: BOGOTA. D.C. - LOCALIDAD 8 KENNEDY | C25: Kennedy Central | D25: 8:00 am | E25: BINGO | F25: AFINIDAD | G25: Diciembre | H25: sábado | I25: 46011 | J25: Bingo | K25: Bingo | L25: AV CR 80 NO 42C 83 SUR | M25: google.com/maps/place/Iglesia+de+Dios+Ministerial+de+Jesucristo+Internacional+-+IDMJI+-+CGMJI+BTA+EL+OLIVO/@4.6215758,-74.164928,3a,75y,316.8h,90t/data=!3m7!1e1!3m5!1sJwIftdN6Rl-LMLqtdi_3Nw!2e0!6shttps:%2F%2Fstreetviewpixels-pa.googleapis.com%2Fv1%2Fthumbnail%3Fcb_client%3Dmaps_sv.tactile%26w%3D900%26h%3D600%26pitch%3D0%26panoid%3DJwIftdN6Rl-LMLqtdi_3Nw%26yaw%3D316.80283!7i16384!8i8192!4m14!1m7!3m6!1s0x8e3f9e842a6a8335:0xe8f39c19a9ab6da3!2sIglesia+de+Dios+Ministerial+de+Jesucristo+Internacional+-+IDMJI+-+CGMJI+BTA+EL+OLIVO!8m2!3d4.6216536!4d-74.1650013!16s%2Fg%2F1tdksvtw!3m5!1s0x8e3f9e842a6a8335:0xe8f39c19a9ab6da3!8m2!3d4.6216536!4d-74.1650013!16s%2Fg%2F1tdksvtw?entry=ttu&g_ep=EgoyMDI1MTEwOS4wIKXMDSoASAFQAw%3D%3D | N25: 4.622006495658455, -74.16497448186743 | O25: Kennedy Central | P25: 100 | Q25: Jenny García (3108524285)
A26: SUR | B26: BOGOTA. D.C. - LOCALIDAD 8 KENNEDY | C26: Class | D26: 7:00 AM | E26: ALABANZA | F26: AFINIDAD | G26: Diciembre | H26: Martes | I26: 46014 | J26: Reunion Identidad y Conviccion y motivacion a personas recientes en la iglesia | K26: Afinidad | L26: Cra. 80a #56-51 | M26: https://www.google.com/maps/place/IDMJI+Class+Roma/@4.6141834,-74.1760423,3a,75y,329.85h,84.86t/data=!3m7!1e1!3m5!1s_5pKrbVhz2n3AEOMoun0Lg!2e0!6shttps:%2F%2Fstreetviewpixels-pa.googleapis.com%2Fv1%2Fthumbnail%3Fcb_client%3Dmaps_sv.tactile%26w%3D900%26h%3D600%26pitch%3D5.144541014976355%26panoid%3D_5pKrbVhz2n3AEOMoun0Lg%26yaw%3D329.8452991252842!7i16384!8i8192!4m14!1m7!3m6!1s0x8e3f9f3434c2710b:0x65030ca5b65a340e!2sIDMJI+Class+Roma!8m2!3d4.6142421!4d-74.1762168!16s%2Fg%2F11fq5t0q39!3m5!1s0x8e3f9f3434c2710b:0x65030ca5b65a340e!8m2!3d4.6142421!4d-74.1762168!16s%2Fg%2F11fq5t0q39?entry=ttu&g_ep=EgoyMDI1MTEyMy4xIKXMDSoASAFQAw%3D%3D | N26: 4.614423894411722, -74.17613097327387 | O26: Class | P26: Pendiente confirmar con delegado | Q26: Bryan Rodríguez (3202378579)
A27: SUR | B27: BOGOTA. D.C. - LOCALIDAD 8 KENNEDY | C27: Class | D27: 6:30 PM | E27: ALABANZA | F27: AFINIDAD | G27: Diciembre | H27: Martes | I27: 46014 | J27: Micro reunion con líderes que tienen de 0 a 5 referidos; objetivo motivarlos a hablar del partido | K27: Afinidad | L27: Cra. 80a #56-51 | M27: https://www.google.com/maps/place/IDMJI+Class+Roma/@4.6141834,-74.1760423,3a,75y,329.85h,84.86t/data=!3m7!1e1!3m5!1s_5pKrbVhz2n3AEOMoun0Lg!2e0!6shttps:%2F%2Fstreetviewpixels-pa.googleapis.com%2Fv1%2Fthumbnail%3Fcb_client%3Dmaps_sv.tactile%26w%3D900%26h%3D600%26pitch%3D5.144541014976355%26panoid%3D_5pKrbVhz2n3AEOMoun0Lg%26yaw%3D329.8452991252842!7i16384!8i8192!4m14!1m7!3m6!1s0x8e3f9f3434c2710b:0x65030ca5b65a340e!2sIDMJI+Class+Roma!8m2!3d4.6142421!4d-74.1762168!16s%2Fg%2F11fq5t0q39!3m5!1s0x8e3f9f3434c2710b:0x65030ca5b65a340e!8m2!3d4.6142421!4d-74.1762168!16s%2Fg%2F11fq5t0q39?entry=ttu&g_ep=EgoyMDI1MTEyMy4xIKXMDSoASAFQAw%3D%3D | N27: 4.614423894411722, -74.17613097327387 | O27: Class | P27: Pendiente confirmar con delegado | Q27: Albeiro Rodriguez (3124215077)
A28: SUR | B28: BOGOTA. D.C. - LOCALIDAD 8 KENNEDY | C28: Kennedy Central | D28: 8:00 AM | E28: ENSEÑANZA | F28: AFINIDAD | G28: Diciembre | H28: Domingo | I28: 46019 | J28: Actividad de afinidad - activación de líderes y referidos [PENDIENTE DELEGADO DESCRIBIR LA ACTIVIDAD] | K28: Afinidad | L28: AV CR 80 NO 42C 83 SUR | M28: https://maps.app.goo.gl/B7Vvnj17Ra5gpNUL9 | N28: 4.622006495658455, -74.16497448186743 | O28: Kennedy Central | P28: Pendiente confirmar con delegado | Q28: Jenny García (3108524285)
A29: SUR | B29: BOGOTA. D.C. - LOCALIDAD 8 KENNEDY | C29: Kennedy Central | D29: 11:00 AM | E29: ENSEÑANZA | F29: AFINIDAD | G29: Diciembre | H29: Domingo | I29: 46019 | J29: Actividad de afinidad - activación de líderes y referidos [PENDIENTE DELEGADO DESCRIBIR LA ACTIVIDAD] | K29: Afinidad | L29: AV CR 80 NO 42C 83 SUR | M29: https://maps.app.goo.gl/B7Vvnj17Ra5gpNUL9 | N29: 4.622006495658455, -74.16497448186743 | O29: Kennedy Central | P29: Pendiente confirmar con delegado | Q29: Jenny García (3108524285)
A30: SUR | B30: BOGOTA. D.C. - LOCALIDAD 8 KENNEDY | C30: Patio Bonito | D30: 7:00 AM | E30: ALABANZA | F30: AFINIDAD | G30: Enero | H30: Viernes | I30: 46024 | J30: Actividad de afinidad - activación de líderes y referidos [PENDIENTE DELEGADO DESCRIBIR LA ACTIVIDAD] | K30: Afinidad | L30: Cra 95A #39 SUR NO.38C | M30: https://maps.app.goo.gl/aGBx2P51EGsbTbt19 | N30: 4.646227879789345, -74.17302253463195 | O30: Patio Bonito | P30: Pendiente confirmar con delegado | Q30: Hamilton Liz (3125621911)
A31: SUR | B31: BOGOTA. D.C. - LOCALIDAD 8 KENNEDY | C31: Patio Bonito | D31: 6:00 PM | E31: ALABANZA | F31: AFINIDAD | G31: Enero | H31: Viernes | I31: 46024 | J31: Actividad de afinidad - activación de líderes y referidos [PENDIENTE DELEGADO DESCRIBIR LA ACTIVIDAD] | K31: Afinidad | L31: Cra 95A #39 SUR NO.38C | M31: https://maps.app.goo.gl/aGBx2P51EGsbTbt19 | N31: 4.646227879789345, -74.17302253463195 | O31: Patio Bonito | P31: Pendiente confirmar con delegado | Q31: Hamilton Liz (3125621911)
A32: SUR | B32: BOGOTA. D.C. - LOCALIDAD 8 KENNEDY | C32: Class | D32: 7:00 AM | E32: ALABANZA | F32: AFINIDAD | G32: Enero | H32: Martes | I32: 46035 | J32: Actividad de afinidad - activación de líderes y referidos Colaboradores de la iglesia | K32: Afinidad | L32: KR 80A # 56 35 SUR CLASS ROMA | M32: https://www.google.com/maps?q=4.614135243,-74.17617048 | N32: 4.614295606307947, -74.17625633511189 | O32: CLASS ROMA | Q32: N/A
A33: SUR | B33: BOGOTA. D.C. - LOCALIDAD 8 KENNEDY | C33: Class | D33: 11:00 AM | E33: TERRITORIO | F33: POLITICO COMUNITARIA | G33: Enero | H33: Martes | I33: 46035 | J33: MT – PORTAL DE CALI REDES DE ACUEDUCTO (2015) | K33: 1. Limpieza de sumideros y de caja por medio del vactor 2. Limpieza de punto critico de basura | L33: CARRERA 82B#54B 11SUR CASA 91 | M33: https://maps.app.goo.gl/L7WTUHHDCAwqR5Z87 | N33: 4.620655888758921, -74.17926693629067 | O33: Portal de Cali | P33: 25 | Q33: Blanca
A34: SUR | B34: BOGOTA. D.C. - LOCALIDAD 8 KENNEDY | C34: Class | D34: 12:30 M | E34: ALMUERZO | F34: N/A | G34: Enero | H34: Martes | I34: 46035 | J34: ALMUERZO | K34: ALMUERZO
A35: SUR | B35: BOGOTA. D.C. - LOCALIDAD 8 KENNEDY | C35: Class | D35: 3:00 PM | E35: TERRITORIO | F35: POLITICO COMUNITARIA | G35: Enero | H35: Martes | I35: 46035 | J35: MT - VEGAS DE SANTA ANA MALLA VIAL E INUNDACIONES RÍO TUNJUELO (5509) | K35: 1. Jornada de personalización de Tu Llave 2. Mesa de trabajo con el Acueducto por afectaciones en las redes de alcantarillado | L35: Diagonal 57 A bis # 81 C - 27 sur | M35: https://maps.app.goo.gl/C5huNCbBnyA9KYG67 | N35: 4.616694700593081, -74.17972714463525 | O35: Vegas de Santa Ana | P35: 25 | Q35: Aldemar Rodriguez
A36: SUR | B36: BOGOTA. D.C. - LOCALIDAD 8 KENNEDY | C36: Class | D36: 4:30 PM | E36: TERRITORIO | F36: POLITICO COMUNITARIA | G36: Enero | H36: Martes | I36: 46035 | J36: Reunión con vecinos y familiares | K36: Rendición de cuentas | L36: Diagonal 56B sur #81J - 72 | M36: https://maps.app.goo.gl/KnubUPfDcHNqzmx5A | N36: 4.618603925849968, -74.18148190073752 | O36: Salem Samaria | P36: 20 | Q36: Liliana Malagon
A37: SUR | B37: BOGOTA. D.C. - LOCALIDAD 8 KENNEDY | C37: Class | D37: 6:30 PM | E37: ALABANZA | F37: AFINIDAD | G37: Enero | H37: Martes | I37: 46035 | J37: Actividad de afinidad - activación de líderes y referidos - Colaboradores de la iglesia | K37: Afinidad | L37: KR 80A # 56 35 SUR CLASS ROMA | M37: https://www.google.com/maps?q=4.614135243,-74.17617048 | N37: 4.614295606307947, -74.17625633511189 | O37: CLASS ROMA | Q37: N/A
C38: Patio Bonito | D38: 7:00 AM | E38: ENSEÑANZA | F38: AFINIDAD | G38: Enero | H38: Miércoles | I38: 46036 | K38: Afinidad | L38: Cra 95A #39 SUR NO.38C | M38: 4.646227879789345, -74.17302253463195 | N38: https://maps.app.goo.gl/aGBx2P51EGsbTbt19 | O38: Patio Bonito | Q38: Hamilton Liz (3125621911)
A39: SUR | B39: BOGOTA. D.C. - LOCALIDAD 8 KENNEDY | C39: Patio Bonito | D39: 2:00 PM | E39: TERRITORIO | F39: POLITICO COMUNITARIA | G39: Enero | H39: Miércoles | I39: 46036 | J39: VISITA MICROEMPRESA | K39: 1. Ley de micronegocios 2. Gestión en solicitudes puntuales de vecinos | L39: Cl. 33 Sur #89d-53 | M39: https://www.google.com/maps/@4.643407,-74.165419,3a,75y,276.93h,87.2t/data=!3m7!1e1!3m5!1s_zx3abQgk9whm3wZQIl9RA!2e0!6shttps:%2F%2Fstreetviewpixels-pa.googleapis.com%2Fv1%2Fthumbnail%3Fcb_client%3Dmaps_sv.tactile%26w%3D900%26h%3D600%26pitch%3D2.8031195662346704%26panoid%3D_zx3abQgk9whm3wZQIl9RA%26yaw%3D276.92928112065755!7i16384!8i8192?entry=ttu&g_ep=EgoyMDI2MDEwNy4wIKXMDSoASAFQAw%3D%3D | N39: 4.643631506000829, -74.16557307731713 | O39: Unir 1 | P39: 15 | Q39: ALVARO GARZÓN
A40: SUR | B40: BOGOTA. D.C. - LOCALIDAD 8 KENNEDY | C40: Patio Bonito | D40: 4:00 PM | E40: TERRITORIO | F40: POLITICO COMUNITARIA | G40: Enero | H40: Miércoles | I40: 46036 | J40: Riveras de Occidente | K40: 1. Gestión de arreglo de vía | L40: Cra. 93b # 26 Sur - 1 | M40: https://www.google.com/maps/@4.6473158,-74.1676827,3a,75y,215.87h,79.72t/data=!3m7!1e1!3m5!1sL-INdquaOGG3IsrmzWzolw!2e0!6shttps:%2F%2Fstreetviewpixels-pa.googleapis.com%2Fv1%2Fthumbnail%3Fcb_client%3Dmaps_sv.tactile%26w%3D900%26h%3D600%26pitch%3D10.282519976709054%26panoid%3DL-INdquaOGG3IsrmzWzolw%26yaw%3D215.86822430098266!7i16384!8i8192?entry=ttu&g_ep=EgoyMDI1MTIwOS4wIKXMDSoASAFQAw%3D%3D | N40: 4.647150036969973, -74.16782757241296 | O40: Riveras de Occidente | P40: 40 | Q40: VERONICA AVILA
A41: SUR | B41: BOGOTA. D.C. - LOCALIDAD 8 KENNEDY | C41: Patio Bonito | D41: 6:00 PM | E41: ENSEÑANZA | F41: AFINIDAD | G41: Enero | H41: Miércoles | I41: 46036 | K41: Afinidad | L41: Cra 95A #39 SUR NO.38C | M41: 4.646227879789345, -74.17302253463195 | N41: https://maps.app.goo.gl/aGBx2P51EGsbTbt19 | O41: Patio Bonito | Q41: Hamilton Liz (3125621911)
A42: SUR | B42: BOGOTA. D.C. - LOCALIDAD 8 KENNEDY | C42: Kennedy Central | D42: 7:00 AM | E42: ENSEÑANZA | F42: AFINIDAD | G42: Enero | H42: Jueves | I42: 46037 | J42: Actividad de afinidad - activación de líderes y referidos Microreunión Focalizada MRF MRF: Líderes activos, con 0 referidos activos, pero con referidos inactivos. | K42: Afinidad | L42: AV CR 80 NO 42C 83 SUR KENNEDY | M42: https://maps.app.goo.gl/UiBexu9Axhn6zuEZ6 | N42: 4.621764992515213, -74.16489171361977 | O42: Los Olivos | Q42: N/A
A43: SUR | B43: BOGOTA. D.C. - LOCALIDAD 8 KENNEDY | C43: Kennedy Central | D43: 10:00 AM | E43: TERRITORIO | F43: POLITICO COMUNITARIA | G43: Enero | H43: Jueves | I43: 46037 | J43: MT - CIUDAD DE CALI AFECTACIÓN POR SEMÁFORO (5109) | K43: 1. Se asignó un auxiliar de tránsito desde el 22 de agosto. 2. Confirmado el retiro del semáforo para el 19 de octubre de 2025 o hasta entregar la obra de la av Cali. | L43: Cra. 86c Bis #42 - 32 | M43: https://maps.app.goo.gl/9j3GGhx4THnQhm1N6 | N43: 4.6318622196069965, -74.16833461172479 | O43: Ciudad de Cali | P43: 25 | Q43: ORLANDO MARULANDA LEON 3045831717
A44: SUR | B44: BOGOTA. D.C. - LOCALIDAD 8 KENNEDY | C44: Kennedy Central | D44: 12:00 M | E44: ALMUERZO | F44: N/A | G44: Enero | H44: Jueves | I44: 46037 | J44: ALMUERZO ALMUERZO | K44: ALMUERZO ALMUERZO
A45: SUR | B45: BOGOTA. D.C. - LOCALIDAD 8 KENNEDY | C45: Kennedy Central | D45: 2:00 PM | E45: TERRITORIO | F45: POLITICO COMUNITARIA | G45: Enero | H45: Jueves | I45: 46037 | J45: MT - CIUDAD KENNEDY OCCIDENTAL INSEGURIDAD POR RETIRO DE REJAS DE INGRESO (6236 | K45: 1. Se esta gestionando con el DADEP la administración de las bahías por parte de la JAC 2. Se realizaron dos mesas de trabajo para fortalecer el frente de seguridad 3. Se esta gestionando con la ALK el arreglo de la bahía, ya que es un segmento local. | L45: Av calle 43 #79d 01 Salón comunal nuevo Kennedy 2 sector | M45: https://maps.app.goo.gl/3r17ZACt9RpwC6Kr7 | N45: 4.619368374284227, -74.16620313683892 | O45: Nuevo Kennedy | P45: 20 | Q45: MIGUEL ADRIEL GUERRERO SANCHEZ 3214929228
A46: SUR | B46: BOGOTA. D.C. - LOCALIDAD 8 KENNEDY | C46: Kennedy Central | D46: 3:30 PM | E46: TERRITORIO | F46: POLITICO COMUNITARIA | G46: Enero | H46: Jueves | I46: 46037 | J46: MT - JORNADA OPAM PARQUE HOLANDA (6172) | K46: Visita empresa INGEPAR 1. Se realizó jornada de salud y bienestar animal con OPAM, se beneficiarion cerca de 40 personas con sus animales de compañía. | L46: Cra. 88b #53 - 51 sur | M46: https://maps.app.goo.gl/B7Vvnj17Ra5gpNUL9 | N46: 4.629549105441344, -74.18311837297175 | O46: Bosa Brasilia | P46: 20 | Q46: NUBIA LILIANA PARRA GUERRERO 3202930363
A47: SUR | B47: BOGOTA. D.C. - LOCALIDAD 8 KENNEDY | C47: Kennedy Central | D47: 5:00 PM | E47: ENSEÑANZA | F47: AFINIDAD | G47: Enero | H47: Jueves | I47: 46037 | J47: Actividad de afinidad - activación de líderes y referidos Microreunión Focalizada MRF MRF: Líderes activos, con 0 referidos activos, pero con referidos inactivos. | K47: Afinidad | L47: AV CR 80 NO 42C 83 SUR KENNEDY | M47: https://maps.app.goo.gl/UiBexu9Axhn6zuEZ6 | N47: 4.621764992515213, -74.16489171361977 | O47: Los Olivos | Q47: N/A
C48: Kennedy Central | D48: 7:00 PM | E48: ENSEÑANZA | F48: AFINIDAD | G48: Enero | H48: Jueves | I48: 46037 | J48: Actividad de afinidad - activación de líderes y referidos Microreunión Focalizada MRF MRF: Líderes activos, con 0 referidos activos, pero con referidos inactivos. | K48: Afinidad | L48: AV CR 80 NO 42C 83 SUR KENNEDY | M48: https://maps.app.goo.gl/UiBexu9Axhn6zuEZ6 | N48: 4.621764992515213, -74.16489171361977 | O48: Los Olivos | Q48: N/A
A49: SUR | B49: BOGOTA. D.C. - LOCALIDAD 8 KENNEDY | C49: Carvajal | D49: 7:00 AM | E49: ALABANZA | F49: AFINIDAD | G49: Enero | H49: Viernes | I49: 46038 | J49: Actividad de afinidad - activación de líderes y referidos: REUNION CON LIDERES EN EL SEGUNDO PISO DE CARVAJAL, SE VA A INVITAR APROXIMADAMENTE 30 PERSONAS QUE AUN NO SE HAN ACTIVADO COMO LIDERES, QUE NO TIENE REFERIDOS, PARA REALIZAR ACTIVIDAD DENTRO DE LA REUNION, ASI M ISMO SE DARA A CONOCER A LOS CANDIDATOS Y SE REALIZARA PEDAGOGIA ELECTORAL | K49: Afinidad | L49: AV. BOYACÁ # 35 — 25 SUR CARVAJAL (COSTADO OCCIDENTAL) | M49: https://maps.app.goo.gl/1KebB9j3ZXbtfCe99 | N49: 4.616396511798349, -74.14035717367963 | O49: Carvajal | P49: 30 | Q49: N/A
A50: SUR | B50: BOGOTA. D.C. - LOCALIDAD 8 KENNEDY | C50: Carvajal | D50: 10:00 AM | E50: TERRITORIO | F50: POLITICO COMUNITARIA | G50: Enero | H50: Viernes | I50: 46038 | J50: MT – AMERICAS OCCIDENTAL REDUCTORES DE VELOCIDAD | K50: 1. Se logró la intervención de la vía que tenía un deterioro por unos reductores de velocidad en plastico que estaba generando grietas en las casas. 2. Se esta gestionando una luminaria. | L50: Cruce entre la Calle 1 con Carrera 73B Bis | M50: https://maps.app.goo.gl/vSWMtHstraS7geEn8 | N50: 4.62369146930814, -74.14308836286854 | O50: Amercias Occidental | P50: 20 | Q50: FRANZ JAIR RODRIGUEZ MENDOZA 3005588503
A51: SUR | B51: BOGOTA. D.C. - LOCALIDAD 8 KENNEDY | C51: Carvajal | D51: 12:30 M | E51: ALMUERZO | F51: N/A | G51: Enero | H51: Viernes | I51: 46038 | J51: ALMUERZO | K51: ALMUERZO
A52: SUR | B52: BOGOTA. D.C. - LOCALIDAD 8 KENNEDY | C52: Carvajal | D52: 2:00 PM | E52: TERRITORIO | F52: POLITICO COMUNITARIA | G52: Enero | H52: Viernes | I52: 46038 | J52: MT - VILLA ALSACIA MALA DISPOSICIÓN DE RESIDUOS EN CANECAS METALICAS (6239) | K52: 1. Se realizó una jornada de embellecimiento para mititgar un punto critico | L52: Calle 10 #72A-20 | M52: https://maps.app.goo.gl/PySex4MEm2rvJmzp8 | N52: 4.641044868522982, -74.13599881970931 | O52: Castilla | P52: 20 | Q52: ANA EULALIA BECERRA RODRIGUEZ 3132151731
A53: SUR | B53: BOGOTA. D.C. - LOCALIDAD 8 KENNEDY | C53: Carvajal | D53: 4:00 PM | E53: TERRITORIO | F53: POLITICO COMUNITARIA | G53: Enero | H53: Viernes | I53: 46038 | J53: FERIA DE SERVICIOS | K53: Se realizo mesa de trabajo en cancha de castilla para tratar temas de seguridad, embellecimiento del parque y temas de basuras | L53: CRA 77#9-57 | M53: https://maps.app.goo.gl/KVJQYUw7kRwMkiRL7 | N53: 4.642127999972338, -74.13932701774873 | O53: CASTILLA | P53: 20 | Q53: MARIA LUISA ARIAS Y SERGIO OSORIO
A54: SUR | B54: BOGOTA. D.C. - LOCALIDAD 8 KENNEDY | C54: Carvajal | D54: 6:00 PM | E54: ALABANZA | F54: AFINIDAD | G54: Enero | H54: Viernes | I54: 46038 | J54: Actividad de afinidad - activación de líderes y referidos: REUNION CON LIDERES EN EL SEGUNDO PISO DE CARVAJAL, SE VA A INVITAR APROXIMADAMENTE 30 PERSONAS QUE AUN NO SE HAN ACTIVADO COMO LIDERES, QUE NO TIENE REFERIDOS, PARA REALIZAR ACTIVIDAD DENTRO DE LA REUNION, ASI M ISMO SE DARA A CONOCER A LOS CANDIDATOS Y SE REALIZARA PEDAGOGIA ELECTORAL | K54: Afinidad | L54: AV. BOYACÁ # 35 — 25 SUR CARVAJAL (COSTADO OCCIDENTAL) | M54: https://maps.app.goo.gl/1KebB9j3ZXbtfCe99 | N54: 4.616396511798349, -74.14035717367963 | O54: Carvajal | Q54: N/A
A55: SUR | B55: BOGOTA. D.C. - LOCALIDAD 8 KENNEDY | C55: Class | D55: 7:00 AM | E55: ALABANZA | F55: AFINIDAD | G55: Enero | H55: Viernes | I55: 46045 | J55: Actividad de afinidad - Microreunión activación de líderes y referidos | K55: Afinidad | L55: KR 80A # 56 35 SUR CLASS ROMA | M55: https://www.google.com/maps?q=4.614135243,-74.17617048 | N55: 4.614295606307947, -74.17625633511189 | O55: CLASS ROMA | Q55: N/A
A56: SUR | B56: BOGOTA. D.C. - LOCALIDAD 8 KENNEDY | C56: Class | D56: 10:00 AM | E56: TERRITORIO | F56: POLITICO COMUNITARIA | G56: Enero | H56: Viernes | I56: 46045 | J56: Reunión con familiares y referidos | K56: 1. Se esta gestionando la via, se encuentra en el banco de iniciativas de la ALK 2. Jornada de personalización de tarjeta tu llave | L56: Cl 58sur # 78j-10 | M56: https://maps.app.goo.gl/nn48M362V2t6aEPVA | N56: 4.607838431900593, -74.1753985093171 | O56: Villa de los Sauces | P56: 20 | Q56: LILIANA ANDREA TOCA SANCHEZ 3115822253
C57: Localidad | D57: 11:30 AM | E57: TERRITORIO | F57: POLITICO COMUNITARIA | G57: Enero | H57: Viernes | I57: 46045 | J57: Reunión empresario de corabastos | K57: Reunión empresario de corabastos: Fabio Andrés Cortes | L57: Av. Cdad. de Villavicencio #78n-04 78n-4 | M57: https://maps.app.goo.gl/ZnJBkzPBi2Kxv9p66 | N57: 4.617573360722535, -74.16373565415444 | O57: Kennedy | P57: 3 | Q57: Fabio Andrés Cortes 3178081946
A58: SUR | B58: BOGOTA. D.C. - LOCALIDAD 8 KENNEDY | C58: Class | D58: 12:30 M | E58: ALMUERZO | F58: AFINIDAD | G58: Enero | H58: Viernes | I58: 46045 | J58: ALMUERZO | K58: ALMUERZO | L58: Av. Cdad. de Villavicencio #78n-04 78n-4 | M58: https://maps.app.goo.gl/ZnJBkzPBi2Kxv9p66 | N58: 4.617573360722535, -74.16373565415444
A59: SUR | B59: BOGOTA. D.C. - LOCALIDAD 8 KENNEDY | C59: Localidad | D59: 2:00 PM | E59: TERRITORIO | F59: POLITICO COMUNITARIA | G59: Enero | H59: Viernes | I59: 46045 | J59: Actividad de Juventudes | K59: Actividad de Juventudes | L59: Av. Cdad. de Villavicencio #78n-04 78n-4 | M59: https://maps.app.goo.gl/ZnJBkzPBi2Kxv9p66 | N59: 4.617573360722535, -74.16373565415444 | O59: Kennedy | P59: 80 | Q59: Cristian Gomez
C60: Class | D60: 5:00 PM | E60: ALMUERZO | F60: POLITICO COMUNITARIA | G60: Enero | H60: Viernes | I60: 46045 | J60: Reunión con familiares y referidos | K60: Reunión con familiares y referidos | L60: Calle 53 sur # 81 h 06 urbanización el Carmelo manzana 2 | M60: https://maps.app.goo.gl/H8D8VUaLYi1yLTHx5 | N60: 4.620706011569686, -74.17642719761761 | O60: Carmelo | P60: 20 | Q60: Mary Mendez
A61: SUR | B61: BOGOTA. D.C. - LOCALIDAD 8 KENNEDY | C61: Class | D61: 7:00 PM | E61: TERRITORIO | F61: POLITICO COMUNITARIA | G61: Enero | H61: Viernes | I61: 46045 | J61: Reunión con familiares y referidos | K61: 1. Se logró crear la zona segura 2. Resalto Parabolico | L61: Cra 78b 57a 11 sur | M61: https://maps.app.goo.gl/jFjERfhfKHaf2x9d7 | N61: 4.608147230641861, -74.17265049548041 | O61: Roma IV | P61: 25 | Q61: MIGUEL MOJICA (líder externo)
A62: SUR | B62: BOGOTA. D.C. - LOCALIDAD 8 KENNEDY | C62: Class | D62: 7:00 AM | E62: ALABANZA | F62: AFINIDAD | G62: Enero | H62: Jueves | I62: 46051 | J62: Actividad de afinidad - Microreunión activación de líderes y referidos | K62: Afinidad | L62: KR 80A # 56 35 SUR CLASS ROMA | M62: https://www.google.com/maps?q=4.614135243,-74.17617048 | N62: 4.614295606307947, -74.17625633511189 | O62: CLASS ROMA | Q62: N/A
A63: SUR | B63: BOGOTA. D.C. - LOCALIDAD 8 KENNEDY | C63: Class | D63: 10:00 AM | E63: TERRITORIO | F63: POLITICO COMUNITARIA | G63: Enero | H63: Jueves | I63: 46051 | J63: Reunión con empresario de jeans | L63: Calle 54c Sur #81g-75 segundo piso | M63: https://maps.app.goo.gl/t1EZ8Ds19F9NQ2FZ7 | N63: 4.6193644171812815, -74.17833044658433 | O63: Villa zarzamora | P63: 20 | Q63: Ricardo Gutiérrez
A64: SUR | B64: BOGOTA. D.C. - LOCALIDAD 8 KENNEDY | C64: Class | D64: 12:00 M | E64: ALMUERZO | F64: N/A | G64: Enero | H64: Jueves | I64: 46051 | J64: ALMUERZO | K64: ALMUERZO
A65: SUR | B65: BOGOTA. D.C. - LOCALIDAD 8 KENNEDY | C65: Carvajal | D65: 2:00 PM | E65: TERRITORIO | F65: POLITICO COMUNITARIA | G65: Enero | H65: Jueves | I65: 46051 | J65: Visita empresa JJD world logistic sas | K65: Visita a empresarios | L65: Av cra 80 # 10 D 15 | M65: https://maps.app.goo.gl/JSxrPgzNoZP8dazP6 | N65: 4.646747173213774, -74.14127981799767 | O65: Lagos de Castilla | P65: 10 | Q65: John Jairo Díaz 3227864558
A66: SUR | B66: BOGOTA. D.C. - LOCALIDAD 8 KENNEDY | C66: Localidad | D66: 0.64583333 | E66: TERRITORIO | F66: POLITICO COMUNITARIA | G66: Enero | H66: Jueves | I66: 46051 | J66: Visita empresa Pastelería Cikoloto | K66: Visita a empresarios | L66: Calle 8 sur #70-61 | M66: https://maps.app.goo.gl/8XDAgEpW3qmTAY6o8 | N66: 4.617694311523241, -74.13265038891345 | O66: Americas | P66: 3 | Q66: Rocio Aranzalez
C67: Localidad | D67: 0.66666667 | E67: TERRITORIO | F67: POLITICO COMUNITARIA | G67: Enero | H67: Jueves | I67: 46051 | J67: Recorrido comerciantes: Carrera 70 b # 2 a 30 pet shop Avenida calle 3 # 71a 10 ferretería Calle 3 # 71-26 minimercado San Mateo | K67: Visita a comerciantes | L67: Carrera 70 b # 2 a 30 pet shop | M67: https://maps.app.goo.gl/WVMzAxVeqE5J4Yyo6 | N67: 4.624319497943808, -74.13238940425539 | O67: Techo | P67: 3 | Q67: Rocio Aranzalez
C68: Localidad | D68: 0.70833333 | E68: TERRITORIO | F68: POLITICO COMUNITARIA | G68: Enero | H68: Jueves | I68: 46051 | J68: Reunión de campaña | K68: Familia y vecinos de la líder | L68: K71#2a-66 portales de techo 3 | M68: https://maps.app.goo.gl/d1vwx5sg4Fe3bHqr9 | N68: 4.625148355052766, -74.13321287541976 | O68: Techo | P68: 15 | Q68: Rocio Aranzalez
A69: SUR | B69: BOGOTA. D.C. - LOCALIDAD 8 KENNEDY | C69: Class | D69: 6:30 PM | E69: ALABANZA | F69: AFINIDAD | G69: Enero | H69: Jueves | I69: 46051 | J69: Actividad de afinidad - Microreunión activación de líderes y referidos | K69: Afinidad | L69: KR 80A # 56 35 SUR CLASS ROMA | M69: https://www.google.com/maps?q=4.614135243,-74.17617048 | N69: 4.614295606307947, -74.17625633511189 | O69: CLASS ROMA | Q69: N/A
A70: SUR | B70: BOGOTA. D.C. - LOCALIDAD 8 KENNEDY | C70: Patio Bonito | D70: 7:00 AM | E70: ALABANZA | F70: AFINIDAD | G70: Enero | H70: Viernes | I70: 46052 | J70: Actividad de afinidad - Microreunión activación de líderes y referidos | K70: Afinidad | L70: Cra 95A #39 SUR NO.38C | M70: 4.646227879789345, -74.17302253463195 | N70: https://maps.app.goo.gl/aGBx2P51EGsbTbt19 | O70: Patio Bonito | Q70: Hamilton Liz (3125621911)
A71: SUR | B71: BOGOTA. D.C. - LOCALIDAD 8 KENNEDY | C71: Patio Bonito | D71: 11:00 AM | E71: TERRITORIO | F71: POLITICO COMUNITARIA | G71: Enero | H71: Viernes | I71: 46052 | J71: Recorrido con vecinos y comerciantes | K71: Compartir ley de micronegocios | L71: Cl. 26 Sur CAI Patio Bonito | M71: https://maps.app.goo.gl/1rW3gNnmxuUEsaT56 | N71: 4.639081957557648, -74.16072218742319 | O71: Patio Bonito | P71: 20 | Q71: Mary Preciado
A72: SUR | B72: BOGOTA. D.C. - LOCALIDAD 8 KENNEDY | C72: Patio Bonito | D72: 12:00 M | E72: ALMUERZO | F72: N/A | G72: Enero | H72: Viernes | I72: 46052 | J72: ALMUERZO | K72: ALMUERZO
A73: SUR | B73: BOGOTA. D.C. - LOCALIDAD 8 KENNEDY | C73: Patio Bonito | D73: 2:00 PM | E73: TERRITORIO | F73: POLITICO COMUNITARIA | G73: Enero | H73: Viernes | I73: 46052 | J73: MT - CIUDAD GRANADA FERIA DE EMPLEO (3672) + MT - CIUDAD GRANADA JORNADA DE OPAM (3300) | K73: 1. Feria de empleo, se beneficiaron cerca de 15 personas 2. Jornada de bienestar y salud animal | L73: carrera 92 # 40a sur - 16 | M73: https://www.google.com/maps/place/Sal%C3%B3n+comunal+barrio+ciudad+granada/@4.6420065,-74.1720249,3a,75y,72.47h,80.3t/data=!3m7!1e1!3m5!1sRBbyxs1JKhMDCNWVVWGwJw!2e0!6shttps:%2F%2Fstreetviewpixels-pa.googleapis.com%2Fv1%2Fthumbnail%3Fcb_client%3Dmaps_sv.tactile%26w%3D900%26h%3D600%26pitch%3D9.69712405910603%26panoid%3DRBbyxs1JKhMDCNWVVWGwJw%26yaw%3D72.46767932186751!7i16384!8i8192!4m6!3m5!1s0x8e3f9dcb60b081ef:0x7b579bf0f00710f4!8m2!3d4.6433739!4d-74.1717385!16s%2Fg%2F11d_wwmg4k?entry=ttu&g_ep=EgoyMDI2MDEyMS4wIKXMDSoASAFQAw%3D%3D | N73: 4.641935589580969, -74.17199601687463 | O73: Ciudad Granada | P73: 20 | Q73: Isaura Porras
A74: SUR | B74: BOGOTA. D.C. - LOCALIDAD 8 KENNEDY | C74: Patio Bonito | D74: 4:00 PM | E74: TERRITORIO | F74: POLITICO COMUNITARIA | G74: Enero | H74: Viernes | I74: 46052 | J74: MT - UNIR 1 PARQUE (2763) | K74: 1. El operador "Mi Bus" realiza acciones para mitigar le ruido del taller. 2. SDIS realiza la respectiva gestión con la tropa social, indica que no se encontró algún habitante de calle en la zona. Adjunto acta del recorrido. 3. Se logra el mantenimiento de la tapa de EAAB. 4. Se logra jornada de salud animal gratuita, beneficiando a 50 animales de compañía | L74: Cl. 34 Bis Sur #90C-41 | M74: https://maps.app.goo.gl/QCEJXrLWdmR4Tz8x6 | N74: 4.643977838589568, -74.16696084276202 | O74: Unir 1 | P74: 25 | Q74: MARIA HERMENCIA SANCHEZ CASTRO 3212923898
A75: SUR | B75: BOGOTA. D.C. - LOCALIDAD 8 KENNEDY | C75: Patio Bonito | D75: 6:00 PM | E75: ALABANZA | F75: AFINIDAD | G75: Enero | H75: Viernes | I75: 46052 | J75: Actividad de afinidad - Microreunión activación de líderes y referidos | K75: Afinidad | L75: Cra 95A #39 SUR NO.38C | M75: 4.646227879789345, -74.17302253463195 | N75: https://maps.app.goo.gl/aGBx2P51EGsbTbt19 | O75: Patio Bonito | Q75: Hamilton Liz (3125621911)
A76: SUR | B76: BOGOTA. D.C. - LOCALIDAD 8 KENNEDY | C76: Kennedy Central | D76: 9:00 AM | E76: TERRITORIO | F76: POLITICO COMUNITARIA | G76: Enero | H76: Sábado | I76: 46053 | J76: MT - SINAI MALLA VIAL DETERIORADA FABRICA RECICLAJE Y SALÓN (2011) + MT - SINAÍ PARQUE TRANSMILENIO Y EXCRETAS (1788) | K76: 1. SE REALIZÓ JORNADA DE PERSONALIZACIÓN DE TARJETAS 2. Se realizó una jornada de bienestar y salud animal con OPAM 3. Se realizó una jornada de sensibilización de excretas | L76: Traversal 78n con calle 43f rente a la bomba de gasolina a un lado del piquetiadero Don Jorge | M76: https://maps.app.goo.gl/XuwCLhnDQbtb4r8U7 | N76: 4.615687256292251, -74.16462957726137 | O76: Sinaí | P76: 20 | Q76: DAIRO GARCIA CALDERON 3196422287
A77: SUR | B77: BOGOTA. D.C. - LOCALIDAD 8 KENNEDY | C77: Kennedy Central | D77: 10:30 AM | E77: TERRITORIO | F77: POLITICO COMUNITARIA | G77: Enero | H77: Sábado | I77: 46053 | J77: Reunión de campaña | K77: Familia y vecinos de la líder | L77: Calle 44B sur #73c17 | M77: https://maps.app.goo.gl/mua9Z8ES2D4hQGwT8 | N77: 4.60802119604895, -74.15991591959741 | O77: Lago Timiza | P77: 15 | Q77: Claudia Nieto 3102215612
A78: SUR | B78: BOGOTA. D.C. - LOCALIDAD 8 KENNEDY | C78: Kennedy Central | D78: 12:00 M | E78: ALMUERZO | F78: N/A | G78: Enero | H78: Sábado | I78: 46053 | J78: ALMUERZO ALMUERZO | K78: ALMUERZO ALMUERZO | R78: Kennedy Central
A79: SUR | B79: BOGOTA. D.C. - LOCALIDAD 8 KENNEDY | C79: Kennedy Central | D79: 2:30 PM | E79: TERRITORIO | F79: AFINIDAD | G79: Enero | H79: Sábado | I79: 46053 | J79: Reunion de identidad y convicción | K79: Afinidad | L79: AV CR 80 NO 42C 83 SUR KENNEDY | M79: https://maps.app.goo.gl/UiBexu9Axhn6zuEZ6 | N79: 4.621764992515213, -74.16489171361977 | O79: Los Olivos | P79: 400
A80: SUR | B80: BOGOTA. D.C. - LOCALIDAD 8 KENNEDY | C80: Kennedy Central | D80: 5:30 PM | E80: TERRITORIO | F80: POLITICO COMUNITARIA | G80: Enero | H80: Sábado | I80: 46053 | J80: MT - CASABLANCA ANDENES Y PARADERO SITP (4620) | K80: 1. Se logró la intervención del paradero del SITP que se encontraba en malas condiciones 2. Se logró jornada de personalización de Tu Llave 3. Se logró una jornada de bienestar y salud animal con OPAM | L80: Cl. 47b Sur #15 Salón Social Casablanca etapa 1 detrás del centro comercial de Casablanca | M80: https://maps.app.goo.gl/MMSyTqmrbFrsqDpW7 | N80: 4.617411979584148, -74.16745234381071 | O80: Casablanca | P80: 30 | Q80: - TERESA DE JESUS PORTELA GRISALES 3153137308 - LILIANA SICACHÁ - LUIS MOYA
A81: SUR | B81: BOGOTA. D.C. - LOCALIDAD 8 KENNEDY | C81: Kennedy Central | D81: 7:00 AM | E81: ESTUDIO BIBLICO | F81: AFINIDAD | G81: Febrero | H81: Martes | I81: 46063 | J81: Actividad de afinidad - Microreunión activación de líderes y referidos | K81: Afinidad | L81: Cra. 80 #42C-83 SUR | M81: https://www.google.com/maps/place/Iglesia+de+Dios+Ministerial+de+Jesucristo+Internacional+-+IDMJI+-+CGMJI+BTA+EL+OLIVO/@4.6215697,-74.1649254,3a,75y,316.96h,90t/data=!3m7!1e1!3m5!1sJwIftdN6Rl-LMLqtdi_3Nw!2e0!6shttps:%2F%2Fstreetviewpixels-pa.googleapis.com%2Fv1%2Fthumbnail%3Fcb_client%3Dmaps_sv.tactile%26w%3D900%26h%3D600%26pitch%3D0%26panoid%3DJwIftdN6Rl-LMLqtdi_3Nw%26yaw%3D316.9615!7i16384!8i8192!4m10!1m2!2m1!1sidmji+kennedy!3m6!1s0x8e3f9e842a6a8335:0xe8f39c19a9ab6da3!8m2!3d4.6216536!4d-74.1650013!15sCg1pZG1qaSBrZW5uZWR5IgOIAQGSARBjaHJpc3RpYW5fY2h1cmNo4AEA!16s%2Fg%2F1tdksvtw?entry=ttu&g_ep=EgoyMDI2MDEyOC4wIKXMDSoASAFQAw%3D%3D | N81: 4.623059676758325, -74.16483460364921 | O81: Kennedy | P81: N/A
A82: SUR | B82: BOGOTA. D.C. - LOCALIDAD 8 KENNEDY | C82: Kennedy Central | D82: 2:00 PM | E82: TERRITORIO | F82: POLITICO COMUNITARIA | G82: Febrero | H82: Martes | I82: 46063 | J82: Reunión referidos líder Ana Elsy Ibarra | K82: Mesas de trabajo de manejo de excretas anímales por problemática en el sector | L82: Calle 42 a sur # 21 | M82: https://maps.app.goo.gl/xPBZcKwAEYCeuHnb9 | N82: 4.638962500694809, -74.17299220425517 | O82: Dindalito | P82: 20 | Q82: Ana Elcy
C83: Localidad | D83: 3:30 PM | E83: TERRITORIO | F83: LIBERTAD RELIGIOSA | G83: Febrero | H83: Martes | I83: 46063 | J83: Reunión líderes Sector Religioso | K83: Gestión en libertad religiosa | L83: Av. Cdad. de Villavicencio #78n-04 78n-4 | M83: https://www.google.com/maps/place/Restaurante+y+Piqueteadero+Don+Jorge/@4.6174935,-74.1638475,3a,75y,70.5h,90t/data=!3m7!1e1!3m5!1sA-86IPQE2qnpsRBlxjE1rA!2e0!6shttps:%2F%2Fstreetviewpixels-pa.googleapis.com%2Fv1%2Fthumbnail%3Fcb_client%3Dmaps_sv.tactile%26w%3D900%26h%3D600%26pitch%3D0%26panoid%3DA-86IPQE2qnpsRBlxjE1rA%26yaw%3D70.49593!7i16384!8i8192!4m14!1m7!3m6!1s0x8e3f9e8f3f9f6d89:0xa4f20f88ccc7423c!2sRestaurante+y+Piqueteadero+Don+Jorge!8m2!3d4.617527!4d-74.1637425!16s%2Fg%2F1q5bnjdf6!3m5!1s0x8e3f9e8f3f9f6d89:0xa4f20f88ccc7423c!8m2!3d4.617527!4d-74.1637425!16s%2Fg%2F1q5bnjdf6?entry=ttu&g_ep=EgoyMDI2MDEyOC4wIKXMDSoASAFQAw%3D%3D | N83: 4.61776225166584, -74.16374252528091 | O83: Kennedy | P83: 20 | Q83: Lorena Garzón
A84: SUR | B84: BOGOTA. D.C. - LOCALIDAD 8 KENNEDY | C84: Kennedy Central | D84: 5:00 PM | E84: ESTUDIO BIBLICO | F84: AFINIDAD | G84: Febrero | H84: Martes | I84: 46063 | J84: Actividad de afinidad - Microreunión activación de líderes y referidos | K84: Afinidad | L84: Cra. 80 #42C-83 SUR | M84: Iglesia de Dios Ministerial de Jesucristo Internacional - IDMJI - CGMJI BTA EL OLIVO | N84: 4.623059676758325, -74.16483460364921 | O84: Kennedy | P84: N/A | R84: Kennedy Central
A85: SUR | B85: BOGOTA. D.C. - LOCALIDAD 8 KENNEDY | C85: Carvajal | D85: 7:00 AM | E85: ENSEÑANZA | F85: AFINIDAD | G85: Febrero | H85: Miércoles | I85: 46064 | J85: REUNION CON LIDERES EN EL SEGUNDO PISO DE CARVAJAL, SE VA A INVITAR APROXIMADAMENTE 30 PERSONAS QUE AUN NO SE HAN ACTIVADO COMO LIDERES, QUE NO TIENE REFERIDOS, PARA REALIZAR ACTIVIDAD DENTRO DE LA REUNION, ASI M ISMO SE DARA A CONOCER A LOS CANDIDATOS Y SE REALIZARA PEDAGOGIA ELECTORAL | K85: Afinidad | L85: AV. BOYACÁ # 35 — 25 SUR CARVAJAL (COSTADO OCCIDENTAL) | M85: https://maps.app.goo.gl/1KebB9j3ZXbtfCe99 | N85: 4.616396511798349, -74.14035717367963 | O85: Carvajal | P85: N/A | Q85: N/A
A86: SUR | B86: BOGOTA. D.C. - LOCALIDAD 8 KENNEDY | C86: Carvajal | D86: 2:30 PM | E86: TERRITORIO | F86: POLITICO COMUNITARIA | G86: Febrero | H86: Miércoles | I86: 46064 | J86: Turismauro - visita empleados | K86: Visita a empresarios | L86: Av. de las Américas #73 - 67 | M86: https://maps.app.goo.gl/cB7JaP7nsRn5M2kH7 | N86: 4.630632984407078, -74.14150494162887 | O86: Mandalay | P86: 15 | Q86: Sebastian Angel
A87: SUR | B87: BOGOTA. D.C. - LOCALIDAD 8 KENNEDY | C87: Carvajal | D87: 4:00 PM | E87: TERRITORIO | F87: POLITICO COMUNITARIA | G87: Febrero | H87: Miércoles | I87: 46064 | J87: MT - LUCERNA PROVIVIENDA OCCIDENTAL HUECO EN LA VIA CIV 8008866 (3271) | K87: 1. Se logró el arrrglo de un hueco por una mala coxion de las redes de alcantarillado | L87: CALLE 38 A #72K - 27 | M87: https://maps.app.goo.gl/aSmy6cu3dtProg2x9 | N87: 4.612541218524758, -74.14481479087371 | O87: Lucerna | P87: 30 | Q87: Silvia Cabuya
A88: SUR | B88: BOGOTA. D.C. - LOCALIDAD 8 KENNEDY | C88: Carvajal | D88: 6:00 PM | E88: ENSEÑANZA | F88: AFINIDAD | G88: Febrero | H88: Miércoles | I88: 46064 | J88: REUNION CON LIDERES EN EL SEGUNDO PISO DE CARVAJAL, SE VA A INVITAR APROXIMADAMENTE 30 PERSONAS QUE AUN NO SE HAN ACTIVADO COMO LIDERES, QUE NO TIENE REFERIDOS, PARA REALIZAR ACTIVIDAD DENTRO DE LA REUNION, ASI M ISMO SE DARA A CONOCER A LOS CANDIDATOS Y SE REALIZARA PEDAGOGIA ELECTORAL | K88: Afinidad | L88: AV. BOYACÁ # 35 — 25 SUR CARVAJAL (COSTADO OCCIDENTAL) | M88: https://maps.app.goo.gl/1KebB9j3ZXbtfCe99 | N88: 4.616396511798349, -74.14035717367963 | O88: Carvajal | P88: N/A | Q88: N/A
C89: Localidad | D89: 0.27083333 | E89: TERRITORIO | F89: POLITICO COMUNITARIA | G89: Febrero | H89: Miércoles | I89: 46071 | J89: REPROGRAMAR LA ACTIVIDAD DE CORABASTOS | P89: 50
A90: SUR | B90: BOGOTA. D.C. - LOCALIDAD 8 KENNEDY | C90: Patio Bonito | D90: 2:30 PM | E90: TERRITORIO | F90: POLITICO COMUNITARIA | G90: Febrero | H90: Miércoles | I90: 46071 | J90: MT - TINTALITO PUNTO DE ARROJO (3691) | K90: 1. Se realiza intervención con jornada de embellecimiento para mitigar el punto critico, con el apoyo de la Alcaldía Local de Kennedy. | L90: Carrera 88 #42 f -28 sur | M90: https://maps.app.goo.gl/1MEcLnm21ZnJyyPQ7 | N90: 4.6340966883902395, -74.17175924765361 | O90: Tintalito | P90: 25 | Q90: MERCEDES LAVERDE 3208267021
A91: SUR | B91: BOGOTA. D.C. - LOCALIDAD 8 KENNEDY | C91: Patio Bonito | D91: 4:00 PM | E91: TERRITORIO | F91: POLITICO COMUNITARIA | G91: Febrero | H91: Miércoles | I91: 46071 | J91: Reunión Corabastos | L91: Av. Cdad. de Villavicencio #78n-04 78n-4 | M91: https://maps.app.goo.gl/ZnJBkzPBi2Kxv9p66 | N91: 4.617573360722535, -74.16373565415444 | P91: 25
A92: SUR | B92: BOGOTA. D.C. - LOCALIDAD 8 KENNEDY | C92: Patio Bonito | D92: 6:00 PM | E92: ENSEÑANZA | F92: AFINIDAD | G92: Febrero | H92: Miércoles | I92: 46071 | J92: Actividad de afinidad - Microreunión activación de líderes y referidos | P92: N/A
A93: SUR | B93: BOGOTA. D.C. - LOCALIDAD 8 KENNEDY | C93: Carvajal | D93: 7:00 AM | E93: ALABANZA | F93: AFINIDAD | G93: febrero | H93: Martes | I93: 46070 | J93: Actividad de afinidad - activación de líderes y referidos: REUNION CON LIDERES EN EL SEGUNDO PISO DE CARVAJAL, SE VA A INVITAR APROXIMADAMENTE 30 PERSONAS QUE AUN NO SE HAN ACTIVADO COMO LIDERES, QUE NO TIENE REFERIDOS, PARA REALIZAR ACTIVIDAD DENTRO DE LA REUNION, ASI M ISMO SE DARA A CONOCER A LOS CANDIDATOS Y SE REALIZARA PEDAGOGIA ELECTORAL | K93: Afinidad | L93: AV. BOYACÁ # 35 — 25 SUR CARVAJAL (COSTADO OCCIDENTAL) | M93: https://maps.app.goo.gl/1KebB9j3ZXbtfCe99 | N93: 4.616396511798349, -74.14035717367963 | O93: Carvajal | P93: N/A | Q93: N/A
A94: SUR | B94: BOGOTA. D.C. - LOCALIDAD 8 KENNEDY | C94: Carvajal | D94: 10:00 AM | E94: TERRITORIO | F94: POLITICO COMUNITARIA | G94: febrero | H94: Martes | I94: 46070 | J94: Reunion empresa Industrias Fagor | K94: Reunion empresa Industrias Fagor | L94: Cl. 17 # 68D-37 | M94: https://maps.app.goo.gl/FvPfN3pEXvNrxZ418 | N94: 4.64333674677587, -74.12046455911158 | O94: Carvajal | P94: 40 | Q94: Wilson Gonzalez (3142772157
A95: SUR | B95: BOGOTA. D.C. - LOCALIDAD 8 KENNEDY | C95: Carvajal | D95: 12:00 M | E95: ALMUERZO | F95: N/A | G95: febrero | H95: Martes | I95: 46070 | J95: ALMUERZO | K95: ALMUERZO | P95: N/A
A96: SUR | B96: BOGOTA. D.C. - LOCALIDAD 8 KENNEDY | C96: Carvajal | D96: 2:00 PM | E96: TERRITORIO | F96: POLITICO COMUNITARIA | G96: febrero | H96: Martes | I96: 46070 | J96: Recorrido negocios Carolina | K96: Reunion con micro empresarios del teritorio | L96: CRA 72J #48A-05 SUR ( BARRIO BOITA) | M96: https://n9.cl/b6mjt | N96: 4.6026756513418094, -74.15159897573301 | O96: BOITA | P96: 20 | Q96: Carolina montañez y sandra montañez( 3134235526)
A97: SUR | B97: BOGOTA. D.C. - LOCALIDAD 8 KENNEDY | C97: Carvajal | D97: 4:00 PM | E97: TERRITORIO | F97: POLITICO COMUNITARIA | G97: febrero | H97: Martes | I97: 46070 | J97: Reunión con familia y vecinos | K97: Reunión con familia y vecinos | L97: CRA 79G #13-46 BARRIO VISION DE COLOMBIA | M97: https://n9.cl/xmofw | N97: 4.652583589262143, -74.13565376906922 | O97: BARRIO VISION COLOMBIA | P97: 20 | Q97: Betzabe Soto ‪3134295319‬
A98: SUR | B98: BOGOTA. D.C. - LOCALIDAD 8 KENNEDY | C98: Carvajal | D98: 6:00 PM | E98: ALABANZA | F98: AFINIDAD | G98: febrero | H98: Martes | I98: 46070 | J98: Actividad de afinidad - activación de líderes y referidos: REUNION CON LIDERES EN EL SEGUNDO PISO DE CARVAJAL, SE VA A INVITAR APROXIMADAMENTE 30 PERSONAS QUE AUN NO SE HAN ACTIVADO COMO LIDERES, QUE NO TIENE REFERIDOS, PARA REALIZAR ACTIVIDAD DENTRO DE LA REUNION, ASI M ISMO SE DARA A CONOCER A LOS CANDIDATOS Y SE REALIZARA PEDAGOGIA ELECTORAL | K98: Afinidad | L98: AV. BOYACÁ # 35 — 25 SUR CARVAJAL (COSTADO OCCIDENTAL) | M98: https://maps.app.goo.gl/1KebB9j3ZXbtfCe99 | N98: 4.616396511798349, -74.14035717367963 | O98: Carvajal | P98: N/A | Q98: N/A
C99: Kennedy Central | D99: 7:00 AM | E99: ENSEÑANZA | F99: AFINIDAD | G99: febrero | H99: Jueves | I99: 46079 | J99: Actividad de afinidad - Microreunión activación de líderes y referidos | P99: N/A
C100: Kennedy Central | D100: 11:00 AM | E100: TERRITORIO | F100: POLITICO COMUNITARIA | G100: Febrero | H100: Jueves | I100: 46079 | J100: Recorrido comerciantes Britalia | K100: 1. Se logró socializar la oferta para micronegocios por parte de la ALK 2. Se hicieron dos jornadas de control de vectores en mayo y agosto, y se programó una tercera en noviembre. | L100: Cl. 46 Sur #81H-02 | M100: https://www.google.com/maps/place/CAI+Britalia/@4.6211355,-74.1690507,3a,75y,218.9h,90t/data=!3m7!1e1!3m5!1szw4On_LJNelxB2pAe1nXtw!2e0!6shttps:%2F%2Fstreetviewpixels-pa.googleapis.com%2Fv1%2Fthumbnail%3Fcb_client%3Dmaps_sv.tactile%26w%3D900%26h%3D600%26pitch%3D0%26panoid%3Dzw4On_LJNelxB2pAe1nXtw%26yaw%3D218.89775!7i13312!8i6656!4m14!1m7!3m6!1s0x8e3f9e7e08282575:0xfd33c97a6ca0ed32!2sCAI+Britalia!8m2!3d4.6210238!4d-74.16914!16s%2Fg%2F1tfyfmg8!3m5!1s0x8e3f9e7e08282575:0xfd33c97a6ca0ed32!8m2!3d4.6210238!4d-74.16914!16s%2Fg%2F1tfyfmg8?entry=ttu&g_ep=EgoyMDI2MDEyOC4wIKXMDSoASAFQAw%3D%3D | N100: 4.621355308060035, -74.16916146162264 | O100: Britalia | P100: 30 | Q100: NILCE SALGADO CALVO 3202012650 CLARA MERCEDES LUMPAQUE ESTRADA 3058167240
...

Sheet Hoja 28
A1: AÑO | B1: COD MES | C1: MES INICIO | D1: CÓDIGO SEGUIMIENTO | E1: TIPO DE ACTIVIDAD | F1: TEMA | G1: SUBTEMA | H1: DESCRIPCIÓN Y/O ACTIVIDAD | I1: ENTIDADES | J1: BARRIO | K1: ZONA | L1: LOCALIDAD | M1: IGLESIA | N1: COORDENADAS - IGLESIA | O1: TIPO DE GESTIÓN | P1: NOMBRE DEL BENEFICIARIO Y/O LÍDER | Q1: GÉNERO | R1: CÉDULA | S1: DIRECCIÓN DEL BARRIO | T1: COORDENADAS DE LA REUNIÓN/ GESTIÓN | U1: CORREO | V1: TELEFONO | W1: PRIORIZACIÓN | X1: BENEFICIADO | Y1: ESTADO ACTUAL DEL TRÁMITE | Z1: RESULTADOS DE LA GESTIÓN | AA1: OBSERVACIONES | AB1: FECHA DE INICIO | AC1: FECHA DE CIERRE | AD1: ENCARGADO | AE1: NOMBRE DEL ASESOR ENCARGADO| | AF1: CIUDAD | AG1: DEPARTAMENTO | AH1: LINK DE EVIDENCIA | AI1: SEMANA | AJ1: CONTACTADO POR AFINIDAD
A2: 2024 | B2: 1 | C2: Enero | D2: 202400007 | E2: Apoyo Ciudadano | F2: Salud | G2: Citas médicas | H2: Requerimiento cita neumología pediátrica Datos clínicos de importancia Asma infantil crónica. | I2: Secretaría Distrital de Salud | J2: Castilla | K2: Sur | L2: 08.Kennedy | M2: N/A | N2: =BUSCARX(R[0]C[-1],CONVENCIONES!R12C1:R42C1,CONVENCIONES!R12C2:R42C2) -> #ERROR! | O2: Gestión 2024 | P2: Lian Samuel Victoria Sánchez | Q2: Hombre | R2: 1145933937 | S2: Calle 10b # 81f-92 | T2: 4.650055904649422, -74.14550204826222 | U2: jaime.victoria2671@correo.policia.gov.co | V2: 3143946191 | W2: Tramites | X2: Interno | Y2: Finalizado | Z2: Positivo | AA2: N/A | AB2: 45314 | AC2: N/A | AD2: Asesor | AE2: Angie Benitez | AF2: Bogotá | AG2: Cundinamarca | AH2: 202400007_Lian Samuel Victoria Sánchez | AJ2: NO
A3: 2024 | B3: 1 | C3: Enero | D3: 202400025 | E3: Apoyo Ciudadano | F3: Educación | H3: Cupo estudiantil a menor migrante venezolana | I3: Secretaría de Educación del Distrito | J3: Andalucia 1er sector | K3: Sur | L3: 08.Kennedy | M3: N/A | N3: =BUSCARX(R[0]C[-1],CONVENCIONES!R12C1:R42C1,CONVENCIONES!R12C2:R42C2) -> #ERROR! | O3: Gestión 2024 | P3: Nombres del estudiante: Daniela Stefani Guzamana Mendez Pasaporte: 172513001 Correo: tovaryuliath@gmail.com Grado: Décimo Acudiente Nombres: Yuliath Celiana Tovar Guzamana PPT: 7109640 Correo: tovaryuliath@gmail.com Contacto: 3213646592 Líder que hizo la solicitud: Antonio Castaño Celular: 3178294782 | Q3: Mujer | R3: 7109640 | S3: N/A | T3: 4.65544903829502, -74.13812385348416 | U3: tovaryuliath@gmail.com Correo: tovaryuliath@gmail.com | V3: Contacto: 3213646592 | W3: Tramites | X3: Externos | Y3: Finalizado | Z3: Positivo | AA3: N/A | AB3: 41668 | AC3: N/A | AD3: Asesor | AE3: Angie Benitez | AF3: Bogotá | AG3: Cundinamarca | AH3: 202400025_Yuliath Celiana Tovar Guzamana | AJ3: NO
A4: 2024 | B4: 2 | C4: Febrero | D4: 202400038 | E4: Apoyo Ciudadano | F4: Educación | G4: cupo escolar | H4: Maritza Lopez Castañeda, solicita ayuda con un cupo Estudiantil | I4: Secretaría de Educación del Distrito | J4: Kennedy | K4: Sur | L4: 08.Kennedy | M4: 08.Kennedy Central | N4: =BUSCARX(R[0]C[-1],CONVENCIONES!R12C1:R42C1,CONVENCIONES!R12C2:R42C2) -> #ERROR! | O4: Gestión 2024 | P4: Maritza Lopez Castañeda | Q4: Mujer | R4: 1028785887 | S4: N/A | T4: N/A | U4: maritzalopez2808@gmail.com | V4: 3226438335 | W4: Tramites | X4: Interno | Y4: Finalizado | Z4: Positivo | AA4: El enlace nos colabora con el cupo escolar en el colegio jornada tarde, pero la acudiente no acepto y prefirió continuar en el mismo colegio. | AB4: 45330 | AC4: 44966 | AD4: Asesor | AE4: Katherine Galindo | AF4: Bogotá | AG4: Cundinamarca | AH4: Maritza López Castañeda | AJ4: NO
A5: 2024 | B5: 2 | C5: Febrero | D5: 202400079 | E5: Apoyo Ciudadano | F5: Salud | G5: Procedimientos y exámenes | H5: Solicitud: verificación diagnóstico y tratamiento a realizar ya que el primer concepto indican que no le harán tratamiento Diagnóstico: cáncer de hígado (no conocen que tipo de cáncer, solo hicieron una biopsia y no pudieron identificar el cáncer). Tiempo de solicitud: lleva 2 meses en la clínica sin respuesta | I5: Superintendencia de Salud | J5: Roma | K5: Sur | L5: 08.Kennedy | M5: 08.Class | N5: =BUSCARX(R[0]C[-1],CONVENCIONES!R12C1:R42C1,CONVENCIONES!R12C2:R42C2) -> #ERROR! | O5: Gestión 2024 | P5: Gerardo Ávila | Q5: Hombre | R5: 4894006 | S5: calle 56a sur # 78 N 48 manzana 44 interior 1 apto 101 | T5: 4.6131323776124855, -74.17500280572317 | U5: N/A | V5: Falleció la persona. | W5: Tramites | X5: Interno | Y5: Finalizado | Z5: N/A | AA5: Falleció la persona. | AB5: 45351 | AC5: N/A | AD5: Asesor | AE5: Angie Benitez | AF5: Bogotá | AG5: Cundinamarca | AH5: 202400079_Gerardo Ávila | AJ5: NO
A6: 2024 | B6: 3 | C6: Marzo | D6: 202400082 | E6: Apoyo Ciudadano | F6: Salud | H6: La familia de un adulto mayor con discapacidad solicita apoyo ya que se encuentra delicado de salud y solicitan ayuda para ingresarlo en un geratrico donde lo puedan cuidar. | I6: Secretaría Distrital de Integración Social | J6: Patio Bonito | K6: Sur | L6: 08.Kennedy | M6: 08.Patio Bonito | N6: =BUSCARX(R[0]C[-1],CONVENCIONES!R12C1:R42C1,CONVENCIONES!R12C2:R42C2) -> #ERROR! | O6: Gestión 2024 | P6: Gildardo Ayala | Q6: Hombre | R6: 5947933 | S6: N/A | T6: 4.638160202192498, -74.16295192449837 | U6: N/A | V6: 3104781799 | W6: Tramites | X6: Interno | Y6: Finalizado | Z6: Negativo | AA6: No se le puede brindar algún tipo de apoyo ya que la persona no se encuentra en Bogotá | AB6: 45352 | AC6: =DIA.LAB(R[0]C[-1],15) -> #ERROR! | AD6: Asesor | AE6: Fernando Zamora | AF6: Bogotá | AG6: Cundinamarca | AH6: 202400082_Gildardo Ayala | AJ6: NO
A7: 2024 | B7: 3 | C7: Marzo | D7: 202400086 | E7: Apoyo Ciudadano | F7: Salud | H7: La Sra Yolanda Garzón solicita cita con especialista en oftamología por primera vez, lleva mas de 6 meses esperando la cita y esta perdiendo la vista | I7: Secretaría Distrital de Salud | J7: Tierra Buena | K7: Sur | L7: 08.Kennedy | M7: 08.Patio Bonito | N7: =BUSCARX(R[0]C[-1],CONVENCIONES!R12C1:R42C1,CONVENCIONES!R12C2:R42C2) -> #ERROR! | O7: Gestión 2024 | P7: Yolanda Garzón | Q7: Mujer | R7: 41308189 | S7: calle 26 sur #95a49 | T7: 4.650076195336499, -74.16991540572303 | U7: N/A | V7: 3228569868 | W7: Tramites | X7: Interno | Y7: Finalizado | Z7: Positivo | AA7: Se programa la cita correspondiente | AB7: 45362 | AC7: =DIA.LAB(R[0]C[-1],15) -> #ERROR! | AD7: Asesor | AE7: Fernando Zamora | AF7: Bogotá | AG7: Cundinamarca | AH7: 202400086_Yolanda Garzón | AJ7: NO
A8: 2024 | B8: 3 | C8: Marzo | D8: 202400090 | E8: Apoyo Ciudadano | F8: Salud | G8: Citas médicas | H8: Diagnóstico: tuvo un accidente practicando el deporte de clavados en natación. Solicitudes: * Cita: Resonancia de Orbitas, esta cita está agendado para el 6 de abril, pero se necesita urgente o anticiparla porque sus ojos están afectados por el accidente. * Cita: Neurocirugía 1a vez, para esta cita dicen que no hay agenda. | I8: Secretaría Distrital de Salud | J8: Ciudad de cali - patio bonito | K8: Sur | L8: 08.Kennedy | M8: 08.Kennedy Central | N8: =BUSCARX(R[0]C[-1],CONVENCIONES!R12C1:R42C1,CONVENCIONES!R12C2:R42C2) -> #ERROR! | O8: Gestión 2024 | P8: Nombre de la menor: Viviana Marulanda Valenzuela. Datos de la acudiente: Emilse Valenzuela - celular: 312 4310711 | Q8: Mujer | R8: 1.141.327.972 | S8: Carrera 86c bis No 42-51 sur | T8: 4.632030395354502, -74.16841293455875 | U8: emilce095@gmail.com | V8: 312 4310711 | W8: Tramites | X8: Interno | Y8: Finalizado | Z8: Positivo | AA8: N/A | AB8: 45363 | AC8: 45365 | AD8: Asesor | AE8: Angie Benitez | AF8: Bogotá | AG8: Cundinamarca | AH8: 202400090_Emilse Valenzuela | AJ8: NO
A9: 2024 | B9: 3 | C9: Marzo | D9: 202400091 | E9: Apoyo Ciudadano | F9: Salud | G9: Citas médicas | H9: Diagnóstico: hiperplasia de próstata Control por especialista en Urologia | I9: Secretaría Distrital de Salud | J9: Las margaritas | K9: Sur | L9: 08.Kennedy | M9: 08.Kennedy Central | N9: =BUSCARX(R[0]C[-1],CONVENCIONES!R12C1:R42C1,CONVENCIONES!R12C2:R42C2) -> #ERROR! | O9: Gestión 2024 | P9: Raúl Hernández | Q9: Hombre | R9: 19.437.301 | S9: Calle 46 sur # 86-41 Casa 384 alamedas de san José 2 zona las margaritas localidad de Kennedy | T9: 4.628496889205801, -74.17446470572308 | U9: dianis6413@gmail.com | V9: 3143367599 | W9: Tramites | X9: Interno | Y9: Finalizado | Z9: Positivo | AA9: N/A | AB9: 45364 | AC9: 45370 | AD9: Asesor | AE9: Angie Benitez | AF9: Bogotá | AG9: Cundinamarca | AH9: 202400091_Raúl Hernández | AJ9: NO
A10: 2024 | B10: 3 | C10: Marzo | D10: 202400093 | E10: Apoyo Ciudadano | F10: Salud | G10: Entrega de equipos médicos | H10: Diagnóstico: Trombosis en pierna. Solicitud: silla de ruedas. contexto: fueron presencialmente que ya no hay ese servicio. la justificación fue una resolución. | I10: Secretaría Distrital de Salud | J10: Las margaritas | K10: Sur | L10: 08.Kennedy | M10: 08.Kennedy Central | N10: =BUSCARX(R[0]C[-1],CONVENCIONES!R12C1:R42C1,CONVENCIONES!R12C2:R42C2) -> #ERROR! | O10: Gestión 2024 | P10: José Antonio Mendoza Vera | Q10: Hombre | R10: 2278975 | S10: Dirección :carrera 89 a 45a 38 sur Barrio : margaritas etapa 1, torre 23, apto 201 | T10: 4.634271482873386, -74.17697183455873 | U10: albam6075@gmail.com | V10: celular: 3114688767 - hija | W10: Tramites | X10: Interno | Y10: Pendiente | Z10: Negativo | AA10: No llamaron a la persona ni le hicieron la gestión. La persona ya está recuperada y no requiere el servicio. | AB10: 45365 | AC10: N/A | AD10: Asesor | AE10: Angie Benitez | AF10: Bogotá | AG10: Cundinamarca | AH10: 202400093_José Antonio Mendoza Vera | AJ10: NO
A11: 2024 | B11: 3 | C11: Marzo | D11: 202400104 | E11: Apoyo Ciudadano | F11: Salud | G11: Programación de cirugías | H11: Descripción del caso: Desde el mes de junio del año 2023 he venido presentando dolor severo continuo en parte abdominal y espalda baja del lado izquierdo por lo que me han visto doctores y ginecólogos, enviándome diferentes exámenes (ecografías transvaginales, antígeno carcinoembrionario, antígeno de cáncer de ovario, pruebas de embarazo exámenes de orina, exámenes de sangre en general) después de múltiples citas y al ver que los medicamentos no han dado ningún resultado, la ginecóloga Adriana Farias me dio orden de cirugía ( CISTECTOMIA DE OVARIO POR LAPAROSCOPIA) el día 06 de febrero de 2024, realice la autorización y me dieron el código asignado pero a la fecha no ha subido al sistema y debo seguir esperando a que me llamen para asignarme la clínica y la fecha de cirugía, yo sigo con dolores severos por lo que he acudido de urgencias a la clínica Colombia y al Hospital mayor Medery, verificando en nuevas ecografías que además del quiste en ovario izquierdo tengo endometriosis severa pero me dicen que no es una urgencia vital y por tanto no me pueden operar de urgencias, mi estado de salud es deplorable y mi calidad de vida va en descenso día a día al punto de tener que mandarme inyectar medicamentos fuertes como tramadol y dipirona, agradezco de corazón, la colaboración que me puedan brindar para agilizar mi cirugía de ovario izquierdo. | I11: Secretaría Distrital de Salud | J11: Castilla | K11: Sur | L11: 08.Kennedy | M11: N/A | N11: =BUSCARX(R[0]C[-1],CONVENCIONES!R12C1:R42C1,CONVENCIONES!R12C2:R42C2) -> #ERROR! | O11: Gestión 2024 | P11: Gina Lorena Lopez Mantilla | Q11: Mujer | R11: 52903620 | S11: Calle 8C 80 – 38 int 3 apto 512 conjunto Bosques de Bavaria Barrio Castilla | T11: 4.642836139522496, -74.14436504859762 | U11: glorenalopez@hotmail.com | V11: 301 5813744 | W11: Tramites | X11: Externos | Y11: Finalizado | Z11: Positivo | AA11: N/A | AB11: 45371 | AC11: N/A | AD11: Asesor | AE11: Angie Benitez | AF11: Bogotá | AG11: Cundinamarca | AH11: 202400104_Gina Lorena Lopez Mantilla | AJ11: NO
A12: 2024 | B12: 4 | C12: Abril | D12: 202400110 | E12: Apoyo Ciudadano | F12: Salud | G12: Citas médicas | H12: “Reciba un cordial saludo concejal, mi nombre es Martha Elizabeth Barbosa Sastoque y me encuentro en el régimen subsidiado a través de capital salud, desde el 23 de agosto del año 2023 llevo solicitando cita para optometría y me dieron el código de 890207. Asimismo, desde el 14 de agosto de 2023 estoy solicitando cita de otorrinolaringología a través del código 890282. Le agradecería si me ayudan a gestionar estas dos citas ya que llevo hace varios meses tratando de solicitarlas”. | I12: Secretaría Distrital de Salud | J12: Los periodistas | K12: Sur | L12: 08.Kennedy | M12: 08.Class | N12: =BUSCARX(R[0]C[-1],CONVENCIONES!R12C1:R42C1,CONVENCIONES!R12C2:R42C2) -> #ERROR! | O12: Gestión 2024 | P12: Martha Elizabeth Barbosa Sastoque | Q12: Mujer | R12: 52016841 | S12: Trav 78 h bis N 41-86 sur | T12: 4.616787189394192, -74.15697963455875 | U12: marelizbar1970@gmail.com | V12: 3024382399 | W12: Tramites | Y12: Finalizado | Z12: Positivo | AA12: N/A | AB12: 45384 | AC12: 45391 | AD12: Asesor | AE12: Angie Benitez | AF12: Bogotá | AG12: Cundinamarca | AH12: PENDIENTE LINK | AJ12: NO
A13: 2024 | B13: 4 | C13: Abril | D13: 202400140 | E13: Apoyo Ciudadano | F13: Salud | G13: Procedimientos y exámenes | H13: Diagnóstico: tumor benigno del tejido conjuntivo del abdomen. Solicitud: Biopsia cerrada intraabdominal. Tiempo de solicitud: Me han dilatado la solicitud más de un mes y nada que me hacen la biopsia, me remiten un lugar a otro y no me practican el procedimiento que me ordenó el médico. | I13: Secretaría Distrital de Salud | J13: El amparo | K13: Sur | L13: 08.Kennedy | M13: 08.Kennedy Central | N13: =BUSCARX(R[0]C[-1],CONVENCIONES!R12C1:R42C1,CONVENCIONES!R12C2:R42C2) -> #ERROR! | O13: Gestión 2024 | P13: Flower Alegrías Carbonero | Q13: N/A | R13: 76231536 | S13: calle 42#80g02 | T13: 4.6243384512631875, -74.16436231524406 | U13: floweralegrias979@gmail.com | V13: 311 5010594 | W13: Tramites | X13: Interno | Y13: Finalizado | Z13: Positivo | AA13: N/A | AB13: 45402 | AC13: 45412 | AD13: Asesor | AE13: Angie Benitez | AF13: Bogotá | AG13: Cundinamarca | AH13: PENDIENTE LINK | AJ13: NO
A14: 2024 | B14: 4 | C14: Abril | D14: 202400142 | E14: Apoyo Ciudadano | F14: Salud | G14: Citas médicas | H14: Diagnóstico: EPOC crónico, hipertensa, pasada un poco de peso. La señora depende del oxígeno las 24 horas debido a su avanzada edad, también se le dificulta caminar. Solicitud: cita pendiente con especialista en psiquiatria y solicitud de pañales talla XL. | I14: Secretaría Distrital de Salud | J14: Alcalá | K14: Sur | L14: 08.Kennedy | M14: 08.Kennedy Central | N14: =BUSCARX(R[0]C[-1],CONVENCIONES!R12C1:R42C1,CONVENCIONES!R12C2:R42C2) -> #ERROR! | O14: Gestión 2024 | P14: Rosa Matilde Sastoque de Barbosa. | Q14: Mujer | R14: 20925201 | S14: calle 30 sur #52-55 | T14: 4.604939983787324, -74.1276540345588 | U14: familiabarbosa321f@gmail.com | V14: 302 4382399 | W14: Tramites | Y14: Finalizado | Z14: Positivo | AA14: N/A | AB14: 45404 | AC14: N/A | AD14: Asesor | AE14: Angie Benitez | AF14: Bogotá | AG14: Cundinamarca | AH14: PENDIENTE LINK | AJ14: NO
A15: 2024 | B15: 4 | C15: Abril | D15: 202400144 | E15: Apoyo Ciudadano | F15: Salud | G15: Citas médicas | H15: Diagnóstico:secuelas de un acidente Solicitud: una consulta con especialista otorrinolaringología y otra con especialista en neurología Tiempo de solicitud:casi un año | I15: Secretaría Distrital de Salud | J15: Vegas de santa ana | K15: Sur | L15: 08.Kennedy | M15: N/A | N15: =BUSCARX(R[0]C[-1],CONVENCIONES!R12C1:R42C1,CONVENCIONES!R12C2:R42C2) -> #ERROR! | O15: Gestión 2024 | P15: Familiar: Yudit Rojas Paciente: Jhon Javier Gomez Sanchez | Q15: Hombre | R15: 1930645800 | S15: cra 81 j 57A- 95 sur | T15: 4.618483796471932, -74.18145065077307 | U15: Gómezjaver200@gmail.com | V15: 3217458382 | W15: Tramites | Y15: Finalizado | Z15: Pendiente | AA15: N/A | AB15: 45404 | AC15: N/A | AD15: Asesor | AE15: Angie Benitez | AF15: Bogotá | AG15: Cundinamarca | AH15: PENDIENTE LINK | AJ15: NO
A16: 2024 | B16: 4 | C16: Abril | D16: 202400149 | E16: Apoyo Ciudadano | F16: Salud | H16: Solicita una terapia | I16: Secretaría Distrital de Salud | J16: Tintal | K16: Sur | L16: 08.Kennedy | M16: 08.Kennedy Central | N16: =BUSCARX(R[0]C[-1],CONVENCIONES!R12C1:R42C1,CONVENCIONES!R12C2:R42C2) -> #ERROR! | O16: Gestión 2024 | P16: María Luzmila Rodríguez | Q16: Mujer | R16: 41445987 | S16: Calle 6a 88 51 Fase 2 | T16: 4.645569756879411, -74.15779493455871 | U16: N/A | V16: 3222262371 | W16: Tramites | X16: Interno | Y16: Finalizado | Z16: Positivo | AA16: Se programa la cita correspondiente | AB16: 45405 | AC16: =DIA.LAB(R[0]C[-1],15) -> #ERROR! | AD16: Asesor | AE16: Fernando Zamora | AF16: Bogotá | AG16: Cundinamarca | AH16: 202400149_María Luzmila Rodríguez | AJ16: NO
A17: 2024 | B17: 4 | C17: Abril | D17: 202400150 | E17: Apoyo Ciudadano | F17: Cementerios | H17: Solicitud de registro de defunsión que tiene reserva | I17: Registraduría | J17: Boita | K17: Sur | L17: 08.Kennedy | M17: 08.Kennedy Central | N17: =BUSCARX(R[0]C[-1],CONVENCIONES!R12C1:R42C1,CONVENCIONES!R12C2:R42C2) -> #ERROR! | O17: Gestión 2024 | P17: Diana Jaraba | Q17: Mujer | R17: 1007095114 | S17: calle 42 f sur #72h 95 | T17: 4.604087866462173, -74.14844373455881 | U17: jarababogada@gmail.com | V17: 301 6455867 | W17: Tramites | Y17: Finalizado | Z17: Positivo | AA17: N/A | AB17: 45405 | AC17: N/A | AD17: Asesor | AE17: Angie Benitez | AF17: Bogotá | AG17: Cundinamarca | AH17: PENDIENTE LINK | AJ17: NO
A18: 2024 | B18: 4 | C18: Abril | D18: 202400154 | E18: Apoyo Ciudadano | F18: Salud | G18: Citas médicas | H18: Diagnóstico: manguito tirador derecho Solicitud: cita con el cirujano para realizar cirugía Tiempo de solicitud: 9 meses | I18: Secretaría Distrital de Salud | J18: Carmelo | K18: Sur | L18: 08.Kennedy | M18: 08.Class | N18: =BUSCARX(R[0]C[-1],CONVENCIONES!R12C1:R42C1,CONVENCIONES!R12C2:R42C2) -> #ERROR! | O18: Gestión 2024 | P18: María Engracia Romero de Penagos | Q18: Mujer | R18: 28834677 | S18: carrera 87#57 a 09 sur | T18: 4.624477670996924, -74.18776833455878 | U18: alejandrarodriguezpenagos@hotmail.com | V18: 3114500159 | W18: Tramites | Y18: Finalizado | Z18: Positivo | AA18: N/A | AB18: 45406 | AC18: N/A | AD18: Asesor | AE18: Angie Benitez | AF18: Bogotá | AG18: Cundinamarca | AH18: PENDIENTE LINK | AJ18: NO
A19: 2024 | B19: 4 | C19: Abril | D19: 202400157 | E19: Apoyo Ciudadano | F19: Salud | G19: Procedimientos y exámenes | H19: Solicitud: Que le realicen los exámenes para generar el diagnostico, al paciente solo le indican bacterias o parasitos estomacales, le indicaron que podría ser cancer pero no le han realizado los exámenes correspondientes Tiempo de solicitud: 4 meses Nota: requiere atención porque presuntamente tiene síntomas cancerígenos sin embargo la EPS no le han dado las ordenes para los exámenes y descartar o confirmar esa circunstancia | I19: Secretaría Distrital de Salud | J19: Bosa Linda | K19: Sur | L19: 08.Kennedy | M19: 08.Class | N19: =BUSCARX(R[0]C[-1],CONVENCIONES!R12C1:R42C1,CONVENCIONES!R12C2:R42C2) -> #ERROR! | O19: Gestión 2024 | P19: José María Arango Reinosa | Q19: Hombre | R19: 79635982 | S19: Carrera 85 #55 - 29 | T19: 4.648494761362429, -74.14854919752344 | U19: doraba.arango1975@gmail.com | V19: 3118469096 | W19: Tramites | Y19: Finalizado | Z19: Positivo | AA19: N/A | AB19: 45406 | AC19: N/A | AD19: Asesor | AE19: Angie Benitez | AF19: Bogotá | AG19: Cundinamarca | AH19: PENDIENTE LINK | AJ19: NO
A20: 2024 | B20: 4 | C20: Abril | D20: 202400158 | E20: Apoyo Ciudadano | F20: Salud | G20: Citas médicas | H20: Solicitud: cita con oftalmología | I20: Secretaría Distrital de Salud | J20: Palenque | K20: Sur | L20: 08.Kennedy | M20: 08.Kennedy Central | N20: =BUSCARX(R[0]C[-1],CONVENCIONES!R12C1:R42C1,CONVENCIONES!R12C2:R42C2) -> #ERROR! | O20: Gestión 2024 | P20: Alis Peña de Chitiva | Q20: Mujer | R20: 41515508 | S20: cra 78 f # 42 c 04 sur | T20: 4.614946771581417, -74.15955886339442 | U20: juanchitiva@hotmail.com | V20: 3102502262 | W20: Tramites | Y20: Finalizado | Z20: Positivo | AA20: N/A | AB20: 45412 | AC20: N/A | AD20: Asesor | AE20: Angie Benitez | AF20: Bogotá | AG20: Cundinamarca | AH20: PENDIENTE LINK | AJ20: NO
A21: 2024 | B21: 4 | C21: Abril | D21: 202400159 | E21: Apoyo Ciudadano | F21: Salud | G21: Medicamentos | H21: Diagnóstico: trastornos mentales y del comportamiento debido a uso del tabaco: síndrome de dependencia Solicitud: La hna sufre de depresión y ansiedad, la EPS no le hace entrega de orden de medicamentos ya que no hay agenda con el psiquiatra; por lo cual el hijo debe llevarla de manera mensual a urgencias psiquiátricas para que le entreguen medicamentos por cada mes; se solicita cita y seguimiento con psiquiatría con el fin de que le hagan entrega de ordenes de medicamentos crónicos sin necesidad de asistir a urgencias Tiempo de solicitud: 4 meses | I21: Secretaría Distrital de Salud | J21: Pastranita | K21: Sur | L21: 08.Kennedy | M21: 08.Class | N21: =BUSCARX(R[0]C[-1],CONVENCIONES!R12C1:R42C1,CONVENCIONES!R12C2:R42C2) -> #ERROR! | O21: Gestión 2024 | P21: Nubia Rodriguez Mendez | Q21: Mujer | R21: 39749227 | S21: Transversal 78L ·50 sur -17 apto 401 | T21: 4.614045683632616, -74.16940289575687 | U21: richardjokerazul@gmail.com | V21: 3059293551 (Hno Ricardo - hijo) | W21: Tramites | Y21: Finalizado | Z21: Pendiente | AA21: Ya se asignó cita, faltarían los medicamentos. | AB21: 45412 | AC21: N/A | AD21: Asesor | AE21: Angie Benitez | AF21: Bogotá | AG21: Cundinamarca | AH21: PENDIENTE LINK | AJ21: NO
A22: 2024 | B22: 4 | C22: Abril | D22: 202400176 | E22: Apoyo Ciudadano | F22: Educación | H22: Cupo para el colegio Debora Arango Motivo: me gustaría el cambio del colegio ya que este Debora Arango me queda más cerca de mi residencia, que el colegio Romulo Gallego | I22: Secretaría de Educación del Distrito | J22: Roma | K22: Sur | L22: 08.Kennedy | M22: 08.Class | N22: =BUSCARX(R[0]C[-1],CONVENCIONES!R12C1:R42C1,CONVENCIONES!R12C2:R42C2) -> #ERROR! | O22: Gestión 2024 | P22: Mayelli Abonia Camacho Cedula: 29.507.889 Alanna Samai Cuesta Abonia Tarjeta de identidad 1.030.677.352 | Q22: Mujer | R22: 29.507.889 | S22: Calle 53a # 81i-21 sur | T22: 4.616576475077917, -74.17434200880973 | U22: mayaboca17@gmail.com | V22: 3147962210 | W22: Tramites | Y22: Finalizado | Z22: Positivo | AA22: Se hizo la gestión a través del DILE de Kennedy por medio de la edilesa | AB22: 45407 | AC22: 45422 | AD22: Asesor | AE22: Angie Benitez | AF22: Bogotá | AG22: Cundinamarca | AH22: PENDIENTE LINK | AJ22: NO
A23: 2024 | B23: 5 | C23: Mayo | D23: 202400179 | E23: Apoyo Ciudadano | F23: Salud | G23: Citas médicas | H23: Diagnóstico: enfermedad de Chagas aguda que afecta el corazón Solicitud; consulta de primera vez por especialista en cirugía cardiovascular. | I23: Secretaría Distrital de Salud | J23: Ciudad de Cali | K23: Sur | L23: 08.Kennedy | M23: 08.Kennedy Central | N23: =BUSCARX(R[0]C[-1],CONVENCIONES!R12C1:R42C1,CONVENCIONES!R12C2:R42C2) -> #ERROR! | O23: Gestión 2024 | P23: Celia Matilde Forero rojas Acudiente: Luz Marina Valenzuela | Q23: Mujer | R23: 28190396 | S23: Kra 86c bis #42 - 51 sur | T23: 4.633140133136534, -74.16639663455871 | U23: luzmari2909@hotmail.com | V23: 3213032240 / 3124310711 | W23: Tramites | X23: Interno | Y23: Finalizado | Z23: Positivo | AA23: N/A | AB23: 45427 | AC23: N/A | AD23: Asesor | AE23: Angie Benitez | AF23: Bogotá | AG23: Cundinamarca | AH23: PENDIENTE LINK | AJ23: NO
A24: 2024 | B24: 5 | C24: Mayo | D24: 202400181 | E24: Apoyo Ciudadano | F24: Salud | G24: Medicamentos | H24: Diagnóstico: hipertensa, sufre del corazón, tiroides , triglicedeos, catarata densa en los ojos. Solicitud: 1. medicamentos para hipertensión. 2. Cita con oftalmología. | I24: Secretaría Distrital de Salud | J24: Villa Nelly | K24: Sur | L24: 08.Kennedy | M24: 08.Kennedy Central | N24: =BUSCARX(R[0]C[-1],CONVENCIONES!R12C1:R42C1,CONVENCIONES!R12C2:R42C2) -> #ERROR! | O24: Gestión 2024 | P24: Otilia Sosa Gracia | Q24: Mujer | R24: 20858218 | S24: calle 42 g #80 b 21 sur | T24: 4.622008710619711, -74.16559977688753 | U24: elsyyg@gmail.com | V24: 3138010381 | W24: Tramites | X24: Interno | Y24: En Proceso | Z24: Pendiente | AA24: N/A | AB24: 45427 | AC24: N/A | AD24: Asesor | AE24: Angie Benitez | AF24: Bogotá | AG24: Cundinamarca | AH24: PENDIENTE LINK | AJ24: NO
A25: 2024 | B25: 5 | C25: Mayo | D25: 202400182 | E25: Apoyo Ciudadano | F25: Salud | G25: Citas médicas | H25: Diagnóstico: leve de Autismo, TDH elevada con hiperactiva. Solicitud puntual:Agilizar una cita con el especialista Neurólogo pediatra para que pueda revisar los exámenes examinar el niño y así obtener un diagnóstico definitivo, y acceder a un tratamiento. Tengo la orden desde septiembre 29 del 2023 y no asido posible la cita con el especialista por motivos de que hay agenda. Mi hijo tiene dificultades para adaptarse a los entornos sociales. | I25: Secretaría Distrital de Salud | J25: Carvajal | K25: Sur | L25: 08.Kennedy | M25: 08.Carvajal | N25: =BUSCARX(R[0]C[-1],CONVENCIONES!R12C1:R42C1,CONVENCIONES!R12C2:R42C2) -> #ERROR! | O25: Gestión 2024 | P25: Mateo Alejandro Díaz Montañez | Q25: Hombre | R25: 1023410547 | S25: CL 64 C SUR 27 13 CANDELARIA | T25: 4.615132307907278, -74.13793253984731 | U25: NA | V25: 3163437486 | W25: Tramites | X25: Interno | Y25: En Proceso | Z25: Pendiente | AA25: N/A | AB25: 45427 | AC25: N/A | AD25: Asesor | AE25: Angie Benitez | AF25: Bogotá | AG25: Cundinamarca | AH25: PENDIENTE LINK | AJ25: NO
A26: 2024 | B26: 5 | C26: Mayo | D26: 202400284 | E26: Apoyo Ciudadano | F26: Salud | H26: Solicita una cita con el Fisiatra, una con el Endocrinólogo y otra cirugía oral – Odontólogo | I26: Secretaría Distrital de Salud | J26: Santa Sofía | K26: Sur | L26: 08.Kennedy | M26: 08.Patio Bonito | N26: =BUSCARX(R[0]C[-1],CONVENCIONES!R12C1:R42C1,CONVENCIONES!R12C2:R42C2) -> #ERROR! | O26: Gestión 2024 | P26: Digna María Vargas de Castillo | Q26: Mujer | R26: 26533998 | S26: Cra 29A # 75-30 | T26: 4.622839368592367, -74.08538886819075 | U26: hanavicolombia@gmail.com | V26: 3108548307 | W26: Tramites | X26: Interno | Y26: Finalizado | Z26: Positivo | AA26: Se programo la cita correspondiente | AB26: 45439 | AC26: 45449 | AD26: Asesor | AE26: Fernando Zamora | AF26: Bogotá | AG26: Cundinamarca | AH26: 202400284_Digna María Vargas de Castillo | AJ26: NO
A27: 2024 | B27: 5 | C27: Mayo | D27: 202400285 | E27: Apoyo Ciudadano | F27: Salud | H27: Solicita una cita con Endocrinólogo | I27: Secretaría Distrital de Salud | J27: Santa Sofía | K27: Sur | L27: 08.Kennedy | M27: 08.Patio Bonito | N27: =BUSCARX(R[0]C[-1],CONVENCIONES!R12C1:R42C1,CONVENCIONES!R12C2:R42C2) -> #ERROR! | O27: Gestión 2024 | P27: José Nicolás Castillo Moreno | Q27: Hombre | R27: 19244568 | S27: Cra 29A # 75-30 | T27: 4.622839368592367, -74.08538886819075 | U27: hanavicolombia@gmail.com | V27: 3108548307 | W27: Tramites | X27: Interno | Y27: Finalizado | Z27: Positivo | AA27: Se programo la cita correspondiente | AB27: 45439 | AC27: 45449 | AD27: Asesor | AE27: Fernando Zamora | AF27: Bogotá | AG27: Cundinamarca | AH27: 202400285_José Nicolás Castillo Moreno | AJ27: NO
A28: 2024 | B28: 5 | C28: Mayo | D28: 202400292 | E28: Apoyo Ciudadano | F28: Salud | G28: Tratamientos | H28: Diagnóstico: cáncer de mama Solicitud : recibir la tercer quimioterapia en el tiempo estipulado por el oncólogo. | I28: Superintendencia de Salud | J28: Villa Alsacia | K28: Sur | L28: 08.Kennedy | M28: N/A | N28: =BUSCARX(R[0]C[-1],CONVENCIONES!R12C1:R42C1,CONVENCIONES!R12C2:R42C2) -> #ERROR! | O28: Gestión 2024 | P28: Margarita López Ramírez | Q28: Mujer | R28: 52734656 | S28: carrera 72 A bis A #11B - 27 | T28: 4.644586969759896, -74.13433423455866 | U28: mlopezr1@educacionbogota.edu.co | V28: 3057519590 | W28: Tramites | Y28: Finalizado | Z28: Positivo | AA28: La persona también hizo gestión por su parte | AB28: 45433 | AC28: 45440 | AD28: Asesor | AE28: Angie Benitez | AF28: Bogotá | AG28: Cundinamarca | AH28: PENDIENTE LINK | AJ28: NO
A29: 2024 | B29: 6 | C29: Junio | D29: 202400382 | E29: Apoyo Ciudadano | F29: Salud | H29: El ciudadano Álvaro Silva Castro indica que no le han entregado un medicamento indispensable para mejorar su salud | I29: Secretaría Distrital de Salud | J29: Patio Bonito | K29: Sur | L29: 08.Kennedy | M29: 08.Patio Bonito | N29: =BUSCARX(R[0]C[-1],CONVENCIONES!R12C1:R42C1,CONVENCIONES!R12C2:R42C2) -> #ERROR! | O29: Gestión 2024 | P29: Álvaro Silva Castro | Q29: Hombre | R29: 14269252 | S29: Calle 8a#92-71 | T29: 4.655349208446909, -74.1568137619685 | U29: alvarosilva7@hotmail.com | V29: 3133683676 | W29: Tramites | X29: Interno | Y29: Finalizado | Z29: Positivo | AA29: Se hace traslado a la entidad | AB29: 45468 | AC29: =DIA.LAB(R[0]C[-1],15) -> #ERROR! | AD29: Asesor | AE29: Fernando Zamora | AF29: Bogotá | AG29: Cundinamarca | AH29: 202400382_Álvaro Silva Castro | AJ29: NO
A30: 2024 | B30: 7 | C30: Julio | D30: 202400416 | E30: Apoyo Ciudadano | F30: Salud | G30: Citas médicas | H30: Traslado caso de paciente con catarata requiere cita de oftalmología | I30: Secretaría Distrital de Salud | J30: Las Margaritas | K30: Sur | L30: 08.Kennedy | M30: 07.Bosa Recreo | N30: =BUSCARX(R[0]C[-1],CONVENCIONES!R12C1:R42C1,CONVENCIONES!R12C2:R42C2) -> #ERROR! | O30: Gestión 2024 | P30: Cleotilde Sanabria | Q30: Mujer | R30: 20285203 | S30: Calle 48 Sur 88C-49 | T30: 4.6317774265560585, -74.17887255569696 | U30: cleotildesanabriagonzales@gmail.com | V30: 3102099828 | W30: Tramites | X30: Interno | Y30: Finalizado | Z30: Positivo | AA30: Se asigna cita médica | AB30: 45475 | AC30: N/A | AD30: Asesor | AE30: Maicol Quiroga | AF30: Bogotá | AG30: Cundinamarca | AH30: Cleotilde Sanabria | AJ30: NO
A31: 2024 | B31: 7 | C31: Julio | D31: 202400422 | E31: Apoyo Ciudadano | F31: Salud | H31: Solicita una cita con especialista por dolor constante en la espalda desde hace 3 meses | I31: Secretaría Distrital de Salud | J31: Altamar | K31: Sur | L31: 08.Kennedy | M31: 08.Patio Bonito | N31: =BUSCARX(R[0]C[-1],CONVENCIONES!R12C1:R42C1,CONVENCIONES!R12C2:R42C2) -> #ERROR! | O31: Gestión 2024 | P31: Rita Leonor Sánchez Gonzales | Q31: Mujer | R31: 23486496 | S31: Cl. 42b Sur #87i-20 | T31: 4.63471293116785, -74.17096643390632 | U31: jazmincilla@hotmail.es | V31: 3114738322 | W31: Tramites | X31: Interno | Y31: Finalizado | Z31: Positivo | AA31: Se programa la cita solicitada | AB31: 45477 | AC31: N/A | AD31: Asesor | AE31: Fernando Zamora | AF31: Bogotá | AG31: Cundinamarca | AH31: 202400422_Rita Leonor Sánchez Gonzales | AJ31: NO
A32: 2024 | B32: 7 | C32: Julio | D32: 202400423 | E32: Apoyo Ciudadano | F32: Educación | H32: Solcita información sobre el proceso de admisión de su hijo en la universidad distrital y la agencia Atenea | I32: Secretaría de Educación del Distrito | J32: Calarca | K32: Sur | L32: 08.Kennedy | M32: 08.Class | N32: =BUSCARX(R[0]C[-1],CONVENCIONES!R12C1:R42C1,CONVENCIONES!R12C2:R42C2) -> #ERROR! | O32: Gestión 2024 | P32: Kelly Cecilia Boya Escobar | Q32: Mujer | R32: 67041434 | S32: cll. 47 # 80 - 56 | T32: 4.619868541173852, -74.16889470515919 | U32: kellyboya0112@gmail.com | V32: 3182990558 | W32: Tramites | X32: Interno | Y32: Finalizado | Z32: Negativo | AA32: La respuesta a la petición fue negativa, ya que indica que no aplica al proceso satisfactoriamente y que debe hacer el proceso cuando hayan nuevas convocatorias | AB32: 45477 | AC32: N/A | AD32: Asesor | AE32: Fernando Zamora | AF32: Bogotá | AG32: Cundinamarca | AH32: 202400423_Kelly Cecilia Boya Escobar | AJ32: NO
A33: 2024 | B33: 7 | C33: Julio | D33: 202400432 | E33: Apoyo Ciudadano | F33: Salud | G33: Procedimientos y exámenes | H33: Caso salud: - Electrocardiograma de ritmo o de superficie. - Consulta por primera vez por optometría. | I33: Superintendencia de Salud | J33: Palenque | K33: Sur | L33: 08.Kennedy | M33: 08.Kennedy Central | N33: =BUSCARX(R[0]C[-1],CONVENCIONES!R12C1:R42C1,CONVENCIONES!R12C2:R42C2) -> #ERROR! | O33: Gestión 2024 | P33: Ana Teresa Vargas Florez | Q33: Mujer | R33: 27876793 | S33: Calle 42f #78c 03 | T33: 4.613273106566682, -74.16032417657928 | U33: anateresavargas0124@gmail.com | V33: celular: 3015584177 - 3152405466 (hermano de la paciente). | W33: Tramites | X33: Interno | Y33: En Proceso | Z33: Pendiente | AA33: Se hace el traslado a la entidad a través de oficio | AB33: 45481 | AC33: N/A | AD33: Asesor | AE33: Angie Benitez | AF33: Bogotá | AG33: Cundinamarca | AH33: PENDIENTE LINK | AJ33: NO
A34: 2024 | B34: 7 | C34: Julio | D34: 202400441 | E34: Apoyo Ciudadano | F34: Servicio militar | H34: Asesoría para obtener la libreta militar | I34: Secretaría Distrital de Seguridad, Convivencia y Justicia | J34: Ayacucho II sector | K34: Sur | L34: 08.Kennedy | M34: 08.Kennedy Central | N34: =BUSCARX(R[0]C[-1],CONVENCIONES!R12C1:R42C1,CONVENCIONES!R12C2:R42C2) -> #ERROR! | O34: Gestión 2024 | P34: Jorge Enrique Alba Balaguera | Q34: Hombre | R34: 1022430676 | S34: CRA 78p bis #6-35sur | T34: 4.62934032753972, -74.1510866900773 | U34: joalba2748@gmail.com | V34: 313 4256455 | W34: Tramites | X34: N/A | Y34: Finalizado | Z34: Positivo | AA34: Es un referido | AB34: 45483 | AC34: N/A | AD34: Asesor | AE34: Angie Benitez | AF34: Bogotá | AG34: Cundinamarca | AH34: PENDIENTE LINK | AJ34: NO
A35: 2024 | B35: 7 | C35: Julio | D35: 202400449 | E35: Apoyo Ciudadano | F35: Salud | H35: Solicitud de cita para paciente con cancer | I35: Secretaría Distrital de Salud | J35: Patio Bonito | K35: Sur | L35: 08.Kennedy | M35: 08.Patio Bonito | N35: =BUSCARX(R[0]C[-1],CONVENCIONES!R12C1:R42C1,CONVENCIONES!R12C2:R42C2) -> #ERROR! | O35: Gestión 2024 | P35: Henry Enrique Herrera Molina | Q35: Hombre | R35: 79713798 | S35: Cra 89c # 38d 19 sur | T35: 4.639966868831216, -74.16820810362483 | U35: henryh_m@hotmail.com | V35: 3143908862 | W35: Tramites | X35: Interno | Y35: Finalizado | Z35: Positivo | AA35: Se hace el traslado a la entidad | AB35: 45484 | AC35: N/A | AD35: Asesor | AE35: Fernando Zamora | AF35: Bogotá | AG35: Cundinamarca | AH35: 202400449_Henry Enrique Herrera Molina | AJ35: NO
A36: 2024 | B36: 7 | C36: Julio | D36: 202400529 | E36: Apoyo Ciudadano | F36: Educación | H36: Educación inclusiva para una menor con discapacidad cognitiva. La solicitud es: un colegio público o privado con más inclusión y personalizado. | I36: Secretaría de Educación del Distrito | J36: Villa Andrea | K36: Sur | L36: 08.Kennedy | M36: 08.Class | N36: =BUSCARX(R[0]C[-1],CONVENCIONES!R12C1:R42C1,CONVENCIONES!R12C2:R42C2) -> #ERROR! | O36: Gestión 2024 | P36: Acudiente: Heidi Isabel Díaz montaña Menor: Danna Sofia Bernal Díaz | Q36: Mujer | R36: 52468928 | S36: Cra 81i #51b19 sur | T36: 4.6215075899432865, -74.1757500002634 | U36: didita8016@hotmail.com | V36: 3115918677 mamá 3134154612 papá | W36: Niñez | X36: Interno | Y36: Finalizado | Z36: Positivo | AB36: 45496 | AC36: N/A | AD36: Asesor | AE36: Angie Benitez | AF36: Bogotá | AG36: Cundinamarca | AH36: 202400529_Danna Sofia Bernal Díaz | AJ36: NO
A37: 2024 | B37: 7 | C37: Julio | D37: 202400533 | E37: Apoyo Ciudadano | F37: Salud | G37: Citas médicas | H37: Solicitud: 1. Cita para que le lean los exámenes y que le digan cual es el paso por seguir. 2. Una ecografía Doppler para tejidos blandos. | I37: Secretaría Distrital de Salud | J37: Gran britalia | K37: Sur | L37: 08.Kennedy | M37: 08.Kennedy Central | N37: =BUSCARX(R[0]C[-1],CONVENCIONES!R12C1:R42C1,CONVENCIONES!R12C2:R42C2) -> #ERROR! | O37: Gestión 2024 | P37: Blanca Nubia Torres Quesada | Q37: Mujer | R37: 38248419 | S37: Cr. 80d # 25 sur 21 | T37: 4.618815166790833, -74.17421029323631 | U37: blancanubiatorresquesada@gmail.com | V37: 3104725272 | W37: Tramites | X37: Interno | Y37: En Proceso | Z37: Pendiente | AB37: 45503 | AD37: Asesor | AE37: Angie Benitez | AF37: Bogotá | AG37: Cundinamarca | AH37: 202400533_Blanca Nubia Torres Quesada | AJ37: NO
A38: 2024 | B38: 7 | C38: Julio | D38: 202400539 | E38: Apoyo Ciudadano | F38: Salud | G38: Asesoría legal | H38: Seguimiento a un fallo de tutela donde se reconoce la entrega de procedimientos, citas, valoraciones, suministros de medicamentos e insumos requeridos, historia clínica, tratamiento integral. | I38: Superintendencia de Salud | J38: Castilla | K38: Sur | L38: 08.Kennedy | M38: 08.Kennedy Central | N38: =BUSCARX(R[0]C[-1],CONVENCIONES!R12C1:R42C1,CONVENCIONES!R12C2:R42C2) -> #ERROR! | O38: Gestión 2024 | P38: Esperanza Rodriguez Rodríguez (mamá). Nombre de beneficiario: José sebastian colorado rodriguez. CC.1022439924, edad: 26 años | Q38: Mujer | R38: 51843877 | S38: Carrera 79 no 10d 95 torre 22 apto 301 | T38: 4.64577355426377, -74.13958390354676 | U38: esroro51@hotmail.com | V38: 3174591892 | W38: Tramites | X38: Externos | Y38: Finalizado | Z38: Positivo | AA38: Referida de líder Luz Marina Valenzuela. Diagnóstico: Síndrome de dawn y epilepsia. Tratamiento de la epilepsia. Problemática: no le dan citas ni órdenes, porque lo retiraron del sistema de salud, no le entregaron historia clínica y no le entregan certificado de discapacidad. No le entregan los medicamentos porque lo retiraron del sistema. Les ha tocado pagar médicos particulares y comprar los medicamentos. | AB38: 45503 | AD38: Asesor | AE38: Angie Benitez | AF38: Bogotá | AG38: Cundinamarca | AH38: 202400539_Esperanza Rodríguez Rodríguez. | AJ38: NO
A39: 2024 | B39: 8 | C39: Agosto | D39: 202400554 | E39: Apoyo Ciudadano | F39: ASI | G39: asesoría | H39: Ciudadana solicita asesoría para el ingreso a ruta de atención de un caso de abuso sexual infantil | I39: Secretaría Distrital de la Mujer | J39: Tierrabuena | K39: Sur | L39: 08.Kennedy | M39: N/A | N39: =BUSCARX(R[0]C[-1],CONVENCIONES!R12C1:R42C1,CONVENCIONES!R12C2:R42C2) -> #ERROR! | O39: Gestión 2024 | P39: Claudia Milena Peña Chinchilla | Q39: Mujer | R39: 1.022.957.582 | S39: Cll 2 # 93d-38 | T39: 4.64995909588834, -74.16720645316468 | U39: clauss5227@hotmail.com | V39: 3124907493 | W39: Tramites | X39: Externos | Y39: Finalizado | Z39: Positivo | AA39: Adicional se envía caso al ICBF número de radicado 1764238399 | AB39: 45505 | AC39: 45505 | AD39: Asesor | AE39: Katherine Galindo | AF39: Bogotá | AG39: Cundinamarca | AH39: Claudia Milena Peña Chinchilla | AJ39: NO
A40: 2024 | B40: 8 | C40: Agosto | D40: 202400555 | E40: Apoyo Ciudadano | F40: ASI | H40: Se solicita atención por ingreso a urgencias código blanco | I40: Secretaría Distrital de Salud | J40: Tierrabuena | K40: Sur | L40: 08.Kennedy | M40: N/A | N40: =BUSCARX(R[0]C[-1],CONVENCIONES!R12C1:R42C1,CONVENCIONES!R12C2:R42C2) -> #ERROR! | O40: Gestión 2024 | P40: Claudia Milena Peña Chinchilla | Q40: Mujer | R40: 1.022.957.582 | S40: Cll 2 # 93d-38 | T40: 4.64995909588834, -74.16720645316468 | U40: clauss5227@hotmail.com | V40: 3124907493 | W40: Tramites | X40: Externos | Y40: Finalizado | Z40: Positivo | AA40: Se activó código blanco, aunque la atención no fue tan rápida | AB40: 45505 | AC40: 45524 | AD40: Asesor | AE40: Maicol Quiroga | AF40: Bogotá | AG40: Cundinamarca | AH40: 202400555 Claudia Peña | AJ40: NO
A41: 2024 | B41: 8 | C41: Agosto | D41: 202400557 | E41: Apoyo Ciudadano | F41: Salud | G41: Citas médicas | H41: Consulta con especialista en neurología | I41: Secretaría Distrital de Salud | J41: Vegas de Santa Ana | K41: Sur | L41: 08.Kennedy | M41: 08.Class | N41: =BUSCARX(R[0]C[-1],CONVENCIONES!R12C1:R42C1,CONVENCIONES!R12C2:R42C2) -> #ERROR! | O41: Gestión 2024 | P41: Jhon Javer Gómez Sánchez | Q41: Mujer | R41: 1030645800 | S41: Cra 81j 57A-95 sur | T41: 4.6171796399123695, -74.18151054578377 | U41: Gomezjaver200@gmail.com | V41: 3217458382 | W41: Tramites | X41: Externos | Y41: Finalizado | Z41: Pendiente | AA41: Solicitud de una trabajadora del líder Ricardo de Class - empresa satélite. | AB41: 45506 | AD41: Asesor | AE41: Angie Benitez | AF41: Bogotá | AG41: Cundinamarca | AH41: 202400557_Jhon Javer Gómez Sánchez | AJ41: NO
A42: 2024 | B42: 8 | C42: Agosto | D42: 202400560 | E42: Apoyo Ciudadano | F42: Salud | G42: Entrega de equipos médicos | H42: Autorización de equipo para respirar y operación de cataratas urgente | I42: Superintendencia de Salud | J42: Catalina 2 | K42: Sur | L42: 08.Kennedy | M42: 08.Class | N42: =BUSCARX(R[0]C[-1],CONVENCIONES!R12C1:R42C1,CONVENCIONES!R12C2:R42C2) -> #ERROR! | O42: Gestión 2024 | P42: Jesús María Rubio Moreno | Q42: Mujer | R42: 3160835 | S42: calle 53 sur #77 L 19 | T42: 4.607398309351572, -74.16894927522681 | U42: molinajesus1948@gmail.com | V42: 3203630467 | W42: Tramites | X42: Interno | Y42: En Proceso | Z42: Pendiente | AB42: 02/0//2024 | AD42: Asesor | AE42: Angie Benitez | AF42: Bogotá | AG42: Cundinamarca | AH42: PENDIENTE LINK | AJ42: NO
A43: 2024 | B43: 8 | C43: Agosto | D43: 202400573 | E43: Apoyo Ciudadano | F43: Salud | G43: Procedimientos y exámenes | H43: Procedimiento para tumor: laparotomia exploratoria | I43: Secretaría Distrital de Salud | J43: El amparo | K43: Sur | L43: 08.Kennedy | M43: 08.Kennedy Central | N43: =BUSCARX(R[0]C[-1],CONVENCIONES!R12C1:R42C1,CONVENCIONES!R12C2:R42C2) -> #ERROR! | O43: Gestión 2024 | P43: Flover Alegrias Carbonero | Q43: Hombre | R43: 76231536 | S43: calle 42#80g02 | T43: 4.624592336997663, -74.16324787477785 | U43: floweralegrias979@gmail.com | V43: 311 5010594 | W43: Tramites | X43: Interno | Y43: Finalizado | Z43: Positivo | AB43: 45513 | AD43: Asesor | AE43: Angie Benitez | AF43: Bogotá | AG43: Cundinamarca | AH43: PENDIENTE LINK | AJ43: NO
A44: 2024 | B44: 8 | C44: Agosto | D44: 202400617 | E44: Apoyo Ciudadano | F44: Salud | H44: Solicita una cita para la hija, ya que no hay agenda y deben retirarle el yeso del brazo | I44: Secretaría Distrital de Salud | J44: Villa Nelly | K44: Sur | L44: 08.Kennedy | M44: 08.Kennedy Central | N44: =BUSCARX(R[0]C[-1],CONVENCIONES!R12C1:R42C1,CONVENCIONES!R12C2:R42C2) -> #ERROR! | O44: Gestión 2024 | P44: Emily Luciana Zamora Soler | Q44: Mujer | R44: 1030695465 | S44: Av Cra 80 # 42 c 43 sur | T44: 4.621885468172792, -74.16461452249965 | U44: soler2612@hotmail.com | V44: 3205577764 | W44: Tramites | X44: Interno | Y44: Finalizado | Z44: Positivo | AA44: Se da la atención solicitada a la ciudadano | AB44: 45526 | AD44: Asesor | AE44: Fernando Zamora | AF44: Bogotá | AG44: Cundinamarca | AH44: No registra evidencia | AJ44: NO
A45: 2024 | B45: 8 | C45: Agosto | D45: 202400619 | E45: Apoyo Ciudadano | F45: Educación | H45: Ciudadano requiere información sobre el proceso de condonación del fondo FEST de la secretaría de educación | I45: Secretaría de Educación del Distrito | J45: Villa Nelly | K45: Sur | L45: 08.Kennedy | M45: 08.Kennedy Central | N45: =BUSCARX(R[0]C[-1],CONVENCIONES!R12C1:R42C1,CONVENCIONES!R12C2:R42C2) -> #ERROR! | O45: Gestión 2024 | P45: Fernando José Zamora Camacho | Q45: Hombre | R45: 1000154383 | S45: Av Cra 80 # 42 c 43 sur | T45: 4.621885468172792, -74.16461452249965 | U45: fernandozamora23@gmail.com | V45: 3057909818 | W45: Tramites | X45: Interno | Y45: Finalizado | Z45: Positivo | AA45: Se da la información al ciudadano | AB45: 45526 | AD45: Asesor | AE45: Fernando Zamora | AF45: Bogotá | AG45: Cundinamarca | AH45: No registra evidencia | AJ45: NO
A46: 2024 | B46: 8 | C46: Agosto | D46: 202400629 | E46: Apoyo Ciudadano | F46: Subsidios | H46: Solicuta el bono de adulto mayor | I46: Secretaría Distrital de Integración Social | J46: La Amistad | K46: Sur | L46: 08.Kennedy | M46: N/A | N46: =BUSCARX(R[0]C[-1],CONVENCIONES!R12C1:R42C1,CONVENCIONES!R12C2:R42C2) -> #ERROR! | O46: Gestión 2024 | P46: Javier Salazar | Q46: Hombre | R46: 10216194 | S46: Tv. 78k Cl. 41a Sur | T46: 4.619432539007697, -74.15741903309089 | V46: 3164438876 | W46: Tramites | X46: Externos | Y46: Finalizado | Z46: Positivo | AA46: Se hace el traslado a la entidad | AB46: 45531 | AD46: Asesor | AE46: Fernando Zamora | AF46: Bogotá | AG46: Cundinamarca | AH46: No registra evidencia | AJ46: NO
A47: 2024 | B47: 9 | C47: Septiembre | D47: 202400655 | E47: Apoyo Ciudadano | F47: Pensión | H47: Solicitud: Asesoría si es posible tener la pensión anticipada por hija con discapacidad múltiple. | I47: Congreso | J47: Villa Andrea | K47: Sur | L47: 08.Kennedy | M47: 08.Class | N47: =BUSCARX(R[0]C[-1],CONVENCIONES!R12C1:R42C1,CONVENCIONES!R12C2:R42C2) -> #ERROR! | O47: Gestión 2024 | P47: Heidy Díaz montaña | Q47: Mujer | R47: 52468928 | S47: Cra81i#51b-19sur | T47: 4.6232507314447355, -74.17655846123692 | U47: didita8016@hotmail.com | V47: 3115918677 | W47: Tramites | X47: Interno | Y47: Finalizado | Z47: Pendiente | AA47: Se hizo la asesoría con apoyo de la UTL de la Senadora Ana Paola Agudelo | AB47: 45538 | AC47: 45538 | AD47: Asesor | AE47: Angie Benitez | AF47: Bogotá | AG47: Cundinamarca | AH47: PENDIENTE LINK | AJ47: NO
A48: 2024 | B48: 9 | C48: Septiembre | D48: 202400658 | E48: Apoyo Ciudadano | F48: Salud | H48: Solicita una cita con Ginecología | I48: Secretaría Distrital de Salud | J48: Ciudad Tintal Etapa 1 | K48: Sur | L48: 08.Kennedy | M48: 08.Patio Bonito | N48: =BUSCARX(R[0]C[-1],CONVENCIONES!R12C1:R42C1,CONVENCIONES!R12C2:R42C2) -> #ERROR! | O48: Gestión 2024 | P48: YASMITH CASTILLO VARGAS | Q48: Mujer | R48: 53072797 | S48: Calle 8A # 92-71 Casa 144 | T48: 4.653401033562285, -74.16289061194358 | U48: hanavicolombia@gmail.com | V48: 3227682914 | W48: Tramites | X48: Interno | Y48: Finalizado | Z48: Positivo | AA48: Se hace traslado a la entidad | AB48: 45538 | AD48: Asesor | AE48: Fernando Zamora | AF48: Bogotá | AG48: Cundinamarca | AH48: 202400658_Traslado DP Ciudadano_Yasmith Castillo Vargas | AJ48: NO
A49: 2024 | B49: 9 | C49: Septiembre | D49: 202400674 | E49: Apoyo Ciudadano | F49: Salud | H49: Solicita un medicamento que la EPS no le ha querido entregar | I49: Secretaría Distrital de Salud | K49: Sur | L49: 08.Kennedy | M49: 08.Carvajal | N49: =BUSCARX(R[0]C[-1],CONVENCIONES!R12C1:R42C1,CONVENCIONES!R12C2:R42C2) -> #ERROR! | O49: Gestión 2024 | P49: Valeria Alejandra Pinto Castillo | Q49: Mujer | R49: 1141323104 | S49: cra 18 b #48 62 | V49: 3003060874 | W49: Tramites | X49: Interno | Y49: Finalizado | Z49: Positivo | AA49: Se hace traslado a la entidad | AB49: 45541 | AD49: Asesor | AE49: Fernando Zamora | AF49: Bogotá | AG49: Cundinamarca | AH49: 202400674_Traslado DP Ciudadano_Valeria Alejandra Pinto Castillo | AJ49: NO
A50: 2024 | B50: 9 | C50: Septiembre | D50: 202400680 | E50: Apoyo Ciudadano | F50: Servicio militar | H50: Alternativas para servicio militar | I50: Otras | J50: Ciudad Kennedy occidental | K50: Sur | L50: 08.Kennedy | M50: 08.Kennedy Central | N50: =BUSCARX(R[0]C[-1],CONVENCIONES!R12C1:R42C1,CONVENCIONES!R12C2:R42C2) -> #ERROR! | O50: Gestión 2024 | P50: Jonnier Andrei Moreno Villamil | Q50: Hombre | R50: 1056410139 | S50: Cr 79g #42 d 64 sur | T50: 4.621044686663726, -74.16485883250803 | U50: jonniermoreno20@gmail.com | V50: 3012216643 | W50: Tramites | X50: Interno | Y50: Finalizado | Z50: Positivo | AB50: 45530 | AC50: 45544 | AD50: Asesor | AE50: Angie Benitez | AF50: Bogotá | AG50: Cundinamarca | AH50: 202400680_Jonnier Andrei Moreno Villamil | AJ50: NO
A51: 2024 | B51: 9 | C51: Septiembre | D51: 202400689 | E51: Apoyo Ciudadano | F51: Salud | H51: La ciudadana solicita que la hija sea atendida para que le puedan retirar el yeso | I51: Secretaría Distrital de Salud | J51: Villa Nelly | K51: Sur | L51: 08.Kennedy | M51: 08.Kennedy Central | N51: =BUSCARX(R[0]C[-1],CONVENCIONES!R12C1:R42C1,CONVENCIONES!R12C2:R42C2) -> #ERROR! | O51: Gestión 2024 | P51: Emily Luciana Zamora Soler | Q51: Mujer | R51: 1030695465 | S51: Av Cra 80 # 42 c 43 sur | T51: 4.621885468172792, -74.16461452249965 | U51: soler2612@hotmail.com | V51: 3205577764 | W51: Tramites | X51: Interno | Y51: Finalizado | Z51: Positivo | AA51: Se da la atención solicitada a la ciudadano | AB51: 45545 | AD51: Asesor | AE51: Fernando Zamora | AF51: Bogotá | AG51: Cundinamarca | AH51: No registra evidencia | AJ51: NO
A52: 2024 | B52: 9 | C52: Septiembre | D52: 202400779 | E52: Apoyo Ciudadano | F52: Salud | H52: Solcita una cita con espacialista ya que no le ha sido posible que le asignen una y la persona esta perdiendo la visión | I52: Secretaría Distrital de Salud | J52: Once de Noviembre | K52: Sur | L52: 08.Kennedy | M52: 08.Patio Bonito | N52: =BUSCARX(R[0]C[-1],CONVENCIONES!R12C1:R42C1,CONVENCIONES!R12C2:R42C2) -> #ERROR! | O52: Gestión 2024 | P52: Digna María Vargas Chala | Q52: Mujer | R52: 25533998 | S52: Cra 29A # 75-30 | T52: 4.6691489859988, -74.0699650387149 | U52: hanavicolombia@gmail.com dinavar2852@gmail.com | V52: 3108548307 | W52: Tramites | X52: Interno | Y52: Finalizado | Z52: Positivo | AA52: Se hace traslado a la entidad | AB52: 45565 | AD52: Asesor | AE52: Fernando Zamora | AF52: Bogotá | AG52: Cundinamarca | AH52: 202400779_Traslado DP Ciudadano_Digna María Vargas Chala | AJ52: NO
A53: 2024 | B53: 10 | C53: Octubre | D53: 202400818 | E53: Apoyo Ciudadano | F53: Salud | G53: Asesoría legal | H53: Seguimiento a un fallo de tutela de segunda instancia, donde se reconoce la entrega de procedimientos, citas, valoraciones, suministros de medicamentos e insumos requeridos, historia clínica, tratamiento integral, reafilación y ceritificado de discapacidad a una persona con síndrome de Down y epilepsia | I53: Superintendencia de Salud | J53: Castilla | K53: Sur | L53: 08.Kennedy | M53: 08.Kennedy Central | N53: =BUSCARX(R[0]C[-1],CONVENCIONES!R12C1:R42C1,CONVENCIONES!R12C2:R42C2) -> #ERROR! | O53: Gestión 2024 | P53: Esperanza Rodriguez Rodríguez (mamá). Nombre de beneficiario: José sebastian colorado rodriguez. CC.1022439924, edad: 26 años | Q53: Mujer | R53: 51843877 | S53: Carrera 79 no 10d 95 torre 22 apto 301 | T53: 4.64577355426377, -74.13958390354676 | U53: esroro51@hotmail.com | V53: 3174591892 | W53: Tramites | X53: Externos | Y53: Finalizado | Z53: Positivo | AA53: Referida de líder Luz Marina Valenzuela. Diagnóstico: Síndrome de dawn y epilepsia. Tratamiento de la epilepsia. Problemática: no le dan citas ni órdenes, porque lo retiraron del sistema de salud, no le entregaron historia clínica y no le entregan certificado de discapacidad. No le entregan los medicamentos porque lo retiraron del sistema. Les ha tocado pagar médicos particulares y comprar los medicamentos. | AB53: 45572 | AD53: Asesor | AE53: Angie Benitez | AF53: Bogotá | AG53: Cundinamarca | AH53: 202400818_Esperanza Rodriguez Rodríguez | AJ53: NO
A54: 2024 | B54: 10 | C54: Octubre | D54: 202400845 | E54: Apoyo Ciudadano | F54: Educación | H54: Cupo escolar a estudiante con discapacidad cognitiva, la institución de interés es IED Carlos Artura Torres | I54: Secretaría de Educación del Distrito | J54: Villa Andrea Kennedy | K54: Sur | L54: 08.Kennedy | M54: 08.Class | N54: =BUSCARX(R[0]C[-1],CONVENCIONES!R12C1:R42C1,CONVENCIONES!R12C2:R42C2) -> #ERROR! | O54: Gestión 2024 | P54: Nombre de acudiente: Heidy Díaz Montaña Estudiante: Danna Sofia Bernal Díaz | Q54: Mujer | R54: 52468928 | S54: Cra 81i #51b-19sur | T54: 4.62188485449497, -74.17577730957824 | U54: didita8016@hotmail.com | V54: 3115918677 | W54: Tramites | X54: Interno | Y54: Pendiente | Z54: Positivo | AB54: 45574 | AD54: Asesor | AE54: Angie Benitez | AF54: Bogotá | AG54: Cundinamarca | AH54: PENDIENTE LINK | AJ54: NO
A55: 2024 | B55: 10 | C55: Octubre | D55: 202400899 | E55: Apoyo Ciudadano | F55: Salud | G55: Citas médicas | H55: Solicitud: cita con especialista de córnea para que pueda revisar la ecografía ocular y se pueda autorizar la cirugía de trasplante de córnea. | I55: Secretaría Distrital de Salud | J55: Hogares colombianos | K55: Sur | L55: 08.Kennedy | M55: 08.Kennedy Central | N55: =BUSCARX(R[0]C[-1],CONVENCIONES!R12C1:R42C1,CONVENCIONES!R12C2:R42C2) -> #ERROR! | O55: Gestión 2024 | P55: Andrés Felipe Cortés Pérez | Q55: Hombre | R55: 1.030.649.545 | S55: calle 35 b sur #78 L 10 | T55: 4.626198766914959, -74.1522995172186 | U55: andres.perez051913@hotmail.com | V55: 3108285941 | W55: Tramites | X55: Interno | Y55: En Proceso | Z55: Pendiente | AA55: El caso llegó a través de la mamá Nidia Peréz 3153813601. | AB55: 45590 | AD55: Asesor | AE55: Angie Benitez | AF55: Bogotá | AG55: Cundinamarca | AH55: 202400899_Andrés Felipe Cortés Pérez | AJ55: NO
A56: 2024 | B56: 10 | C56: Octubre | D56: 202400901 | E56: Apoyo Ciudadano | F56: Emprendimiento y empleo | H56: Permiso para venta informal al frente de su casa en espacio público los fines de semana. | I56: Secretaría Distrital de Desarrollo Económico | J56: Jackeline | K56: Sur | L56: 08.Kennedy | M56: 08.Kennedy Central | N56: =BUSCARX(R[0]C[-1],CONVENCIONES!R12C1:R42C1,CONVENCIONES!R12C2:R42C2) -> #ERROR! | O56: Gestión 2024 | P56: Nidia Flor Alba Pulido Bravo | Q56: Mujer | R56: 23876086 | S56: Carrera 77V #46 B 61 sur | T56: 4.609503874779034, -74.1639743845991 | U56: nidiapulido575@gmail.com | V56: 3027065819 | W56: Tramites | X56: Interno | Y56: Pendiente | Z56: Pendiente | AB56: 45589 | AD56: Asesor | AE56: Angie Benitez | AF56: Bogotá | AG56: Cundinamarca | AH56: PENDIENTE LINK | AJ56: NO
A57: 2024 | B57: 11 | C57: Noviembre | D57: 202400945 | E57: Apoyo Ciudadano | F57: Salud | G57: Citas médicas | H57: Solicitud: Atencion Prioritoaria para Oncologia y Radioterapia | I57: Secretaría Distrital de Salud | J57: Patio Bonito | K57: Sur | L57: 08.Kennedy | M57: 08.Kennedy Central | N57: =BUSCARX(R[0]C[-1],CONVENCIONES!R12C1:R42C1,CONVENCIONES!R12C2:R42C2) -> #ERROR! | O57: Gestión 2024 | P57: Miguel Antonio Garzon Martinez | Q57: Hombre | R57: 19349545 | S57: Carrera 88D Nro. 34A - 50 Sur | T57: 4.640730736949674, -74.16461974789914 | U57: dinalinda5@hotma.com | V57: 3108186090 - 3143934301 | W57: Tramites | X57: Externos | Y57: Finalizado | Z57: Positivo | AB57: 45601 | AC57: 45637 | AD57: Asesor | AE57: Angie Benitez | AF57: Bogotá | AG57: Cundinamarca | AH57: 2024009445_Miguel Antonio Garzon Martinez | AJ57: NO
A58: 2024 | B58: 11 | C58: Noviembre | D58: 202401021 | E58: Apoyo Ciudadano | F58: Salud | G58: Procedimientos y exámenes | H58: Solicitud salud: Electronistagmografía o fotoelectronistagmografia. Porque dicen que no hay agenda. | I58: Secretaría Distrital de Salud | J58: Ciudad de Cali | K58: Sur | L58: 08.Kennedy | M58: 08.Kennedy Central | N58: =BUSCARX(R[0]C[-1],CONVENCIONES!R12C1:R42C1,CONVENCIONES!R12C2:R42C2) -> #ERROR! | O58: Gestión 2024 | P58: Celia Matilde Forero Rojas | Q58: Mujer | R58: 28.190.396 | S58: Cra 86c bis No 42-51 sur | T58: 4.632149188331498, -74.16842888638683 | U58: Luzmari2909@hotmail.com | V58: 3213032240 | W58: Tramites | X58: Interno | Y58: Finalizado | Z58: Positivo | AA58: Es la madre de Emilse y Luz Marina Valenzuela | AB58: 45623 | AC58: 45631 | AD58: Asesor | AE58: Angie Benitez | AF58: Bogotá | AG58: Cundinamarca | AH58: 202401021_Celia Matilde Forero Rojas | AJ58: NO
A59: 2024 | B59: 11 | C59: Noviembre | D59: 202401024 | E59: Apoyo Ciudadano | F59: Salud | G59: Procedimientos y exámenes | H59: Solicitud salud: procedimiento adenomectomía o protatectomía transversal. Cirugía por Inflamación de la próstata | I59: Secretaría Distrital de Salud | J59: Timiza | K59: Sur | L59: 08.Kennedy | M59: 08.Kennedy Central | N59: =BUSCARX(R[0]C[-1],CONVENCIONES!R12C1:R42C1,CONVENCIONES!R12C2:R42C2) -> #ERROR! | O59: Gestión 2024 | P59: Héctor Enrique Prieto Guasca | Q59: Hombre | R59: 11376966 | S59: Carrera 72 L # 50 48 sur | T59: 4.609958391954326, -74.1483186367533 | U59: Eprieto671@gmail.com | V59: 3124651116 | W59: Tramites | X59: Interno | Y59: Finalizado | Z59: Positivo | AA59: Se hace traslado a través de oficio, fue por solicitud de la delegada política de Kennedy Central. | AB59: 45623 | AC59: 45631 | AD59: Asesor | AE59: Angie Benitez | AF59: Bogotá | AG59: Cundinamarca | AH59: 202401024_Héctor Enrique Prieto Guasca | AJ59: NO
A60: 2024 | B60: 12 | C60: Diciembre | D60: 202401059 | E60: Apoyo Ciudadano | F60: Educación | H60: Solicitud cupo por falla en el aplicativo con el documento de identidad | I60: Secretaría de Educación del Distrito | J60: Roma | K60: Sur | L60: 08.Kennedy | M60: N/A | N60: =BUSCARX(R[0]C[-1],CONVENCIONES!R12C1:R42C1,CONVENCIONES!R12C2:R42C2) -> #ERROR! | O60: Gestión 2024 | P60: Nathin Vanessa Leal Moscoso | Q60: Mujer | R60: 1030571557 | S60: Cll57a sur #81-28 | T60: 4.616994655590592, -74.17976931686992 | U60: moscosovanessa47@gmail.com | V60: 3142142372 | W60: Tramites | X60: Externos | Y60: Finalizado | Z60: Positivo | AA60: Se menciona que el trámite se realiza a partir del 20 de enero | AB60: 45632 | AC60: 45641 | AD60: Asesor | AE60: Maicol Quiroga | AF60: Bogotá | AG60: Cundinamarca | AH60: 202001059 Nathin Vanessa Leal Moscoso | AJ60: NO
A61: 2024 | B61: 12 | C61: Diciembre | D61: 202401077 | E61: Apoyo Ciudadano | F61: Salud | H61: Solicitud: Adquirir silla de ruedas | I61: Secretaría Distrital de Salud | J61: Prados de Castilla | K61: Sur | L61: 08.Kennedy | M61: 08.Kennedy Central | N61: =BUSCARX(R[0]C[-1],CONVENCIONES!R12C1:R42C1,CONVENCIONES!R12C2:R42C2) -> #ERROR! | O61: Gestión 2024 | P61: Merardo Beltrán González | Q61: Hombre | R61: 17199831 | S61: Cra 90 # 6 a 47 | T61: 4.650913110462878, -74.15816209814646 | U61: Idalidmendezsamchez@gmail.com | V61: 3158679628 | W61: Tramites | X61: Interno | Y61: En Proceso | Z61: Pendiente | AA61: Se realiza traslado a la entidad | AB61: 45637 | AD61: Asesor | AE61: Luz Marina Fino | AF61: Bogotá | AG61: Cundinamarca | AH61: Traslado D.P Merardo Beltrán González - 202401077 | AJ61: NO
A62: 2024 | B62: 12 | C62: Diciembre | D62: 202401078 | E62: Apoyo Ciudadano | F62: Salud | H62: Solicitud: silla de ruedas | I62: Alcaldias Locales | J62: Prados de Castilla | L62: 08.Kennedy | M62: 08.Kennedy Central | N62: =BUSCARX(R[0]C[-1],CONVENCIONES!R12C1:R42C1,CONVENCIONES!R12C2:R42C2) -> #ERROR! | O62: Gestión 2024 | P62: Merardo Beltrán González | Q62: Hombre | R62: 17199831 | S62: Cra 90 # 6 a 47 | T62: 4.650913110462878, -74.15816209814647 | U62: Idalidmendezsamchez@gmail.com | V62: 3158679628 | W62: Tramites | X62: Interno | Y62: En Proceso | Z62: Pendiente | AA62: Se realiza traslado a la entidad | AB62: 45638 | AD62: Asesor | AE62: Luz Marina Fino | AF62: Bogotá | AG62: Cundinamarca | AH62: Traslado D.P Merardo Beltrán González - 202401077 | AJ62: NO
A63: 2024 | B63: 12 | C63: Diciembre | D63: 202401079 | E63: Apoyo Ciudadano | F63: Servicios públicos | H63: Solicitud: Dar respuesta y solución al radicado E-2024-112137 de la comunidad Pinar del Rio 2do sector zona 8 Kennedy, sobre la problemática de taponamiento de sumideros de aguas lluvias en Calle 40 bis B sur desde la carrera 82 hasta la carrera 86 avenida Ciudad de Cali. | I63: Empresa de Acueducto y Alcantarillado de Bogotá -ESP | J63: Pinar del Rio 2do sector | K63: Sur | L63: 08.Kennedy | M63: 08.Kennedy Central | N63: =BUSCARX(R[0]C[-1],CONVENCIONES!R12C1:R42C1,CONVENCIONES!R12C2:R42C2) -> #ERROR! | O63: Gestión 2024 | P63: Alonso de Jesús Correa Sanches | Q63: Hombre | R63: 70725282 | S63: Carrera 82 D No. 40 – 62 sur | T63: 4.6136946890630695, -74.19736157559124 | U63: cb08kennedyalonso@gmail.com | V63: 3134728300 | W63: Tramites | X63: Interno | Y63: En Proceso | Z63: Pendiente | AB63: 45637 | AD63: Asesor | AE63: Angie Benitez | AF63: Bogotá | AG63: Cundinamarca | AH63: 202401079_Alonso de Jesús Correa Sanches | AJ63: NO
A64: 2024 | B64: 12 | C64: Diciembre | D64: 202401100 | E64: Apoyo Ciudadano | F64: Salud | G64: Procedimientos y exámenes | H64: Traslado de salud: Solicitud de adenomectomía por ablación de próstata. | I64: Secretaría Distrital de Salud | J64: Palenque | K64: Sur | L64: 08.Kennedy | M64: 08.Kennedy Central | N64: =BUSCARX(R[0]C[-1],CONVENCIONES!R12C1:R42C1,CONVENCIONES!R12C2:R42C2) -> #ERROR! | O64: Gestión 2024 | P64: Asdrúbal Novoa Villalba | Q64: Mujer | R64: 19366572 | S64: Carrera 78 sur #42 a 15 | T64: 4.611547136394427, -74.16001694598356 | U64: asnvill@yahoo.es | V64: 3102295199 - 3005544552 | W64: Tramites | X64: Interno | Y64: Finalizado | Z64: Positivo | AA64: Se hace traslado a través de enlace | AB64: 45643 | AD64: Asesor | AE64: Angie Benitez | AF64: Bogotá | AG64: Cundinamarca | AH64: 202401100_Asdrúbal Novoa Villalba | AJ64: NO
A65: 2024 | B65: 12 | C65: Diciembre | D65: 202401110 | E65: Apoyo Ciudadano | F65: Subsidios | H65: Traslado derecho de petición para revisión del caso, ya que hace un mes le dieron la tarjeta y no ha podido retirar su subsidio | I65: Secretaría Distrital de Integración Social | J65: Las Acacias | K65: Sur | L65: 08.Kennedy | M65: 08.Patio Bonito | N65: =BUSCARX(R[0]C[-1],CONVENCIONES!R12C1:R42C1,CONVENCIONES!R12C2:R42C2) -> #ERROR! | O65: Gestión 2024 | P65: Alba Salinas Torres | Q65: Mujer | R65: 51569838 | S65: Calle 40 # 99 d 14 sur | T65: 4.649753904708582, -74.17608594574662 | U65: albasalinas1059@gmail.com | V65: 3144623780 | W65: Tramites | X65: Interno | Y65: Finalizado | Z65: Positivo | AA65: Se envia por medio del enlace, [RESPUESTA] "En atención al caso de la ciudadana Alba Salinas Torres, identificada con CC No. 51.569.838 a quien se ubica en el número 3144623780, correo electrónico: albasalinas1059@gmail.com, reside en la dirección: Calle 40 No. 99 D - 14 Sur, Barrio: Las Acacias, Patio Bonito; y manifiesta que " vivía en la localidad de Ciudad Bolívar y recibía el subsidio tipo c, ahora vive en la localidad de Kennedy, pero cuando fue a retirar le dicen que aparece como inactiva ", razón por la que requiere solución por parte de la Secretaría Distrital de Integración Social. En este sentido, los profesionales de atención de la Subdirección Local de Kennedy verificaron el Sistema de Información y Registro de Beneficiarios de la Secretaría Distrital de Integración Social – SIRBE, se evidenció que la ciudadana actualmente no se encuentra en atención de los servicios sociales que presta la Entidad. No obstante, se identificó que la ciudadana fue beneficiaria desde el Proyecto de Inversión 7937 “G eneración de oportunidades para la inclusión social y productiva de las personas mayores en Bogotá D.C. ” Servicio de “ Apoyos Económicos para Persona Mayor ” en la localidad de Ciudad Bolívar hasta el 27 de Noviembre de 2024, fecha en la cual fue egresada del Servicio por encontrarse inscrita y activa como beneficiaria del programa Colombia Mayor en el municipio de Fresno del Departamento de Tolima. Así las cosas, con el fin de brindar atención al caso, el día 24 de diciembre de 2024, se estableció contacto con la ciudadana al número abonado, logrando concretar una cita para el mismo día en las instalaciones del Centro de Desarrollo Comunitario Kennedy - CDC- ubicado en la Carrera 80 No.43- 43 Sur. Donde una vez cumplida la cita por parte de la ciudadana, se logró realizar proceso de focalización para su ingreso desde el Proyecto de Inversión 7953 “ Generación del bien-estar alimentario y nutricional en Bogotá D.C" . Servicio de “ Comedores Comunitarios ”. De igual modo, dado que la ciudadana actualmente reúne las condiciones necesarias que configuran una emergencia social, se le informó que puede acercarse al nuevamente al CDC a partir del 15 de enero del 2025 para realizar atención desde el servicio de ”Respuesta Social” mediante el cual le será entregado un bono canjeable por alimentos por valor de $150.000." | AB65: 45644 | AD65: Asesor | AE65: Fernando Zamora | AF65: Bogotá | AG65: Cundinamarca | AH65: No registra evidencia | AJ65: NO
A66: 2025 | B66: 1 | C66: Enero | D66: 202500001 | E66: Apoyo Ciudadano | F66: Educación | H66: El ciudadano solicita la condonación o la disminción de intereses por la devolución del subsidio de sostenimiento de Jovenes a la E | I66: Agencia Atenea | K66: Sur | L66: 08.Kennedy | M66: 08.Kennedy Central | N66: =BUSCARX(R[0]C[-1],CONVENCIONES!R12C1:R42C1,CONVENCIONES!R12C2:R42C2) -> #ERROR! | O66: N/A | P66: Jhon Freddy Ortega Villalobos | Q66: Hombre | R66: 1007866539 | U66: jhonvicorte@hotmail.com | V66: 3237132604 | W66: Tramites | X66: Interno | Y66: En Proceso | Z66: Pendiente | AB66: 45660 | AD66: Asesor | AE66: Fernando Zamora | AF66: Bogotá | AG66: Cundinamarca | AH66: 202500001_El ciudadano solicita la condonación o la disminción de intereses por la devolución del subsidio de sostenimiento de Jovenes a la E | AJ66: NO
A67: 2025 | B67: 1 | C67: Enero | D67: 202500002 | E67: Apoyo Ciudadano | F67: Subsidios | H67: El ciudadano solicita asistencia social ya que esta pasando por una situación dificil economicamente, tiene un bebe de pocos años de edad | I67: Secretaría Distrital de Integración Social | K67: Sur | L67: 08.Kennedy | M67: 08.Kennedy Central | N67: =BUSCARX(R[0]C[-1],CONVENCIONES!R12C1:R42C1,CONVENCIONES!R12C2:R42C2) -> #ERROR! | O67: N/A | P67: Jhon Freddy Ortega Villalobos | Q67: Hombre | R67: 1007866539 | U67: jhonvicorte@hotmail.com | V67: 3237132604 | W67: Tramites | X67: Interno | Y67: En Proceso | Z67: Pendiente | AB67: 45660 | AD67: Asesor | AE67: Fernando Zamora | AF67: Bogotá | AG67: Cundinamarca | AH67: 202500002_El ciudadano solicita asistencia social ya que esta pasando por una situación dificil economicamente, tiene un bebe de pocos años de edad | AJ67: NO
A68: 2025 | B68: 1 | C68: Enero | D68: 202500003 | E68: Apoyo Ciudadano | F68: Educación | H68: Solicitud de traslado de colegio. El estudiandiente se encontraba en Tom Adam’s y solicita el traslado para el Colegio manuel cepeda. | I68: Secretaría de Educación del Distrito | J68: Casablanca | K68: Sur | L68: 08.Kennedy | M68: 08.Class | N68: =BUSCARX(R[0]C[-1],CONVENCIONES!R12C1:R42C1,CONVENCIONES!R12C2:R42C2) -> #ERROR! | O68: N/A | P68: Estudiante: Faber Jafet Lopera Sierra Acudiente: Ana Maryeth Sierra Armero | Q68: Hombre | R68: TI. 1.104.946.542 | S68: Calle 48a Sur #79b-15 | T68: 4.616405120645921, -74.1685495054107 | U68: faberloperasierra@gmail.com | V68: 320 3029490 | W68: Tramites | X68: Interno | Y68: Finalizado | Z68: Positivo | AB68: 45662 | AC68: 45671 | AD68: Asesor | AE68: Angie Benitez | AF68: Bogotá | AG68: Cundinamarca | AH68: 202500003_Faber Jafet Lopera Sierra | AJ68: NO
A69: 2025 | B69: 1 | C69: Enero | D69: 202500005 | E69: Apoyo Ciudadano | F69: Salud | G69: Citas médicas | H69: Solicitud: Citas médicas para tratamiento oncológico | I69: Secretaría Distrital de Salud | J69: Tierra Buena | K69: Sur | L69: 08.Kennedy | M69: 08.Patio Bonito | N69: =BUSCARX(R[0]C[-1],CONVENCIONES!R12C1:R42C1,CONVENCIONES!R12C2:R42C2) -> #ERROR! | O69: Gestión 2025 | P69: Óscar Oviedo Acero | Q69: Hombre | R69: 11312952 | S69: Carrera 98 # 0 - 41 | T69: 4.65169742970834, -74.17040005767151 | U69: olosorio1972@gmail.com | V69: 3227841129 | W69: Tramites | X69: Interno | Y69: Finalizado | Z69: Pendiente | AA69: Se solicitó a través de enlace el 24 de diciembre de 2024, sin embargo, no se ha hecho el requerimiento. La persona se encuentra en UCI el 7/01/2025, se procede a hacer oficio con copia a supersalud para que se le garanticen todas las atenciones. | AB69: 45664 | AD69: Asesor | AE69: Angie Benitez | AF69: Bogotá | AG69: Cundinamarca | AH69: 202500005_Óscar Oviedo Acero | AJ69: NO
A70: 2025 | B70: 1 | C70: Enero | D70: 202500015 | E70: Apoyo Ciudadano | F70: Subsidios | H70: Asesoría jurídica a Nicol Tatiana Laverde Prado sobre cómo reclamar una indemnización por seguro SOAT a causa de la muerte de su padre por accidente de tránsito. | I70: Otras | J70: Palenque | K70: Sur | L70: 08.Kennedy | M70: 08.Kennedy Central | N70: =BUSCARX(R[0]C[-1],CONVENCIONES!R12C1:R42C1,CONVENCIONES!R12C2:R42C2) -> #ERROR! | O70: Gestión 2025 | P70: Nicol Tatiana Laverde Prado | Q70: Mujer | R70: 1007107298 | S70: Calle 42 f sur #78 b 28 | T70: 4.613342770999458, -74.16011984603308 | U70: niicoltaatiana22@gmail.com | V70: 3222126835 | W70: Tramites | X70: Interno | Y70: Finalizado | Z70: Positivo | AB70: 45645 | AC70: 45670 | AD70: Asesor | AE70: Angie Benitez | AF70: Bogotá | AG70: Cundinamarca | AH70: 202500015_Nicol Tatiana Laverde Prado | AJ70: NO
A71: 2025 | B71: 1 | C71: Enero | D71: 202500072 | E71: Apoyo Ciudadano | F71: Educación | G71: Cupos escolares | H71: Solicitud: cambio de jornada tarde a la mañana por temas de seguridad de la menor y por facilidad de los padres debido a sus trabajos. | I71: Secretaría de Educación del Distrito | J71: Villa Andrea | K71: Sur | L71: 08.Kennedy | M71: 08.Class | N71: =BUSCARX(R[0]C[-1],CONVENCIONES!R12C1:R42C1,CONVENCIONES!R12C2:R42C2) -> #ERROR! | O71: Gestión 2025 | P71: Mayelli Abonia | Q71: Mujer | R71: 29507889 | S71: Calle 53a # 81- 21sur | T71: 4.618911218396922, -74.1754592319063 | U71: mayaboca17@gmail.com | V71: 3147962210 | W71: Tramites | X71: Interno | Y71: En Proceso | Z71: Pendiente | AB71: 45686 | AD71: Asesor | AE71: Angie Benitez | AF71: Bogotá | AG71: Cundinamarca | AH71: 202500072_Mayelli Abonia | AJ71: NO
A72: 2025 | B72: 2 | C72: Febrero | D72: 202500101 | E72: Apoyo Ciudadano | F72: Educación | G72: Cupos escolares | H72: La Sra Natalia Zapata solicita un cupo a un colegio cercano ya que en donde le dieron cupo queda muy lejos al lugar de residencia | I72: Secretaría de Educación del Distrito | J72: Patio Bonito | K72: Sur | L72: 08.Kennedy | M72: 08.Patio Bonito | N72: =BUSCARX(R[0]C[-1],CONVENCIONES!R12C1:R42C1,CONVENCIONES!R12C2:R42C2) -> #ERROR! | O72: Gestión 2025 | P72: Natalia Zapata | Q72: Mujer | R72: 1000227362 | S72: carrera 98 Bis # 42A93 sur | T72: 4.6461056119038835, -74.17790138992412 | U72: n/A | V72: 3244812819 | W72: Tramites | X72: Externos | Y72: Finalizado | Z72: Negativo | AB72: 45693 | AD72: Asesor | AE72: Fernando Zamora | AF72: Bogotá | AG72: Cundinamarca | AH72: PENDIENTE LINK | AJ72: NO
A73: 2025 | B73: 2 | C73: Febrero | D73: 202500162 | E73: Apoyo Ciudadano | F73: Salud | G73: Procedimientos y exámenes | H73: Solicitud: - Ecografía de abdomen total. - Radiografía de senos paranasales. | I73: Secretaría Distrital de Salud | J73: San Andres | K73: Sur | L73: 08.Kennedy | M73: 08.Carvajal | N73: =BUSCARX(R[0]C[-1],CONVENCIONES!R12C1:R42C1,CONVENCIONES!R12C2:R42C2) -> #ERROR! | O73: Gestión 2025 | P73: Jose Alzamora Hernández | Q73: Hombre | R73: 73090457 | S73: Calle 43 a sur #72 a 73 | T73: 4.6022865607799055, -74.1472455644179 | U73: josealzamorah@gmail.com | V73: celular: 3223761671 Celular esposa: 3108723215 | W73: Tramites | X73: Interno | Y73: En Proceso | Z73: Pendiente | AB73: 45701 | AD73: Asesor | AE73: Angie Benitez | AF73: Bogotá | AG73: Cundinamarca | AH73: 202500162_ Jose Alzamora Hernández | AJ73: NO
A74: 2025 | B74: 2 | C74: Febrero | D74: 202500207 | E74: Apoyo Ciudadano | F74: Educación | G74: Cupo | H74: Solicita un cupo escolar | I74: Secretaría de Educación del Distrito | J74: Osorio | K74: Sur | L74: 08.Kennedy | M74: 08.Kennedy Central | N74: =BUSCARX(R[0]C[-1],CONVENCIONES!R12C1:R42C1,CONVENCIONES!R12C2:R42C2) -> #ERROR! | O74: Gestión 2025 | P74: Solangie Martinez Rubiano | Q74: Mujer | R74: 52526336 | S74: Calle 2 #93D-45 | U74: alejo21475@gmail.com | V74: 3027520890 | W74: Tramites | X74: Interno | Y74: En Proceso | Z74: Pendiente | AB74: 45713 | AF74: Bogotá | AG74: Cundinamarca | AH74: PENDIENTE LINK | AJ74: NO
A75: 2025 | B75: 2 | C75: Febrero | D75: 202500221 | E75: Apoyo Ciudadano | F75: Salud | G75: Citas médicas | H75: biopsia de lengua ensivional | I75: Secretaría Distrital de Salud | J75: class | K75: Sur | L75: 08.Kennedy | M75: 08.Class | N75: =BUSCARX(R[0]C[-1],CONVENCIONES!R12C1:R42C1,CONVENCIONES!R12C2:R42C2) -> #ERROR! | O75: Gestión 2025 | P75: Briceida callejas | Q75: Mujer | R75: 33815877 | S75: calle 51 sur # 79d- 09 | T75: 4.616805259678949, -74.16987020361948 | U75: brisscallejas.g@hotmail.com | V75: 3112518910 | W75: Tramites | X75: Interno | Y75: Finalizado | Z75: Positivo | AB75: 45716 | AD75: Asesor | AE75: Katherine Galindo | AF75: Bogotá | AG75: Cundinamarca | AH75: Briceida callejas | AJ75: NO
A76: 2025 | B76: 3 | C76: Marzo | D76: 202500285 | E76: Apoyo Ciudadano | F76: Salud | G76: Procedimientos y exámenes | H76: Solicitu de TAC de columna cervical | I76: Secretaría Distrital de Salud | J76: Patio Bonito | K76: Sur | L76: 08.Kennedy | M76: 08.Patio Bonito | N76: =BUSCARX(R[0]C[-1],CONVENCIONES!R12C1:R42C1,CONVENCIONES!R12C2:R42C2) -> #ERROR! | O76: Gestión 2025 | P76: Deivid Enrique Barranco Guerrero | Q76: Hombre | R76: 72212900 | S76: Carrera 88 N 5-41 | T76: 4.6411717255702865, -74.16212016339438 | U76: barrancoenrique15@gmail.com. | V76: 322384632 | W76: Tramites | X76: Interno | Y76: En Proceso | Z76: Pendiente | AB76: 45726 | AD76: Asesor | AE76: Katherine Galindo | AF76: Bogotá | AG76: Cundinamarca | AH76: PENDIENTE LINK | AJ76: NO
A77: 2025 | B77: 3 | C77: Marzo | D77: 202500328 | E77: Apoyo Ciudadano | F77: Salud | G77: Programación de cirugías | H77: Solicitud: gestionar agenda para una cirugía priooritaria, pero no hay agenda. El procedimiento es una glosectomia radical via abierta. | I77: Secretaría Distrital de Salud | J77: Casa blanca | K77: Sur | L77: 08.Kennedy | M77: 08.Class | N77: =BUSCARX(R[0]C[-1],CONVENCIONES!R12C1:R42C1,CONVENCIONES!R12C2:R42C2) -> #ERROR! | O77: Gestión 2025 | P77: Briceda Callejas Gonzalez | Q77: Mujer | R77: 33815877 | S77: Calle 51 sur 79 D 09 Bloque FA | 5 apto 304 | T77: 4.616078367822084, -74.17077445989494 | U77: brisscallejas.g@hotmail.com | V77: 3112518910 | W77: Tramites | X77: Interno | Y77: Finalizado | Z77: Positivo | AB77: 45730 | AD77: Asesor | AE77: Angie Benitez | AF77: Bogotá | AG77: Cundinamarca | AH77: 202500328_Briceda Callejas Gonzalez | AJ77: NO
A78: 2025 | B78: 3 | C78: Marzo | D78: 202500334 | E78: Apoyo Ciudadano | F78: Niñez | G78: Violencia Intrafamiliar | H78: Solicitud de verificación del proceso de restablecimiento de derechos de un menor de edad y de la resolución emitida por la Comisaría de Familia de Medellín, remitida a la entidad competente. | I78: Personería Distrital | J78: Boita | K78: Sur | L78: 08.Kennedy | M78: N/A | N78: =BUSCARX(R[0]C[-1],CONVENCIONES!R12C1:R42C1,CONVENCIONES!R12C2:R42C2) -> #ERROR! | O78: Gestión 2025 | P78: Andres Felipe Montañez | Q78: Hombre | R78: 1000724429 | S78: calle 48 a sur # 72j - 70 | T78: 4.602860103144236, -74.15209881728678 | U78: N/A | V78: 3202190545 | W78: Niñez | X78: Externos | Y78: En Proceso | Z78: Pendiente | AB78: 45733 | AD78: Asesor | AE78: Katherine Galindo | AF78: Bogotá | AG78: Cundinamarca | AH78: PENDIENTE LINK | AJ78: NO
A79: 2025 | B79: 3 | C79: Marzo | D79: 202500398 | E79: Apoyo Ciudadano | F79: Salud | G79: Procedimientos y exámenes | H79: Solicitudes: 1. Trámite para certificación médica de discapacidad emitida por la EPS Salud Total. 2. Lectura de examen para generar un dictamen médico oficial, lleva 8 meses tratando de que le den el diagnóstico. | I79: Secretaría Distrital de Salud | J79: Catalina | K79: Sur | L79: 08.Kennedy | M79: 08.Kennedy Central | N79: =BUSCARX(R[0]C[-1],CONVENCIONES!R12C1:R42C1,CONVENCIONES!R12C2:R42C2) -> #ERROR! | O79: Gestión 2025 | P79: Jairo Andrés Rodríguez | Q79: Hombre | R79: 1014181526 | S79: Calle 54 a sur #78 f 20 | T79: 4.610765101226499, -74.1702505037046 | U79: andresrodriguez.19@outlook.com | V79: 3173123134 | W79: Tramites | X79: Interno | Y79: En Proceso | Z79: Pendiente | AB79: 45744 | AD79: Asesor | AE79: Angie Benitez | AF79: Bogotá | AG79: Cundinamarca | AH79: 202500398_Jairo Andrés Rodríguez | AJ79: NO
A80: 2025 | B80: 4 | C80: Abril | D80: 202500436 | E80: Apoyo Ciudadano | F80: Salud | G80: Citas médicas | H80: Desde el 18 de noviembre de 2024 se dio inicio al proceso de solicitud para la cirugía de cambio de rodilla izquierda cementada. La paciente requiere agendar nuevamente las citas médicas necesarias para realizar los exámenes prequirúrgicos y poder proceder con la intervención. Está afiliada al régimen subsidiado, bajo la EPS Coosalud, pero en Bogotá es atendida por la IPS SUDRED según directriz de la misma EPS | I80: Secretaría Distrital de Salud | J80: Barranquillita | K80: Sur | L80: 08.Kennedy | M80: 08.Patio Bonito | N80: =BUSCARX(R[0]C[-1],CONVENCIONES!R12C1:R42C1,CONVENCIONES!R12C2:R42C2) -> #ERROR! | O80: Gestión 2025 | P80: Maria Soleda Moreno de Quiñonez | Q80: Mujer | R80: 23443078 | S80: carrera 86 c bis Nº 40-45 sur | T80: 4.633789564504882, -74.16584100341763 | U80: erikapuertas06@gmail.com | V80: 3208285574 | W80: Tramites | X80: Interno | Y80: En Proceso | Z80: Pendiente | AB80: 45751 | AD80: Asesor | AE80: Fernando Zamora | AF80: Bogotá | AG80: Cundinamarca | AH80: PENDIENTE LINK | AJ80: NO
A81: 2025 | B81: 4 | C81: Abril | D81: 202500582 | E81: Apoyo Ciudadano | F81: Educación | G81: Abuso Sexual | H81: Solicitud de seguimiento a las mesas de trabajo y los compromisos con el caso presentado | I81: Secretaría de Educación del Distrito | J81: Kennedy | K81: Sur | L81: 08.Kennedy | M81: 08.Kennedy Central | N81: 4.62161, -74.16491 | O81: Gestión 2025 | P81: Zulein Estefanía Jurado Morales | Q81: Mujer | R81: 1000134899 | S81: Calle Transversal 78IBISA Calle 41C S en Kennedy | T81: 4.6193322596252155, -74.15860789321484 | V81: 3009878225 | W81: Tramites | X81: Externos | Y81: En Proceso | Z81: Pendiente | AB81: 45752 | AD81: Asesor | AE81: Leidy Diana Soler G | AF81: Bogotá | AG81: Cundinamarca | AH81: 202500582 EDUCACIÓN Zulein Estefanía Jurado Morales | AJ81: NO
A82: 2025 | B82: 4 | C82: Abril | D82: 202500583 | E82: Apoyo Ciudadano | G82: Medicamentos | H82: Solicitud de medicamentos: Fluticasona suspensión nasal, fluticasona propionato + salmeterol polvo para inhalación, levocetirizina diclorhidrato + montelukast capsula. Tiempo de solicitud: desde noviembre de 2024. | I82: Secretaría Distrital de Salud | J82: Saucedal | K82: Sur | L82: 08.Kennedy | M82: 08.Kennedy Central | N82: 4.62161, -74.16491 | O82: Gestión 2025 | P82: Angela María Marentes | Q82: Mujer | R82: 39666543 | S82: Calle 36 #83 b 08 sur | T82: 4.634662903470555, -74.16182094912699 | U82: angelamariamarentes@gmail.com | V82: 3053918898 | W82: Tramites | X82: Interno | Y82: Finalizado | Z82: Pendiente | AB82: 45755 | AD82: Asesor | AE82: Angie Benitez | AF82: Bogotá | AG82: Cundinamarca | AH82: 202500583_Angela María Marentes | AJ82: NO
A83: 2025 | B83: 4 | C83: Abril | D83: 202500592 | E83: Apoyo Ciudadano | F83: Hacienda | G83: Impuesto predial | H83: Traslado: Se presenta una solicitud para revisar el valor del impuesto predial, considerado injustificado y excesivo en comparación con otros bienes inmuebles de proporciones similares. Se solicita que, de ser procedente, se ajusten los valores correspondientes y se evalúe la posibilidad de generar saldos a favor o la devolución del dinero. | I83: Secretaría Distrital de Hacienda | J83: Villa Andrea Kennedy | K83: Sur | L83: 08.Kennedy | M83: N/A | N83: N/A | O83: Gestión 2025 | P83: Blanca Lilia Orduña Sierra | Q83: Mujer | R83: 28308532 | S83: Cra 81i #51c-03 | T83: 4.621953180365622, -74.1756934037369 | U83: Blancaliliak19@gmail.com | V83: 3222286998 | W83: Tramites | X83: Externos | Y83: En Proceso | Z83: Pendiente | AB83: 45756 | AD83: Asesor | AE83: Angie Benitez | AF83: Bogotá | AG83: Cundinamarca | AH83: 202500592_ Blanca Lilia Orduña Sierra | AJ83: NO
A84: 2025 | B84: 5 | C84: Mayo | D84: 202500734 | E84: Apoyo Ciudadano | F84: Salud | G84: Citas médicas | H84: Solicitud de intervención cusodia de un menor de edad | I84: Secretaría Distrital de Salud | J84: Sinaí | K84: Sur | L84: 08.Kennedy | M84: 08.Kennedy Central | N84: =BUSCARX(R[0]C[-1],CONVENCIONES!R12C1:R42C1,CONVENCIONES!R12C2:R42C2) -> #ERROR! | O84: Gestión 2025 | P84: Dairo García | Q84: Hombre | R84: 19451254 | S84: Trasversal 78 h bis a 43 - 27 sur | T84: 4.616059552266472, -74.163354490591 | U84: dairogarciacalderon@hotmail.com | V84: 3142486135 - 3196422287 | W84: Tramites | X84: Interno | Y84: Finalizado | Z84: Positivo | AB84: 45779 | AC84: 45787 | AD84: Asesor | AE84: Fernando Zamora | AF84: Bogotá | AG84: Cundinamarca | AH84: PENDIENTE LINK | AJ84: NO
A85: 2025 | B85: 5 | C85: Mayo | D85: 202500794 | E85: Apoyo Ciudadano | F85: Salud | G85: Procedimientos y exámenes | H85: Traslado derecho de petición Pablo Vidal Esteban Villabona, tiene cancer de estomago y requiere un alimento especial que no se la ha entregado la EPS | I85: Secretaría Distrital de Salud | J85: Pastranita 2 sector | K85: Sur | L85: 08.Kennedy | M85: 08.Class | N85: =BUSCARX(R[0]C[-1],CONVENCIONES!R12C1:R42C1,CONVENCIONES!R12C2:R42C2) -> #ERROR! | O85: Gestión 2025 | P85: Pablo vidal Esteban Villabona | Q85: Hombre | R85: 5650739 | S85: Calle 49sur #78G 04 | T85: 4.612959347471619, -74.17165208822214 | U85: emilijacas1975@gmail.com | W85: Tramites | X85: Externos | Y85: En Proceso | Z85: Pendiente | AB85: 45784 | AD85: Asesor | AE85: Fernando Zamora | AF85: Bogotá | AG85: Cundinamarca | AH85: PENDIENTE LINK | AJ85: NO
A86: 2025 | B86: 5 | C86: Mayo | D86: 202500814 | E86: Apoyo Ciudadano | F86: Salud | G86: Citas médicas | H86: Requiere: procedimientos de curación de lesión en piel o tejido celular subcutáneo (código 869500) y valoración por clínica de heridas HOK | I86: Secretaría Distrital de Salud | J86: Sinaí | K86: Sur | L86: 08.Kennedy | M86: 08.Kennedy Central | N86: =BUSCARX(R[0]C[-1],CONVENCIONES!R12C1:R42C1,CONVENCIONES!R12C2:R42C2) -> #ERROR! | O86: Gestión 2025 | P86: Dairo García | Q86: Hombre | R86: 19451254 | S86: Trasversal 78 h bis a 43 - 27 sur | T86: 4.616059552266472, -74.163354490591 | U86: dairogarciacalderon@hotmail.com | V86: 3142486135 - 3196422287 | W86: Tramites | X86: Interno | Y86: Finalizado | Z86: Positivo | AB86: 45786 | AC86: 45787 | AD86: Asesor | AE86: Fernando Zamora | AF86: Bogotá | AG86: Cundinamarca | AH86: PENDIENTE LINK | AJ86: NO
A87: 2025 | B87: 5 | C87: Mayo | D87: 202500867 | E87: Apoyo Ciudadano | F87: Salud | G87: Medicamentos | H87: El ciudadano requiere un medicamento para su tratamiento | I87: Secretaría Distrital de Salud | J87: Socorro | K87: Sur | L87: 08.Kennedy | M87: 08.Kennedy Central | N87: =BUSCARX(R[0]C[-1],CONVENCIONES!R12C1:R42C1,CONVENCIONES!R12C2:R42C2) -> #ERROR! | O87: Gestión 2025 | P87: Gelmo William Marriaga Ríos | Q87: Hombre | R87: 79496374 | S87: Carrera 77v bis b # 4935 sur | T87: 4.61007107791511, -74.16617246108856 | U87: ruthestermarriagarios@gmail.com | W87: Tramites | X87: Interno | Y87: En Proceso | Z87: Pendiente | AB87: 45793 | AD87: Asesor | AE87: Fernando Zamora | AF87: Bogotá | AG87: Cundinamarca | AH87: PENDIENTE LINK | AJ87: NO
A88: 2025 | B88: 5 | C88: Mayo | D88: 202500903 | E88: Apoyo Ciudadano | F88: Victimas del Conflicto Armado | G88: Desplazamiento forzado | H88: Solicitud de atención y orientación integral a tres ciudadanos víctimas de desplazamiento forzado provenientes del municipio de Tibú, Norte de Santander. | I88: Alta Consejeria TIC | J88: Patio Bonito | K88: Sur | L88: 08.Kennedy | M88: N/A | N88: =BUSCARX(R[0]C[-1],CONVENCIONES!R12C1:R42C1,CONVENCIONES!R12C2:R42C2) -> #ERROR! | O88: Gestión 2025 | P88: Wilfer Ezneyr Guerrero Pérez, Luz Marina Guerrero Pérez y Álvaro Lobo Torrado | Q88: N/A | R88: 1093781311, 60434000, 88175482 | S88: Carrera 93A #40-16 | T88: 4.630066894742304, -74.17739150690518 | U88: N/A | V88: 3115288095 / 3229292419 | W88: Tramites | X88: Externos | Y88: Finalizado | Z88: Positivo | AA88: La consejería proporcionó rutas de atención, direcciones de los Centros de Encuentro para la Paz y puntos de atención a víctimas, indicando los servicios disponibles y pasos a seguir. La entidad da por atendida la solicitud. | AB88: 45796 | AC88: 45805 | AD88: Asesor | AE88: Maicol Quiroga | AF88: Bogotá | AG88: Cundinamarca | AH88: Wilfer Ezneyr Guerrero Pérez | AJ88: NO
A89: 2025 | B89: 5 | C89: Mayo | D89: 202500940 | E89: Apoyo Ciudadano | F89: Salud | G89: Cita | H89: Traslado derecho de petición Víctor Manuel Pardo Díaz | I89: Secretaría Distrital de Salud | J89: Britalia | K89: Sur | L89: 08.Kennedy | M89: 08.Kennedy Central | N89: =BUSCARX(R[0]C[-1],CONVENCIONES!R12C1:R42C1,CONVENCIONES!R12C2:R42C2) -> #ERROR! | O89: Gestión 2025 | P89: Victor Manuel pardo días | Q89: Hombre | R89: 14960538 | S89: Cra 80i No 48a-16 sur | T89: 4.6206625470939935, -74.17117954574654 | U89: victormanuelpardo1612@gmail.com | V89: 3170557060 | W89: Tramites | X89: Interno | Y89: En Proceso | Z89: Pendiente | AB89: 45799 | AD89: Asesor | AE89: Fernando Zamora | AF89: Bogotá | AG89: Cundinamarca | AH89: PENDIENTE LINK | AJ89: NO
A90: 2025 | B90: 5 | C90: Mayo | D90: 202500943 | E90: Apoyo Ciudadano | F90: Salud | G90: Cita con especialista | H90: Traslado derecho de petición Rosa Elena Ramírez Cárdenas - 202500943, cita para sutura | I90: Secretaría Distrital de Salud | J90: Chicala | K90: Sur | L90: 08.Kennedy | M90: 08.Kennedy Central | N90: =BUSCARX(R[0]C[-1],CONVENCIONES!R12C1:R42C1,CONVENCIONES!R12C2:R42C2) -> #ERROR! | O90: Gestión 2025 | P90: Rosa Elena Ramírez Cárdenas | Q90: Mujer | R90: 25079451 | S90: Cra. 87 Bis # 40C-53 | T90: 4.634056176886599, -74.1680030035653 | U90: rosaelena.ramirez.03@gmail.com | V90: 3157155888 | W90: Tramites | X90: Interno | Y90: En Proceso | Z90: Pendiente | AB90: 45800 | AD90: Asesor | AE90: Fernando Zamora | AF90: Bogotá | AG90: Cundinamarca | AH90: PENDIENTE LINK | AJ90: NO
A91: 2025 | B91: 5 | C91: Mayo | D91: 202500944 | E91: Apoyo Ciudadano | F91: Salud | G91: Cita con especialista | H91: Traslado derecho de petición Moisés Antonio Velarde Ladino - 202500944 solicita cita para cirujia | I91: Secretaría Distrital de Salud | J91: Chicala | K91: Sur | L91: 08.Kennedy | M91: 08.Kennedy Central | N91: =BUSCARX(R[0]C[-1],CONVENCIONES!R12C1:R42C1,CONVENCIONES!R12C2:R42C2) -> #ERROR! | O91: Gestión 2025 | P91: Moisés Antonio velarde ladino | Q91: Hombre | R91: 15927580 | S91: Cra. 87 Bis # 40C-53 | T91: 4.634056176886599, -74.1680030035653 | U91: rosaelena.ramirez.03@gmail.com | V91: 3152878746 | W91: Tramites | X91: Interno | Y91: En Proceso | Z91: Pendiente | AB91: 45800 | AD91: Asesor | AE91: Fernando Zamora | AF91: Bogotá | AG91: Cundinamarca | AH91: PENDIENTE LINK | AJ91: NO
A92: 2025 | B92: 5 | C92: Mayo | D92: 202500952 | E92: Apoyo Ciudadano | F92: Salud | G92: Solicitud de cita | H92: tiene Capital salud, Subsidiado, y requiere una cita por Hipoacusia bilateral Cita de otología, pero no ha sido posible conseguirla, la orden la tengo desde el 30 de abril. | I92: Secretaría Distrital de Salud | J92: Las Margaritas | K92: Sur | L92: 08.Kennedy | M92: 08.Kennedy Central | N92: =BUSCARX(R[0]C[-1],CONVENCIONES!R12C1:R42C1,CONVENCIONES!R12C2:R42C2) -> #ERROR! | O92: Gestión 2025 | P92: Steven Navarro Parrales | Q92: Hombre | R92: 1117485698 | S92: Carrera. 89a #45a 38 | T92: 4.694219180863009, -74.11030757749724 | U92: navarro456123@gmail.com | V92: 3016288659‬‬ | W92: Tramites | X92: Interno | Y92: Finalizado | Z92: Positivo | AB92: 45833 | AC92: 45833 | AD92: Asesor | AE92: Fernando Zamora | AF92: Bogotá | AG92: Cundinamarca | AH92: PENDIENTE LINK | AJ92: NO
A93: 2025 | B93: 6 | C93: Junio | D93: 202501068 | E93: Apoyo Ciudadano | F93: Salud | G93: Medicamentos | H93: Solicitud de medicamento polietilenglicol 400/propilenglicol gel oftálmico gotas para los ojos, sin entrega desde hace más de 4 meses | I93: Secretaría Distrital de Salud | J93: Kennedy | K93: Sur | L93: 08.Kennedy | M93: 08.Class | N93: =BUSCARX(R[0]C[-1],CONVENCIONES!R12C1:R42C1,CONVENCIONES!R12C2:R42C2) -> #ERROR! | O93: Gestión 2025 | P93: María de Jesús Méndez Martinez | Q93: Mujer | R93: 39711238 | S93: Calle 53 Sur #82H-06 | T93: 4.621809316706806, -74.17697803249638 | U93: marymendezmartinez730@gmail.com | V93: 3112972548 | W93: Tramites | X93: Interno | Y93: En Proceso | Z93: Pendiente | AB93: 45817 | AD93: Asesor | AE93: Alexandra García | AF93: Bogotá | AG93: Cundinamarca | AH93: PENDIENTE LINK | AJ93: NO
A94: 2025 | B94: 6 | C94: Junio | D94: 202501070 | E94: Apoyo Ciudadano | F94: Salud | G94: Citas médicas | H94: Solicita cita de otología por diagnóstico de hipoacusia bilateral | I94: Secretaría Distrital de Salud | J94: Las Margaritas | K94: Sur | L94: 08.Kennedy | M94: 08.Patio Bonito | N94: =BUSCARX(R[0]C[-1],CONVENCIONES!R12C1:R42C1,CONVENCIONES!R12C2:R42C2) -> #ERROR! | O94: Gestión 2025 | P94: Steven Navarro Parrales | Q94: Masculino | R94: 1117485698 | S94: Cra. 89A #45A-38 Sur | T94: 4.634533758020684, -74.1770417044698 | U94: navarro456123@gmail.com | V94: 3016288659 | W94: Tramites | X94: Interno | Y94: Finalizado | Z94: Positivo | AB94: 45811 | AC94: 45833 | AD94: Asesor | AE94: Alexandra García | AF94: Bogotá | AG94: Cundinamarca | AH94: PENDIENTE LINK | AJ94: NO
A95: 2025 | B95: 2 | C95: Febrero | D95: 202501073 | E95: Apoyo Ciudadano | F95: Salud | G95: Medicamentos | H95: Solicita entrega del medicamento carboximetilcelulosa sódica liquigel 1% solución oftálmica, ordenado hace más de 2 meses para tratar entropión y triquiasis palpebral | I95: Secretaría Distrital de Salud | J95: El Carmelo | K95: Sur | L95: 08.Kennedy | M95: 08.Patio Bonito | N95: 4.620952549090315, -74.17641244232873 | O95: Gestión 2025 | P95: Álvaro Martínez Roa | Q95: Hombre | R95: 19223377 | S95: Calle 53 Sur #81H-06 | T95: 4.634533758020684, -74.1770417044699 | U95: alvaromartinezroa29@gmail.com | V95: 3138053703 | W95: Tramites | X95: Externos | Y95: Finalizado | Z95: Positivo | AA95: Es preciso informar que el pasado 12 de junio de 2025, se trasladó a la EPS SALUD TOTAL, donde se recibe respuesta, donde se informa: De acuerdo con su actual requerimiento, donde solicita OPORTUNIDAD EN ENTREGA DE MEDICAMENTOS a favor del señor ALVARO MARTINEZ ROA C 19223377 se trasladó el caso al área médica de nuestra EAPB, quienes indican: Se anexan soportes de la entrega de los medicamentos solicitados dando cumplimiento al requerimiento hecho por el protegido. | AB95: 45817 | AD95: Asesor | AE95: Alexandra García | AF95: Bogotá | AG95: Cundinamarca | AH95: PENDIENTE LINK | AJ95: NO
A96: 2025 | B96: 6 | C96: Junio | D96: 202501075 | E96: Apoyo Ciudadano | F96: Salud | G96: Cita médica | H96: Solicita cita con especialista en otología debido a hipoacusia bilateral y requerimientos prequirúrgicos. | I96: Secretaría Distrital de Salud | J96: Las Margaritas | K96: Sur | L96: 08.Kennedy | M96: 08.Patio Bonito | N96: =BUSCARX(R[0]C[-1],CONVENCIONES!R12C1:R42C1,CONVENCIONES!R12C2:R42C2) -> #ERROR! | O96: Gestión 2025 | P96: Steven Navarro Parrales | Q96: Hombre | R96: 1117485698 | S96: Cra. 89A #45A-38 Sur | T96: 4.634544451777012, -74.17706316214107 | U96: navarro456123@gmail.com | V96: 3016288659 | W96: Tramites | X96: Interno | Y96: Finalizado | Z96: Positivo | AB96: 45817 | AC96: 45833 | AD96: Asesor | AE96: Alexandra García | AF96: Bogotá | AG96: Cundinamarca | AH96: PENDIENTE LINK | AJ96: NO
A97: 2025 | B97: 6 | C97: Junio | D97: 202501076 | E97: Apoyo Ciudadano | F97: Salud | G97: Medicamentos | H97: Solicita entrega de medicamentos: semaglutida, sacubitrilo/valsartán, empagliflozina/metformina y levotiroxina por diagnóstico de falla cardíaca y diabetes. | I97: Secretaría Distrital de Salud | J97: Puente Aranda | K97: Sur | L97: 08.Kennedy | M97: 08.Patio Bonito | N97: =BUSCARX(R[0]C[-1],CONVENCIONES!R12C1:R42C1,CONVENCIONES!R12C2:R42C2) -> #ERROR! | O97: Gestión 2025 | P97: María Elvira Mora de Deaza | Q97: Femenino | R97: 20489048 | S97: Calle 3B #40C-44 | T97: 4.6135495709338326, -74.11134081796291 | U97: mariainesdeazam@gmail.com | V97: 3133670591 - 3132589352 | W97: Tramites | X97: Interno | Y97: En Proceso | Z97: Pendiente | AB97: 45817 | AD97: Asesor | AE97: Alexandra García | AF97: Bogotá | AG97: Cundinamarca | AH97: PENDIENTE LINK | AJ97: NO
A98: 2025 | B98: 6 | C98: Junio | D98: 202501094 | E98: Apoyo Ciudadano | F98: Salud | G98: Medicamentos | H98: Solicitud de entrega del medicamento ácido valproico para convulsiones. Se ha intentado en varias farmacias sin éxito. | I98: Secretaría Distrital de Salud | J98: Ciudad Jardín Sur | K98: Sur | L98: 08.Kennedy | M98: 08.Kennedy Central | N98: =BUSCARX(R[0]C[-1],CONVENCIONES!R12C1:R42C1,CONVENCIONES!R12C2:R42C2) -> #ERROR! | O98: Gestión 2025 | P98: José Miguel Deaza Gil | Q98: Masculino | R98: 449659 | S98: Calle 3b #40 c-44 | T98: 4.613485406491816, -74.11131936029123 | U98: mariainesdeazam@gmail.com | V98: 3133670591 - 3132589352 | W98: Trámites | X98: Sí | Y98: Enviado | Z98: Pendiente de respuesta institucional | AB98: 45820 | AH98: PENDIENTE LINK | AJ98: NO
A99: 2025 | B99: 6 | C99: Junio | D99: 202501097 | E99: Apoyo Ciudadano | F99: Salud | G99: Especialista y Medicamentos | H99: Solicitud de cita con neurólogo y entrega de medicamentos. La ciudadana lleva dos meses esperando la atención sin obtener respuesta. Requiere atención por diagnóstico de hemorragia subaracnoidea y antecedentes de diabetes e hipertensión. Medicamentos: Levotiroxina 100 mcg, Biocalcium, Levotiroxina 50 mcg, Glucoquick agujas, Apidra Solostar, Lantus 100/ml, Calcitriol, Losart/Hidroclorotiazida, C-G-MET G-Tabs 100 mg, Jardiance 10 mg. | I99: Secretaría Distrital de Salud | J99: Patio Bonito 3 sector | K99: Sur | L99: 08.Kennedy | M99: 08.Patio Bonito | N99: =BUSCARX(R[0]C[-1],CONVENCIONES!R12C1:R42C1,CONVENCIONES!R12C2:R42C2) -> #ERROR! | O99: Gestión 2025 | P99: María Fidelia Hernández de Urrea | Q99: Femenino | R99: 41634958 | S99: Calle 5b norte #87f - 38 | T99: 4.642980791707799, -74.1590596269862 | U99: N/A | V99: 3125073505 | W99: Trámites | X99: Sí | Y99: Enviado | Z99: Pendiente de respuesta institucional | AB99: 45820 | AH99: PENDIENTE LINK | AJ99: NO
A100: 2025 | B100: 6 | C100: Junio | D100: 202501185 | E100: Apoyo Ciudadano | F100: Salud | G100: Cita especialista | H100: Solicita cita neurologia desde octubre del 2024 | I100: Secretaría Distrital de Salud | J100: Restrepo | K100: Sur | L100: 08.Kennedy | M100: 08.Class | N100: =BUSCARX(R[0]C[-1],CONVENCIONES!R12C1:R42C1,CONVENCIONES!R12C2:R42C2) -> #ERROR! | O100: Gestión 2024 | P100: Ariana Rojas | Q100: Mujer | R100: 1027153850 | S100: calle 13 sur 24 g 38 | T100: 4.592160633739742, -74.10227917273365 | U100: olagos.826@gmail.com | V100: 3003062824 | W100: Tramites | X100: Interno | Y100: En Proceso | Z100: Pendiente | AB100: 45833 | AD100: Asesor | AE100: Fernando Zamora | AF100: Bogotá | AG100: Cundinamarca | AH100: PENDIENTE LINK | AJ100: NO
...

Sheet Hoja 27
A1: # | B1: Nombre Gestión | C1: Ubicación | D1: Barrio | E1: Iglesia | F1: Temas | G1: Fecha | H1: Estado | I1: Tiene Logros | J1: Gestión en Bancada | K1: Acciones | L1: Solicitante | M1: Beneficiarios | N1: Envíos
A2: 1 | B2: TEM - BOSA Y KENNEDY - CIERRE | C2: BOGOTA D.C. / BOGOTA. D.C. | D2: VILLA NELLY III | E2: KENNEDY | F2: ESPACIO PÚBLICO | G2: 46077 | H2: EN TRAMITE | I2: No | J2: No | K2: 0 | L2: FERNANDO JOSE ZAMORA CAMACHO | M2: 1602 | N2: 1
A3: 2 | B3: MT - MARGARITAS BAJA PRESION DEL AGUA (7439) | C3: BOGOTA D.C. / BOGOTA. D.C. / LOCALIDAD 8 KENNEDY | D3: KENNEDY | E3: KENNEDY | F3: SERVICIOS PÚBLICOS | G3: 45986 | H3: EN TRAMITE | I3: No | J3: Sí | K3: 0 | L3: RAFAEL ENRIQUE GUTIERREZ USAQUEN | M3: 46 | N3: 0
A4: 3 | B4: MT - VALLADOLID MALLA VIAL MAL ESTADO (7388) | C4: BOGOTA D.C. / BOGOTA. D.C. / LOCALIDAD 8 KENNEDY | D4: VILLA NELLY III | E4: KENNEDY | F4: MALLA VIAL, MOVILIDAD | G4: 45988 | H4: EN TRAMITE | I4: Sí | J4: Sí | K4: 1 | L4: FERNANDO JOSE ZAMORA CAMACHO | M4: 6 | N4: 0
A5: 4 | B5: MT - PARQUE URBANIZACION GRAN BRITALIA MALLA Y GRA... | C5: BOGOTA D.C. / BOGOTA. D.C. / LOCALIDAD 8 KENNEDY | D5: BRITALIA | E5: KENNEDY | F5: AMBIENTE | G5: 45974 | H5: EN TRAMITE | I5: No | J5: Sí | K5: 1 | L5: CLARA MERCEDES LUMPAQUE ESTRADA | M5: 1 | N5: 0
A6: 5 | B6: MT - CASTILLA TERRA ESPACIO PÚBLICO Y VIA EN MAL E... | C6: BOGOTA D.C. / BOGOTA. D.C. / LOCALIDAD 8 KENNEDY | D6: MARÍA PAZ | E6: KENNEDY | F6: MALLA VIAL, MOVILIDAD | G6: 45965 | H6: EN TRAMITE | I6: No | J6: Sí | K6: 1 | L6: CHEPE PINILLA GUTIERRES | M6: 1 | N6: 0
A7: 6 | B7: MT - FERIA DE SERVICIOS CASTILLA KENNEDY (6351) | C7: BOGOTA D.C. / BOGOTA. D.C. / LOCALIDAD 8 KENNEDY | D7: VALLADOLID | E7: KENNEDY | F7: ANIMALES, EDUCACIÓN, SALUD, SERVICIOS PÚBLICOS | G7: 45955 | H7: EN TRAMITE | I7: Sí | J7: Sí | K7: 1 | L7: DIANA LUCIA REAL MARROQUIN | M7: 111 | N7: 1
A8: 7 | B8: MT - NUEVO TECHO PARQUE MANTENIMIENTO (6277) | C8: BOGOTA D.C. / BOGOTA. D.C. / LOCALIDAD 8 KENNEDY | D8: CASTILLA | E8: KENNEDY | F8: DEPORTE, NIÑEZ | G8: 45952 | H8: EN TRAMITE | I8: No | J8: Sí | K8: 1 | L8: ANGELICA MARIA MUNERA GONZALEZ | M8: 1 | N8: 0
A9: 8 | B9: MT - CIUDAD KENNEDY OCCIDENTAL INSEGURIDAD POR RET... | C9: BOGOTA D.C. / BOGOTA. D.C. / LOCALIDAD 8 KENNEDY | E9: KENNEDY | F9: INSEGURIDAD | G9: 45951 | H9: EN TRAMITE | I9: Sí | J9: Sí | K9: 2 | L9: MIGUEL ADRIEL GUERRERO SANCHEZ | M9: 20 | N9: 1
A10: 9 | B10: MT - TIMIZA ZONA DE CESIÓN PARQUE DE PROXIMIDAD (... | C10: BOGOTA D.C. / BOGOTA. D.C. / LOCALIDAD 8 KENNEDY | D10: FERIAS | E10: KENNEDY | F10: ESPACIO PÚBLICO, INSEGURIDAD, PARQUES | G10: 45951 | H10: EN TRAMITE | I10: Sí | J10: Sí | K10: 3 | L10: LEIDY MARCELA NEIRA ARIAS | M10: 24 | N10: 1
A11: 10 | B11: MT - JORNADA OPAM PARQUE HOLANDA (6172) | C11: BOGOTA D.C. / BOGOTA. D.C. / LOCALIDAD 8 KENNEDY | D11: LAS MARGARITAS | E11: KENNEDY | F11: ANIMALES | G11: 45921 | H11: EN TRAMITE | I11: Sí | J11: Sí | K11: 1 | L11: NUBIA LILIANA PARRA GUERRERO | M11: 18 | N11: 1
A12: 11 | B12: MT_VERGEL ORIENTAL MALLA VIAL CIV 8014267 (6012) | C12: BOGOTA D.C. / BOGOTA. D.C. / LOCALIDAD 8 KENNEDY | D12: VILLA NELLY III | E12: KENNEDY | F12: VÍAS | G12: 45931 | H12: EN TRAMITE | I12: No | J12: Sí | K12: 1 | L12: FERNANDO JOSE ZAMORA CAMACHO | M12: 0 | N12: 0
A13: 12 | B13: MT - NUEVA CASTILLA PROBLEMAS EN LA PRESTACIÓN DEL... | C13: BOGOTA D.C. / BOGOTA. D.C. / LOCALIDAD 8 KENNEDY | D13: NUEVA CASTILLA | E13: KENNEDY | F13: SERVICIOS PÚBLICOS | G13: 45922 | H13: EN TRAMITE | I13: Sí | J13: Sí | K13: 2 | L13: HERNAN FRANCISCO MONTES | M13: 23 | N13: 2
A14: 13 | B14: MT - CASABLANCA JORNADA OPAM (5646) | C14: BOGOTA D.C. / BOGOTA. D.C. / LOCALIDAD 8 KENNEDY | D14: CASA BLANCA | E14: KENNEDY | F14: ANIMALES | G14: 45910 | H14: EN TRAMITE | I14: Sí | J14: Sí | K14: 0 | L14: TERESA DE JESUS PORTELA GRISALES | M14: 41 | N14: 2
A15: 14 | B15: MT - KENNEDY CENTRAL SEGURIDAD VIAL ZONA ESCOLAR (... | C15: BOGOTA D.C. / BOGOTA. D.C. / LOCALIDAD 8 KENNEDY | D15: AYACUCHO PRIMER SECTOR | E15: KENNEDY | F15: MOVILIDAD | G15: 45909 | H15: EN TRAMITE | I15: No | J15: Sí | K15: 1 | L15: OLGA LUCIA SAENZ GOMEZ | M15: 1 | N15: 0
A16: 15 | B16: MT - CATALINA II SECTOR ANDENES EN MAL ESTADO (51... | C16: BOGOTA D.C. / BOGOTA. D.C. / LOCALIDAD 8 KENNEDY | D16: LAS LUCES | E16: KENNEDY | F16: ANDENES, ESPACIO PÚBLICO | G16: 45883 | H16: EN TRAMITE | I16: No | J16: Sí | K16: 1 | L16: LUCIA EISINENA CABEZAS | M16: 8 | N16: 0
A17: 16 | B17: MT - CIUDAD DE CALI AFECTACIÓN POR SEMÁFORO (5109) | C17: BOGOTA D.C. / BOGOTA. D.C. / LOCALIDAD 8 KENNEDY | D17: CIUDAD DE CALI | E17: KENNEDY | F17: MOVILIDAD | G17: 45883 | H17: EN TRAMITE | I17: Sí | J17: Sí | K17: 1 | L17: ORLANDO MARULANDA LEON | M17: 5 | N17: 1
A18: 17 | B18: MT - FRANCISCO JOSÉ DE CALDAS MALLA VIAL CIV 80044... | C18: BOGOTA D.C. / BOGOTA. D.C. / LOCALIDAD 8 KENNEDY | D18: AYACUCHO PRIMER SECTOR | E18: KENNEDY | F18: MALLA VIAL | G18: 45873 | H18: EN TRAMITE | I18: Sí | J18: Sí | K18: 3 | L18: OLGA LUCIA SAENZ GOMEZ | M18: 86 | N18: 4
A19: 18 | B19: MT - CASABLANCA ANDENES Y PARADERO SITP (4620) | C19: BOGOTA D.C. / BOGOTA. D.C. / LOCALIDAD 8 KENNEDY | D19: CASA BLANCA | E19: KENNEDY | F19: ANDENES, TRANSPORTE PÚBLICO | G19: 45860 | H19: EN TRAMITE | I19: Sí | J19: Sí | K19: 4 | L19: TERESA DE JESUS PORTELA GRISALES | M19: 31 | N19: 4
A20: 19 | B20: MT - LAS MARGARITAS ZONAS DE CESION (4329) | C20: BOGOTA D.C. / BOGOTA. D.C. / LOCALIDAD 8 KENNEDY | E20: KENNEDY | F20: AMBIENTE | G20: 45846 | H20: EN TRAMITE | I20: Sí | J20: Sí | K20: 6 | L20: RAFAEL GUTIERREZ | M20: 23 | N20: 1
A21: 20 | B21: MT - EL AMPARO CALLEJÓN ENTRE CAYETANO Y HUMEDAL (... | C21: BOGOTA D.C. / BOGOTA. D.C. / LOCALIDAD 8 KENNEDY | D21: LA ESPERANZA | E21: KENNEDY | F21: MALLA VIAL, PARQUES | G21: 45840 | H21: EN TRAMITE | I21: No | J21: Sí | K21: 1 | L21: JHONNY ANDRES BOSSA BERMUDEZ | M21: 3 | N21: 0
A22: 21 | B22: MT - CASTILLA JORNADA OPAM (3825) | C22: BOGOTA D.C. / BOGOTA. D.C. / LOCALIDAD 8 KENNEDY | D22: VILLA NELLY III | E22: KENNEDY | F22: AMBIENTE | G22: 45656 | H22: EN TRAMITE | I22: No | J22: Sí | K22: 1 | L22: FERNANDO JOSE ZAMORA CAMACHO | M22: 68 | N22: 1
A23: 22 | B23: MT - VILLA NELLY VIA SIN PAVIMENTAR (3823) | C23: BOGOTA D.C. / BOGOTA. D.C. / LOCALIDAD 8 KENNEDY | D23: VILLA NELLY III | E23: KENNEDY | F23: MOVILIDAD | G23: 45365 | H23: EN TRAMITE | I23: No | J23: Sí | K23: 2 | L23: FERNANDO JOSE ZAMORA CAMACHO | M23: 193 | N23: 1
A24: 23 | B24: MT - VILLA NELLY MALLA VIAL BOCACALLE (3805) | C24: BOGOTA D.C. / BOGOTA. D.C. / LOCALIDAD 8 KENNEDY | D24: VILLA NELLY III | E24: KENNEDY | F24: MOVILIDAD | G24: 45771 | H24: EN TRAMITE | I24: Sí | J24: Sí | K24: 2 | L24: FERNANDO JOSE ZAMORA CAMACHO | M24: 6 | N24: 2
A25: 24 | B25: MT - CASTILLA RINCON DE LOS ANGELES PARQUE MAL EST... | C25: BOGOTA D.C. / BOGOTA. D.C. / LOCALIDAD 8 KENNEDY | D25: VILLA NELLY III | E25: KENNEDY | F25: DEPORTE, MOVILIDAD, NIÑEZ | G25: 45806 | H25: EN TRAMITE | I25: Sí | J25: Sí | K25: 8 | L25: FERNANDO JOSE ZAMORA CAMACHO | M25: 10 | N25: 4
A26: 25 | B26: MT - ORGANIZACIONES DE RECICLADORES KENNEDY (3274) | C26: BOGOTA D.C. / BOGOTA. D.C. / LOCALIDAD 8 KENNEDY | D26: LOMBARDIA | E26: KENNEDY | F26: SERVICIOS PÚBLICOS | G26: 45787 | H26: EN TRAMITE | I26: No | J26: Sí | K26: 1 | L26: SCHEYMAN JULIAN SCARPETTA ZAMBRANO | M26: 6 | N26: 0
A27: 26 | B27: MT - ESTADOS UNIDOS SOCAVON EAAB (3221) | C27: BOGOTA D.C. / BOGOTA. D.C. / LOCALIDAD 8 KENNEDY | D27: VILLA NELLY III | E27: KENNEDY | F27: SERVICIOS PÚBLICOS | G27: 45785 | H27: EN TRAMITE | I27: Sí | J27: Sí | K27: 3 | L27: FERNANDO JOSE ZAMORA CAMACHO | M27: 6 | N27: 5
A28: 27 | B28: MT - LAS MARGARITAS PROBLEMATICA DEL METRO (2761) | C28: BOGOTA D.C. / BOGOTA. D.C. / LOCALIDAD 8 KENNEDY | D28: VILLA NELLY III | E28: KENNEDY | F28: MOVILIDAD | G28: 45706 | H28: EN TRAMITE | I28: No | J28: Sí | K28: 3 | L28: FERNANDO JOSE ZAMORA CAMACHO | M28: 21 | N28: 0
A29: 28 | B29: MT - CLASS MALLA VIAL Y REDUCTORES VELOCIDAD (2723... | C29: BOGOTA D.C. / BOGOTA. D.C. / LOCALIDAD 8 KENNEDY | D29: VILLA NELLY III | E29: KENNEDY | F29: MOVILIDAD | G29: 45770 | H29: EN TRAMITE | I29: Sí | J29: Sí | K29: 3 | L29: FERNANDO JOSE ZAMORA CAMACHO | M29: 8 | N29: 2
A30: 29 | B30: MT - PATIO BONITO PARQUE SAN DIONISIO (2717) | C30: BOGOTA D.C. / BOGOTA. D.C. / LOCALIDAD 8 KENNEDY | D30: VILLA NELLY III | E30: KENNEDY | F30: DEPORTE, NIÑEZ, SERVICIOS PÚBLICOS | G30: 45775 | H30: EN TRAMITE | I30: Sí | J30: Sí | K30: 4 | L30: FERNANDO JOSE ZAMORA CAMACHO | M30: 36 | N30: 2
A31: 30 | B31: MT - CIUDAD ROMA BERTHA HERNANDEZ PARQUE Y SEGURID... | C31: BOGOTA D.C. / BOGOTA. D.C. / LOCALIDAD 8 KENNEDY | D31: CIUDAD ROMA | E31: KENNEDY | F31: MOVILIDAD | G31: 45743 | H31: EN TRAMITE | I31: Sí | J31: Sí | K31: 1 | L31: ANGIE FERNANDA BENITEZ PULIDO | M31: 2 | N31: 1
A32: 31 | B32: MT - PINAR DEL RIO MALLA VIAL Y ESQUINA DE ARROJO... | C32: BOGOTA D.C. / BOGOTA. D.C. / LOCALIDAD 8 KENNEDY | D32: CASTILLA | E32: KENNEDY | F32: MOVILIDAD | G32: 45728 | H32: EN TRAMITE | I32: Sí | J32: Sí | K32: 3 | L32: ANGIE FERNANDA BENITEZ PULIDO | M32: 39 | N32: 3
... A36: 35 | B36: MT - SINAÍ PARQUE TRANSMILENIO Y EXCRETAS (1788) | C36: BOGOTA D.C. / BOGOTA. D.C. / LOCALIDAD 8 KENNEDY | D36: SINAÍ | E36: KENNEDY | F36: AMBIENTE, MOVILIDAD, SERVICIOS PÚBLICOS | G36: 45734 | H36: EN TRAMITE | I36: Sí | J36: Sí | K36: 2 | L36: ANGIE FERNANDA BENITEZ PULIDO | M36: 51 | N36: 2
A37: 36 | B37: MT COMPLEJO ACUÁTICO | C37: BOGOTA D.C. / BOGOTA. D.C. / LOCALIDAD 8 KENNEDY | E37: KENNEDY | F37: DEPORTE | G37: 45702 | H37: EN TRAMITE | I37: Sí | J37: Sí | K37: 2 | L37: ANGIE FERNANDA BENITEZ PULIDO | M37: 7 | N37: 1

Sheet AGENDA PARALELA
A1: BOGOTÁ | B1: LOCALIDAD | C1: SEDE | D1: HORA | E1: ACTIVIDAD | F1: ESTRATEGIA | G1: MES | H1: DIA | I1: FECHA CAMPAÑA | J1: DETALLE DE LA ACTIVIDAD | K1: LOGROS JUSTIFICACION | L1: DIRECCIÓN | M1: LINK DE GOOGLE MAPS | N1: COORDENADAS | O1: BARRIO | P1: BENEFICIARIOS | Q1: LÍDER Y CELULAR | R1: LOGISTICA (Vecinos contactados, espacio, sillas, publicidad, refrigerios)
A2: SUR | B2: KENNEDY | C2: Kennedy Central | D2: 3:30 PM | E2: VOLANTEO | F2: POLITICO COMUNITARIA | G2: =TEXT(I2,"Mmmm") -> diciembre | H2: =TEXT(I2,"dddd") -> viernes | I2: 46010 | O2: Roma sector comercial (Paula Velasquez)
A3: SUR | B3: KENNEDY | C3: Carvajal | D3: 11:00AM | E3: VOLANTEO | F3: POLITICO COMUNITARIA | G3: =TEXT(I3,"Mmmm") -> diciembre | H3: =TEXT(I3,"dddd") -> viernes | I3: 46003 | O3: Maracaná (Carmen Garzón)
A4: SUR | B4: KENNEDY | C4: Patio Bonito | D4: 2:00 PM | E4: VOLANTEO | F4: POLITICO COMUNITARIA | G4: =TEXT(I4,"Mmmm") -> diciembre | H4: =TEXT(I4,"dddd") -> viernes | I4: 46003 | O4: Ciudadela Primavera
A5: SUR | B5: KENNEDY | C5: Class | D5: 3:00 PM | E5: VOLANTEO | F5: POLITICO COMUNITARIA | G5: =TEXT(I5,"Mmmm") -> diciembre | H5: =TEXT(I5,"dddd") -> viernes | I5: 46003 | O5: Roma 4 sector (Bryan Rodriguez)
A6: SUR | B6: KENNEDY | C6: Kennedy Central | D6: 8:30 AM | E6: MICROREUNIÓN | F6: AFINIDAD | G6: diciembre | H6: =TEXT(I6,"dddd") -> lunes | I6: 46013 | J6: Microreunión con hermanos menos 10 referi | K6: Microreunión | L6: AV CR 80 NO 42C 83 SUR | M6: google.com/maps/place/Iglesia+de+Dios+Ministerial+de+Jesucristo+Internacional+-+IDMJI+-+CGMJI+BTA+EL+OLIVO/@4.6215758,-74.164928,3a,75y,316.8h,90t/data=!3m7!1e1!3m5!1sJwIftdN6Rl-LMLqtdi_3Nw!2e0!6shttps:%2F%2Fstreetviewpixels-pa.googleapis.com%2Fv1%2Fthumbnail%3Fcb_client%3Dmaps_sv.tactile%26w%3D900%26h%3D600%26pitch%3D0%26panoid%3DJwIftdN6Rl-LMLqtdi_3Nw%26yaw%3D316.80283!7i16384!8i8192!4m14!1m7!3m6!1s0x8e3f9e842a6a8335:0xe8f39c19a9ab6da3!2sIglesia+de+Dios+Ministerial+de+Jesucristo+Internacional+-+IDMJI+-+CGMJI+BTA+EL+OLIVO!8m2!3d4.6216536!4d-74.1650013!16s%2Fg%2F1tdksvtw!3m5!1s0x8e3f9e842a6a8335:0xe8f39c19a9ab6da3!8m2!3d4.6216536!4d-74.1650013!16s%2Fg%2F1tdksvtw?entry=ttu&g_ep=EgoyMDI1MTEwOS4wIKXMDSoASAFQAw%3D%3D | N6: 4.622006495658455, -74.16497448186743 | O6: Kennedy Central | Q6: Jenny García (DP)
A7: SUR | B7: KENNEDY | C7: Carvajal | D7: 8:30 AM | E7: MICROREUNIÓN | F7: AFINIDAD | G7: diciembre | H7: =TEXT(I7,"dddd") -> miércoles | I7: 46015 | J7: Microreunión | K7: Microreunión | L7: Av. Boyacá #25 Sur NO 35 | M7: google.com/maps/place/Iglesia+De+Dios+Ministerial+De+Jesucristo+Internacional+-+IDMJI+-CARVAJAL/@4.6162521,-74.1430179,17z/data=!3m1!4b1!4m6!3m5!1s0x8e3f9ebb73ed00eb:0x84ff2c16af65e299!8m2!3d4.6162468!4d-74.140443!16s%2Fg%2F1ptwb97lz?entry=ttu&g_ep=EgoyMDI1MTEyMy4xIKXMDSoASAFQAw%3D%3D | N7: 4.616503452100983, -74.14045373278768 | O7: Carvajal | Q7: Sergio Osorio (DP)
A8: SUR | B8: KENNEDY | C8: Kennedy Central | D8: 6:30 PM | E8: MICROREUNIÓN | F8: AFINIDAD | G8: diciembre | H8: =TEXT(I8,"dddd") -> viernes | I8: 46017 | J8: Microreunión | K8: Microreunión | L8: AV CR 80 NO 42C 83 SUR | M8: google.com/maps/place/Iglesia+de+Dios+Ministerial+de+Jesucristo+Internacional+-+IDMJI+-+CGMJI+BTA+EL+OLIVO/@4.6215758,-74.164928,3a,75y,316.8h,90t/data=!3m7!1e1!3m5!1sJwIftdN6Rl-LMLqtdi_3Nw!2e0!6shttps:%2F%2Fstreetviewpixels-pa.googleapis.com%2Fv1%2Fthumbnail%3Fcb_client%3Dmaps_sv.tactile%26w%3D900%26h%3D600%26pitch%3D0%26panoid%3DJwIftdN6Rl-LMLqtdi_3Nw%26yaw%3D316.80283!7i16384!8i8192!4m14!1m7!3m6!1s0x8e3f9e842a6a8335:0xe8f39c19a9ab6da3!2sIglesia+de+Dios+Ministerial+de+Jesucristo+Internacional+-+IDMJI+-+CGMJI+BTA+EL+OLIVO!8m2!3d4.6216536!4d-74.1650013!16s%2Fg%2F1tdksvtw!3m5!1s0x8e3f9e842a6a8335:0xe8f39c19a9ab6da3!8m2!3d4.6216536!4d-74.1650013!16s%2Fg%2F1tdksvtw?entry=ttu&g_ep=EgoyMDI1MTEwOS4wIKXMDSoASAFQAw%3D%3D | N8: 4.622006495658455, -74.16497448186743 | O8: Kennedy Central
A9: SUR | B9: KENNEDY | C9: Carvajal | D9: 7:30 PM | E9: MICROREUNIÓN | F9: AFINIDAD | G9: diciembre | H9: =TEXT(I9,"dddd") -> lunes | I9: 46020 | J9: Microreunión | K9: Microreunión | L9: Av. Boyacá #25 Sur NO 35 | M9: google.com/maps/place/Iglesia+De+Dios+Ministerial+De+Jesucristo+Internacional+-+IDMJI+-CARVAJAL/@4.6162521,-74.1430179,17z/data=!3m1!4b1!4m6!3m5!1s0x8e3f9ebb73ed00eb:0x84ff2c16af65e299!8m2!3d4.6162468!4d-74.140443!16s%2Fg%2F1ptwb97lz?entry=ttu&g_ep=EgoyMDI1MTEyMy4xIKXMDSoASAFQAw%3D%3D | N9: 4.616503452100983, -74.14045373278768 | O9: Carvajal | Q9: Sergio Osorio (DP)
A10: SUR | B10: KENNEDY | C10: Patio Bonito | D10: 8:30 AM | E10: MICROREUNIÓN | F10: AFINIDAD | G10: diciembre | H10: =TEXT(I10,"dddd") -> martes | I10: 46021 | J10: Microreunión | K10: Microreunión | L10: Cra 95A #39 SUR NO.38C | M10: 4.646227879789345, -74.17302253463195 | N10: https://www.google.com/maps/place/Iglesia+de+Dios+Ministerial+de+Jesucristo+Internacional+-+IDMJI+-+CGMJI+BGT+PATIO+BONITO/@4.6459614,-74.1729512,3a,75y,2.26h,90t/data=!3m7!1e1!3m5!1sM3OspZ9UMH1_tuM0OG22Nw!2e0!6shttps:%2F%2Fstreetviewpixels-pa.googleapis.com%2Fv1%2Fthumbnail%3Fcb_client%3Dmaps_sv.tactile%26w%3D900%26h%3D600%26pitch%3D0%26panoid%3DM3OspZ9UMH1_tuM0OG22Nw%26yaw%3D2.26188!7i16384!8i8192!4m14!1m7!3m6!1s0x8e3f9dcb205cea4b:0xc5b44d64b0ce5139!2sIglesia+de+Dios+Ministerial+de+Jesucristo+Internacional+-+IDMJI+-+CGMJI+BGT+PATIO+BONITO!8m2!3d4.6460354!4d-74.1729367!16s%2Fg%2F11c3j5dn0q!3m5!1s0x8e3f9dcb205cea4b:0xc5b44d64b0ce5139!8m2!3d4.6460354!4d-74.1729367!16s%2Fg%2F11c3j5dn0q?entry=ttu&g_ep=EgoyMDI1MTEyMy4xIKXMDSoASAFQAw%3D%3D | O10: Patio Bonito | Q10: Hamilton Liz (DP)
A11: SUR | B11: KENNEDY | C11: Kennedy Central | D11: 6:30 PM | E11: MICROREUNIÓN | F11: AFINIDAD | G11: enero | H11: =TEXT(I11,"dddd") -> lunes | I11: 46027 | J11: Microreunión | K11: Microreunión | L11: AV CR 80 NO 42C 83 SUR | M11: google.com/maps/place/Iglesia+de+Dios+Ministerial+de+Jesucristo+Internacional+-+IDMJI+-+CGMJI+BTA+EL+OLIVO/@4.6215758,-74.164928,3a,75y,316.8h,90t/data=!3m7!1e1!3m5!1sJwIftdN6Rl-LMLqtdi_3Nw!2e0!6shttps:%2F%2Fstreetviewpixels-pa.googleapis.com%2Fv1%2Fthumbnail%3Fcb_client%3Dmaps_sv.tactile%26w%3D900%26h%3D600%26pitch%3D0%26panoid%3DJwIftdN6Rl-LMLqtdi_3Nw%26yaw%3D316.80283!7i16384!8i8192!4m14!1m7!3m6!1s0x8e3f9e842a6a8335:0xe8f39c19a9ab6da3!2sIglesia+de+Dios+Ministerial+de+Jesucristo+Internacional+-+IDMJI+-+CGMJI+BTA+EL+OLIVO!8m2!3d4.6216536!4d-74.1650013!16s%2Fg%2F1tdksvtw!3m5!1s0x8e3f9e842a6a8335:0xe8f39c19a9ab6da3!8m2!3d4.6216536!4d-74.1650013!16s%2Fg%2F1tdksvtw?entry=ttu&g_ep=EgoyMDI1MTEwOS4wIKXMDSoASAFQAw%3D%3D | N11: 4.622006495658455, -74.16497448186743 | O11: Kennedy Central | Q11: Jenny García (DP)
A12: SUR | B12: KENNEDY | C12: Carvajal | D12: 8:30 AM | E12: MICROREUNIÓN | F12: AFINIDAD | G12: enero | H12: =TEXT(I12,"dddd") -> jueves | I12: 46044 | J12: Microreunión | K12: Microreunión | L12: Av. Boyacá #25 Sur NO 35 | M12: google.com/maps/place/Iglesia+De+Dios+Ministerial+De+Jesucristo+Internacional+-+IDMJI+-CARVAJAL/@4.6162521,-74.1430179,17z/data=!3m1!4b1!4m6!3m5!1s0x8e3f9ebb73ed00eb:0x84ff2c16af65e299!8m2!3d4.6162468!4d-74.140443!16s%2Fg%2F1ptwb97lz?entry=ttu&g_ep=EgoyMDI1MTEyMy4xIKXMDSoASAFQAw%3D%3D | N12: 4.616503452100983, -74.14045373278768
A13: SUR | B13: KENNEDY | C13: Patio Bonito | D13: 7:00 AM | E13: MICROREUNIÓN | F13: AFINIDAD | G13: =TEXT(I13,"Mmmm") -> enero | H13: =TEXT(I13,"dddd") -> martes | I13: 46042 | J13: Microreunión | K13: Microreunión
A14: SUR | B14: KENNEDY | C14: Carvajal | D14: 6:00 PM | E14: MICROREUNIÓN | F14: AFINIDAD | G14: =TEXT(I14,"Mmmm") -> enero | H14: =TEXT(I14,"dddd") -> martes | I14: 46042 | J14: Microreunión | K14: Microreunión
A15: SUR | B15: KENNEDY | C15: Carvajal | D15: 7:00 AM | E15: MICROREUNIÓN | F15: AFINIDAD | G15: =TEXT(I15,"Mmmm") -> enero | H15: =TEXT(I15,"dddd") -> miércoles | I15: 46043 | J15: Microreunión | K15: Microreunión
A16: SUR | B16: KENNEDY | C16: Class | D16: 6:30 PM | E16: MICROREUNIÓN | F16: AFINIDAD | G16: =TEXT(I16,"Mmmm") -> enero | H16: =TEXT(I16,"dddd") -> jueves | I16: 46044 | J16: Microreunión | K16: Microreunión
A17: SUR | B17: KENNEDY | C17: Patio Bonito | D17: 7:00 AM | E17: MICROREUNIÓN | F17: AFINIDAD | G17: enero | H17: =TEXT(I17,"dddd") -> martes | I17: 46049 | J17: Microreunión | K17: Microreunión | L17: AV CR 80 NO 42C 83 SUR | M17: google.com/maps/place/Iglesia+de+Dios+Ministerial+de+Jesucristo+Internacional+-+IDMJI+-+CGMJI+BTA+EL+OLIVO/@4.6215758,-74.164928,3a,75y,316.8h,90t/data=!3m7!1e1!3m5!1sJwIftdN6Rl-LMLqtdi_3Nw!2e0!6shttps:%2F%2Fstreetviewpixels-pa.googleapis.com%2Fv1%2Fthumbnail%3Fcb_client%3Dmaps_sv.tactile%26w%3D900%26h%3D600%26pitch%3D0%26panoid%3DJwIftdN6Rl-LMLqtdi_3Nw%26yaw%3D316.80283!7i16384!8i8192!4m14!1m7!3m6!1s0x8e3f9e842a6a8335:0xe8f39c19a9ab6da3!2sIglesia+de+Dios+Ministerial+de+Jesucristo+Internacional+-+IDMJI+-+CGMJI+BTA+EL+OLIVO!8m2!3d4.6216536!4d-74.1650013!16s%2Fg%2F1tdksvtw!3m5!1s0x8e3f9e842a6a8335:0xe8f39c19a9ab6da3!8m2!3d4.6216536!4d-74.1650013!16s%2Fg%2F1tdksvtw?entry=ttu&g_ep=EgoyMDI1MTEwOS4wIKXMDSoASAFQAw%3D%3D | N17: 4.622006495658455, -74.16497448186743 | O17: Kennedy Central
A18: SUR | B18: KENNEDY | C18: Carvajal | D18: 6:00 PM | E18: MICROREUNIÓN | F18: AFINIDAD | G18: enero | H18: =TEXT(I18,"dddd") -> martes | I18: 46049 | J18: Microreunión | K18: Microreunión
A19: SUR | B19: KENNEDY | C19: Patio Bonito | D19: 9:30 AM | E19: VOLANTEO | F19: POLITICO COMUNITARIA | G19: =TEXT(I19,"Mmmm") -> enero | H19: =TEXT(I19,"dddd") -> sábado | I19: 46046 | J19: Volanteo Ciudadela Primavera | K19: Logros: 1. Areglo de vía 2. Mantenimiento de Cancha 3.Jornadas SITP | L19: Carrera 90 a # 4 - 55 | M19: https://www.google.com/maps/place/Cra.+90a+%23+4-55,+Bogot%C3%A1/@4.646679,-74.1623741,3a,75y,137.7h,90t/data=!3m7!1e1!3m5!1suWVL2SWJoVmDqNza0_56dA!2e0!6shttps:%2F%2Fstreetviewpixels-pa.googleapis.com%2Fv1%2Fthumbnail%3Fcb_client%3Dmaps_sv.tactile%26w%3D900%26h%3D600%26pitch%3D0%26panoid%3DuWVL2SWJoVmDqNza0_56dA%26yaw%3D137.7034!7i16384!8i8192!4m10!1m2!2m1!1sCarrera+90+a+%23+4+-+55!3m6!1s0x8e3f9c365233aeed:0x27e0a40c036847a2!8m2!3d4.6467299!4d-74.1624712!15sChVDYXJyZXJhIDkwIGEgIyA0IC0gNTWSAQpzdWJwcmVtaXNl4AEA!16s%2Fg%2F11t7njd0l3?entry=ttu&g_ep=EgoyMDI1MTIwOS4wIKXMDSoASAFQAw%3D%3D | N19: 4.6469223676252485, -74.16246051105125 | O19: Ciudadela Primavera | P19: 30 | Q19: Ana Temilda Guerrero
A20: SUR | B20: KENNEDY | C20: Class | D20: 11:00AM | E20: VOLANTEO | F20: POLITICO COMUNITARIA | G20: =TEXT(I20,"Mmmm") -> enero | H20: =TEXT(I20,"dddd") -> sábado | I20: 46046 | J20: Volanteo zona Roma | K20: Logros: 1.Visita Secretaría de Movilidad 2. Jornada de salud animal 3. Feria de Servicios | L20: Calle 57AS #56B-70S | M20: https://www.google.com/maps/place/Centro+Social+Comunidad+Roma+4+1+sector/@4.6081099,-74.1723756,3a,75y,81.18h,90t/data=!3m7!1e1!3m5!1sZlWC1pSYaAhP2whTuJVRJg!2e0!6shttps:%2F%2Fstreetviewpixels-pa.googleapis.com%2Fv1%2Fthumbnail%3Fcb_client%3Dmaps_sv.tactile%26w%3D900%26h%3D600%26pitch%3D0%26panoid%3DZlWC1pSYaAhP2whTuJVRJg%26yaw%3D81.17883!7i16384!8i8192!4m10!1m2!2m1!1ssal%C3%B3n+comunal+de+roma+4+etapa+1+sector!3m6!1s0x8e3f9e5fea3ce405:0xbd10c76fe465d0cf!8m2!3d4.6081149!4d-74.1722805!15sCidzYWzDs24gY29tdW5hbCBkZSByb21hIDQgZXRhcGEgMSBzZWN0b3JaKSInc2Fsw7NuIGNvbXVuYWwgZGUgcm9tYSA0IGV0YXBhIDEgc2VjdG9ykgEQY29tbXVuaXR5X2NlbnRlcpoBI0NoWkRTVWhOTUc5blMwVk1NelIyVG5WaWJXWjZla1ZCRUFF4AEA-gEECAAQPA!16s%2Fg%2F1ptxxl3t2?entry=ttu&g_ep=EgoyMDI1MTIwOS4wIKXMDSoASAFQAw%3D%3D | N20: 4.608227188618564, -74.17236096674831 | O20: Roma | P20: 30 | Q20: Bryan Rodriguez
A21: SUR | B21: KENNEDY | C21: Carvajal | D21: 9:30 AM | E21: VOLANTEO | F21: POLITICO COMUNITARIA | G21: =TEXT(I21,"Mmmm") -> enero | H21: =TEXT(I21,"dddd") -> sábado | I21: 46046 | J21: Volanteo Parque Maracaná | K21: Logro: 1. Arreglo de señal de tránsito 2. Arreglo de daño en parque por valvula de gas 3. Gestión de reposición de tapa de energía | L21: Cra. 72q #35b sur-65 | M21: https://www.google.com/maps/place/Parque+Maracan%C3%A1/@4.6175826,-74.1444726,3a,75y,72.45h,82.34t/data=!3m7!1e1!3m5!1sGkS9bosxBylOZRzEzDaVmQ!2e0!6shttps:%2F%2Fstreetviewpixels-pa.googleapis.com%2Fv1%2Fthumbnail%3Fcb_client%3Dmaps_sv.tactile%26w%3D900%26h%3D600%26pitch%3D7.660931717408033%26panoid%3DGkS9bosxBylOZRzEzDaVmQ%26yaw%3D72.45102116472239!7i16384!8i8192!4m14!1m7!3m6!1s0x8e3f9ebd1c23c2b7:0x94daa9c80824dddb!2sParque+Maracan%C3%A1!8m2!3d4.6168351!4d-74.144807!16s%2Fg%2F11c1rcptjz!3m5!1s0x8e3f9ebd1c23c2b7:0x94daa9c80824dddb!8m2!3d4.6168351!4d-74.144807!16s%2Fg%2F11c1rcptjz?entry=ttu&g_ep=EgoyMDI1MTIwOS4wIKXMDSoASAFQAw%3D%3D | N21: 4.617081045970417, -74.1447426668778 | O21: Carvajal | P21: 30 | Q21: Andrés Caicedo Carmen Garzón
A22: SUR | B22: KENNEDY | C22: Kennedy Central | D22: 11:00AM | E22: VOLANTEO | F22: POLITICO COMUNITARIA | G22: =TEXT(I22,"Mmmm") -> enero | H22: =TEXT(I22,"dddd") -> sábado | I22: 46046 | J22: Volanteo arreglo vía Corabastos | K22: Logro: 1. Gestión de arreglo de vía | L22: Diagonal 2 con calle 26 | M22: https://www.google.com/maps/place/Corabastos+-+Central+de+Abastos+Nacional/@4.6308474,-74.1536847,3a,75y,355.5h,79.05t/data=!3m7!1e1!3m5!1sLHxcBIsBWE9b1IBd5mM12Q!2e0!6shttps:%2F%2Fstreetviewpixels-pa.googleapis.com%2Fv1%2Fthumbnail%3Fcb_client%3Dmaps_sv.tactile%26w%3D900%26h%3D600%26pitch%3D10.95431592800982%26panoid%3DLHxcBIsBWE9b1IBd5mM12Q%26yaw%3D355.503021920716!7i16384!8i8192!4m10!1m2!2m1!1scorabastos!3m6!1s0x8e3f9e832c0c7055:0xcbd1a812e6c3912d!8m2!3d4.6300314!4d-74.1592464!15sCgpjb3JhYmFzdG9zWgwiCmNvcmFiYXN0b3OSARFmcmVzaF9mb29kX21hcmtldJoBI0NoWkRTVWhOTUc5blMwVkpRMEZuU1VSS2FITTJMVU5CRUFF4AEA-gEECAAQSQ!16s%2Fg%2F11cm0pl6fq?entry=ttu&g_ep=EgoyMDI1MTIwOS4wIKXMDSoASAFQAw%3D%3D | N22: 4.6306810694937965, -74.1537913527754 | O22: Kennedy | P22: 30 | Q22: Olga Saenz
A23: SUR | B23: KENNEDY | C23: Kennedy Central | D23: 2:00 PM | E23: VOLANTEO | F23: POLITICO COMUNITARIA | G23: =TEXT(I23,"Mmmm") -> enero | H23: =TEXT(I23,"dddd") -> sábado | I23: 46046 | J23: Volanteo de la gestión en la zona de Casablanca | K23: Logros: 1. Arreglo del paradero 2. Jornadas Opam 3. Jornada de personalización tu llave | L23: KR 79 - CL 46A Sur | M23: https://maps.app.goo.gl/uDVE47Pzcr3jdVTk8 | N23: 4.616796208498318, -74.1668810856337 | O23: Casablanca | P23: 30 | Q23: Liliana Sicacha Teresa Portela Luis Moya
A24: SUR | B24: KENNEDY | C24: Patio Bonito | D24: 3:00 PM | E24: VOLANTEO | F24: POLITICO COMUNITARIA | G24: =TEXT(I24,"Mmmm") -> enero | H24: =TEXT(I24,"dddd") -> sábado | I24: 46046 | J24: Volanteo de la gestión en la zona de Ciudad Granada y Los Almendros | K24: Logros: 1. Siembra de arboles 2. Luminarias 3. Vía afectada por arreglo del acueducto | L24: Cra 95A #39 SUR NO.38C | M24: https://maps.app.goo.gl/AKBVmaknkc7gUHqy9 | N24: 4.646061212802785, -74.17293040913589 | O24: Ciudad Granada y Los Almendros | P24: 30 | Q24: Paula Coronado
A25: SUR | B25: KENNEDY | C25: Class | D25: 2:00 PM | E25: VOLANTEO | F25: POLITICO COMUNITARIA | G25: =TEXT(I25,"Mmmm") -> enero | H25: =TEXT(I25,"dddd") -> sábado | I25: 46046 | J25: Volanteo de la gestión en la zona de Pastranita 2 sector | K25: Logros: 1. Socavon | L25: CALLE 49 SUR #78G-27 | M25: https://maps.app.goo.gl/zW5ureAC1BgBzS1U8 | N25: 4.612818018470261, -74.16640030425549 | O25: Pastranita 2 sector | P25: 30 | Q25: Sandra
A26: SUR | B26: KENNEDY | C26: Carvajal | D26: 3:00 PM | E26: VOLANTEO | F26: POLITICO COMUNITARIA | G26: =TEXT(I26,"Mmmm") -> enero | H26: =TEXT(I26,"dddd") -> sábado | I26: 46046 | J26: Volanteo de la gestión en la zona de Villa Andriana y Villa Claudia | K26: Logros: 1. Se gestiono y solcionó inconvenientes con la prestación del servicio del agua | L26: CLL 19 sur # 69 55 | M26: https://maps.app.goo.gl/T3EMr2fBAN8U5zAw7 | N26: 4.615839002087795, -74.12992418750464 | O26: Villa Adriana y Villa Claudia | P26: 30 | Q26: Jimmy
A27: SUR | B27: KENNEDY | F27: POLITICO COMUNITARIA | G27: =TEXT(I27,"Mmmm") -> enero | H27: =TEXT(I27,"dddd") -> domingo | I27: 46047
A28: SUR | B28: KENNEDY | F28: POLITICO COMUNITARIA | G28: =TEXT(I28,"Mmmm") -> enero | H28: =TEXT(I28,"dddd") -> martes | I28: 46049
A29: SUR | B29: KENNEDY | C29: Kennedy Central | D29: 2:00 PM | E29: VOLANTEO | F29: POLITICO COMUNITARIA | G29: =TEXT(I29,"Mmmm") -> enero | H29: =TEXT(I29,"dddd") -> miércoles | I29: 46050 | J29: Volanteo Kennedy Central | K29: Logros: 1. Arreglo del hueco al rededor de la iglesia 2. Mantenimiento de la red de EAAB 3. Mantenimiento de las canecas de basura, jornada de sensibilización menajo de basuras | L29: AV CR 80 NO 42C 83 SUR KENNEDY | M29: https://maps.app.goo.gl/FiNCRWcJA3pi2Z6S6 | N29: 4.621929097119992, -74.16481729815158 | O29: Villa Nelly y estados unidos | Q29: Jenny García
A30: SUR | B30: KENNEDY | C30: Patio Bonito | D30: 2:00 PM | E30: VOLANTEO | F30: POLITICO COMUNITARIA | G30: =TEXT(I30,"Mmmm") -> enero | H30: =TEXT(I30,"dddd") -> miércoles | I30: 46050 | J30: Volanteo Villa Hermosa | K30: Logros: 1. Gestión en punto crítico de basura 2. Arreglo de tapas telecomunicaciones 3. Arreglo tapa acueducto | L30: Cra. 87f #40-28 | M30: https://maps.app.goo.gl/RqjsgZJyEmDciLBq6 | N30: 4.634988789585417, -74.1684287569707 | O30: Villa Hermosa | Q30: Samyr
A31: SUR | B31: KENNEDY | C31: Class | D31: 2:00 PM | E31: VOLANTEO | F31: POLITICO COMUNITARIA | G31: =TEXT(I31,"Mmmm") -> enero | H31: =TEXT(I31,"dddd") -> miércoles | I31: 46050
A32: SUR | B32: KENNEDY | C32: Carvajal | D32: 2:00 PM | E32: VOLANTEO | F32: POLITICO COMUNITARIA | G32: =TEXT(I32,"Mmmm") -> enero | H32: =TEXT(I32,"dddd") -> miércoles | I32: 46050 | J32: Volanteo Americas Occidental | K32: Logros: 1.Arreglo de 2 hundimientos | L32: Av. de las Américas #71C - 29 | M32: https://maps.app.goo.gl/wzGPBs1sjMTTAyZ29 | N32: 4.6295913082322135, -74.1356781458372 | O32: Americas Occidental | Q32: Gloria
A33: SUR | B33: KENNEDY | F33: POLITICO COMUNITARIA | G33: =TEXT(I33,"Mmmm") -> febrero | H33: =TEXT(I33,"dddd") -> domingo | I33: 46054
A34: SUR | B34: KENNEDY | F34: POLITICO COMUNITARIA | G34: =TEXT(I34,"Mmmm") -> febrero | H34: =TEXT(I34,"dddd") -> martes | I34: 46056
A35: SUR | B35: KENNEDY | F35: POLITICO COMUNITARIA | G35: =TEXT(I35,"Mmmm") -> febrero | H35: =TEXT(I35,"dddd") -> miércoles | I35: 46057
A36: SUR | B36: KENNEDY | F36: POLITICO COMUNITARIA | G36: =TEXT(I36,"Mmmm") -> febrero | H36: =TEXT(I36,"dddd") -> jueves | I36: 46058
A37: SUR | B37: KENNEDY | F37: POLITICO COMUNITARIA | G37: =TEXT(I37,"Mmmm") -> febrero | H37: =TEXT(I37,"dddd") -> viernes | I37: 46059
A38: SUR | B38: KENNEDY | F38: POLITICO COMUNITARIA | G38: =TEXT(I38,"Mmmm") -> febrero | H38: =TEXT(I38,"dddd") -> sábado | I38: 46060
A39: SUR | B39: KENNEDY | F39: POLITICO COMUNITARIA | G39: =TEXT(I39,"Mmmm") -> febrero | H39: =TEXT(I39,"dddd") -> domingo | I39: 46061
A40: SUR | B40: KENNEDY | F40: POLITICO COMUNITARIA | G40: =TEXT(I40,"Mmmm") -> febrero | H40: =TEXT(I40,"dddd") -> jueves | I40: 46065
A41: SUR | B41: KENNEDY | F41: POLITICO COMUNITARIA | G41: =TEXT(I41,"Mmmm") -> febrero | H41: =TEXT(I41,"dddd") -> viernes | I41: 46066
A42: SUR | B42: KENNEDY | C42: Kennedy Central | D42: 11:30 AM | E42: VOLANTEO | F42: POLITICO COMUNITARIA | G42: =TEXT(I42,"Mmmm") -> febrero | H42: =TEXT(I42,"dddd") -> sábado | I42: 46067 | J42: Volanteo Margaritas - Parque las Margaritas etapa 1 | K42: Jornada personalización del SITP, intervención de parque, mesas de trabajo zonas de cesión
A43: SUR | B43: KENNEDY | C43: Carvajal | D43: 11:30 AM | E43: VOLANTEO | F43: POLITICO COMUNITARIA | G43: =TEXT(I43,"Mmmm") -> febrero | H43: =TEXT(I43,"dddd") -> sábado | I43: 46067 | J43: Volanteo Lucerna | K43: Arreglo de hundimiento | L43: CALLE 38 A #72K - 27 | M43: https://maps.app.goo.gl/aSmy6cu3dtProg2x9 | N43: 4.612541218524758, -74.14481479087371 | O43: Lucerna | P43: 30 | Q43: Silvia Cabuya
A44: SUR | B44: KENNEDY | C44: Carvajal | D44: 3:30 PM | E44: VOLANTEO | F44: POLITICO COMUNITARIA | G44: =TEXT(I44,"Mmmm") -> febrero | H44: =TEXT(I44,"dddd") -> sábado | I44: 46067 | J44: Volanteo Américas Occidental | K44: Arreglo de huecos reductores de velocidad e iluminación | L44: Cruce entre la Calle 1 con Carrera 73B Bis | M44: https://maps.app.goo.gl/vSWMtHstraS7geEn8 | N44: 4.62369146930814, -74.14308836286854 | O44: Americas Occidental | Q44: Franz
A45: SUR | B45: KENNEDY | C45: Class | D45: 9:30 AM | E45: VOLANTEO | F45: POLITICO COMUNITARIA | G45: =TEXT(I45,"Mmmm") -> febrero | H45: =TEXT(I45,"dddd") -> sábado | I45: 46067 | J45: Volanteo logros generales | K45: Lugar confirma el delegado
A46: SUR | B46: KENNEDY | C46: Class | D46: 2:00 PM | E46: VOLANTEO | F46: POLITICO COMUNITARIA | G46: =TEXT(I46,"Mmmm") -> febrero | H46: =TEXT(I46,"dddd") -> sábado | I46: 46067 | J46: Volanteo logros generales | K46: Lugar confirma el delegado
A47: SUR | B47: KENNEDY | C47: Patio Bonito | D47: 9:30 AM | E47: VOLANTEO | F47: POLITICO COMUNITARIA | G47: =TEXT(I47,"Mmmm") -> febrero | H47: =TEXT(I47,"dddd") -> sábado | I47: 46067 | J47: Volanteo Dintalito | K47: Recuperación punto crítico de basura | L47: Carrera 87i con Calle 42f Sur | M47: https://maps.app.goo.gl/1MEcLnm21ZnJyyPQ7 | N47: 4.6340966883902395, -74.17175924765361 | O47: Tintalito | P47: 50 | Q47: Mercedes Laverde
A48: SUR | B48: KENNEDY | C48: Patio Bonito | D48: 2:00 PM | E48: VOLANTEO | F48: POLITICO COMUNITARIA | G48: =TEXT(I48,"Mmmm") -> febrero | H48: =TEXT(I48,"dddd") -> sábado | I48: 46067 | J48: Volanteo Tintal | K48: Recuperación punto crítico de basura, arreglo de pompeyano y jornada salud animal | L48: Cra. 94 #6c-30 | M48: https://www.google.com/maps/place/Centro+Comercial+Ciudad+Tintal/@4.6526255,-74.1602425,3a,75y,95.78h,90t/data=!3m7!1e1!3m5!1sUU8BXkWBym95F7Ob-RmGiQ!2e0!6shttps:%2F%2Fstreetviewpixels-pa.googleapis.com%2Fv1%2Fthumbnail%3Fcb_client%3Dmaps_sv.tactile%26w%3D900%26h%3D600%26pitch%3D0%26panoid%3DUU8BXkWBym95F7Ob-RmGiQ%26yaw%3D95.78156!7i16384!8i8192!4m14!1m7!3m6!1s0x8e3f9c48a6b9e475:0xb493c62a8721eed2!2sCentro+Comercial+Ciudad+Tintal!8m2!3d4.6525882!4d-74.1601199!16s%2Fg%2F1ptxhhfkq!3m5!1s0x8e3f9c48a6b9e475:0xb493c62a8721eed2!8m2!3d4.6525882!4d-74.1601199!16s%2Fg%2F1ptxhhfkq?entry=ttu&g_ep=EgoyMDI2MDEyOC4wIKXMDSoASAFQAw%3D%3D | N48: 4.652855458281603, -74.16017814064253 | O48: Tintal | P48: 50 | Q48: Luz Elena Garzón
A49: SUR | B49: KENNEDY | C49: Kennedy Central | D49: 2:00 PM | E49: VOLANTEO | F49: POLITICO COMUNITARIA | G49: =TEXT(I49,"Mmmm") -> febrero | H49: =TEXT(I49,"dddd") -> domingo | I49: 46068 | J49: Volanteo Portal de Cali - Milenio Plaza
A50: SUR | B50: KENNEDY | C50: Kennedy Central | D50: 2:00 PM | E50: VOLANTEO | F50: POLITICO COMUNITARIA | G50: =TEXT(I50,"Mmmm") -> diciembre | H50: =TEXT(I50,"dddd") -> sábado | J50: Volanteo Castilla | K50: Feria de servicios, mesas de trabajo atención a parques y vías
A51: SUR | B51: KENNEDY | C51: Patio Bonito | D51: 2:00 PM | E51: VOLANTEO | F51: POLITICO COMUNITARIA | G51: =TEXT(I51,"Mmmm") -> febrero | H51: =TEXT(I51,"dddd") -> domingo | I51: 46068 | J51: Volanteo logros generales
A52: SUR | B52: KENNEDY | C52: Class | D52: 2:00 PM | E52: VOLANTEO | F52: POLITICO COMUNITARIA | G52: =TEXT(I52,"Mmmm") -> febrero | H52: =TEXT(I52,"dddd") -> domingo | I52: 46068 | J52: Volanteo logros generales
A53: SUR | B53: KENNEDY | C53: Carvajal | D53: 2:00 PM | E53: VOLANTEO | F53: POLITICO COMUNITARIA | G53: =TEXT(I53,"Mmmm") -> febrero | H53: =TEXT(I53,"dddd") -> domingo | I53: 46068 | J53: Volanteo logros generales
A54: SUR | B54: KENNEDY | C54: Kennedy Central | D54: 11:30 AM | E54: VOLANTEO | F54: POLITICO COMUNITARIA | G54: =TEXT(I54,"Mmmm") -> febrero | H54: =TEXT(I54,"dddd") -> jueves | I54: 46072 | J54: Volanteo Castilla | K54: Feria de servicios, mesas de trabajo atención a parques y vías
A55: SUR | B55: KENNEDY | C55: Carvajal | D55: 11:30 AM | E55: VOLANTEO | F55: POLITICO COMUNITARIA | G55: =TEXT(I55,"Mmmm") -> febrero | H55: =TEXT(I55,"dddd") -> jueves | I55: 46072 | J55: Volanteo Carvajal | K55: Arreglo de paradero, gestión de tapa, iluminación, mesas de trabajo sobre vías en mal estado | L55: Cra. 72 #25 Sur NO 35 | M55: https://www.google.com/maps/place/Iglesia+De+Dios+Ministerial+De+Jesucristo+Internacional+-+IDMJI+-CARVAJAL/@4.6161268,-74.1403318,3a,75y,313.09h,90t/data=!3m7!1e1!3m5!1ssosNWnRPyjh6hBwSX61BIw!2e0!6shttps:%2F%2Fstreetviewpixels-pa.googleapis.com%2Fv1%2Fthumbnail%3Fcb_client%3Dmaps_sv.tactile%26w%3D900%26h%3D600%26pitch%3D0%26panoid%3DsosNWnRPyjh6hBwSX61BIw%26yaw%3D313.09277!7i16384!8i8192!4m14!1m7!3m6!1s0x8e3f9ebb73ed00eb:0x84ff2c16af65e299!2sIglesia+De+Dios+Ministerial+De+Jesucristo+Internacional+-+IDMJI+-CARVAJAL!8m2!3d4.6162468!4d-74.140443!16s%2Fg%2F1ptwb97lz!3m5!1s0x8e3f9ebb73ed00eb:0x84ff2c16af65e299!8m2!3d4.6162468!4d-74.140443!16s%2Fg%2F1ptwb97lz?entry=ttu&g_ep=EgoyMDI2MDEyOC4wIKXMDSoASAFQAw%3D%3D | N55: 4.616524840158024, -74.14046446162256 | O55: Carvajal | P55: 50 | Q55: Sergio Osorio
A56: SUR | B56: KENNEDY | C56: Patio Bonito | D56: 9:30 AM | E56: VOLANTEO | F56: POLITICO COMUNITARIA | G56: =TEXT(I56,"Mmmm") -> febrero | H56: =TEXT(I56,"dddd") -> jueves | I56: 46072
A57: SUR | B57: KENNEDY | C57: Class | D57: 9:30 AM | E57: VOLANTEO | F57: POLITICO COMUNITARIA | G57: =TEXT(I57,"Mmmm") -> febrero | H57: =TEXT(I57,"dddd") -> jueves | I57: 46072
A58: SUR | B58: KENNEDY | C58: Kennedy Central | D58: 3:30 PM | E58: VOLANTEO | F58: POLITICO COMUNITARIA | G58: =TEXT(I58,"Mmmm") -> febrero | H58: =TEXT(I58,"dddd") -> jueves | I58: 46072
A59: SUR | B59: KENNEDY | C59: Carvajal | D59: 3:30 PM | E59: VOLANTEO | F59: POLITICO COMUNITARIA | G59: =TEXT(I59,"Mmmm") -> febrero | H59: =TEXT(I59,"dddd") -> jueves | I59: 46072
A60: SUR | B60: KENNEDY | C60: Patio Bonito | D60: 2:00 PM | E60: VOLANTEO | F60: POLITICO COMUNITARIA | G60: =TEXT(I60,"Mmmm") -> febrero | H60: =TEXT(I60,"dddd") -> jueves | I60: 46072
A61: SUR | B61: KENNEDY | C61: Class | D61: 2:00 PM | E61: VOLANTEO | F61: POLITICO COMUNITARIA | G61: =TEXT(I61,"Mmmm") -> febrero | H61: =TEXT(I61,"dddd") -> jueves | I61: 46072
A62: SUR | B62: KENNEDY | F62: POLITICO COMUNITARIA | G62: =TEXT(I62,"Mmmm") -> febrero | H62: =TEXT(I62,"dddd") -> viernes | I62: 46073
A63: SUR | B63: KENNEDY | C63: Kennedy Central | D63: 11:30 AM | E63: VOLANTEO | F63: POLITICO COMUNITARIA | G63: =TEXT(I63,"Mmmm") -> febrero | H63: =TEXT(I63,"dddd") -> sábado | I63: 46074
A64: SUR | B64: KENNEDY | C64: Kennedy Central | D64: 3:30 PM | E64: VOLANTEO | F64: POLITICO COMUNITARIA | G64: =TEXT(I64,"Mmmm") -> febrero | H64: =TEXT(I64,"dddd") -> sábado | I64: 46074
A65: SUR | B65: KENNEDY | C65: Class | D65: 11:30 AM | E65: VOLANTEO | F65: POLITICO COMUNITARIA | G65: =TEXT(I65,"Mmmm") -> febrero | H65: =TEXT(I65,"dddd") -> sábado | I65: 46074
A66: SUR | B66: KENNEDY | C66: Class | D66: 3:30 PM | E66: VOLANTEO | F66: POLITICO COMUNITARIA | G66: =TEXT(I66,"Mmmm") -> febrero | H66: =TEXT(I66,"dddd") -> sábado | I66: 46074
A67: SUR | B67: KENNEDY | C67: Carvajal | D67: 9:30 AM | E67: VOLANTEO | F67: POLITICO COMUNITARIA | G67: =TEXT(I67,"Mmmm") -> febrero | H67: =TEXT(I67,"dddd") -> sábado | I67: 46074
A68: SUR | B68: KENNEDY | C68: Carvajal | D68: 2:00 PM | E68: VOLANTEO | F68: POLITICO COMUNITARIA | G68: =TEXT(I68,"Mmmm") -> febrero | H68: =TEXT(I68,"dddd") -> sábado | I68: 46074
A69: SUR | B69: KENNEDY | C69: Patio Bonito | D69: 9:30 AM | E69: VOLANTEO | F69: POLITICO COMUNITARIA | G69: =TEXT(I69,"Mmmm") -> febrero | H69: =TEXT(I69,"dddd") -> sábado | I69: 46074
A70: SUR | B70: KENNEDY | C70: Patio Bonito | D70: 2:00 PM | E70: VOLANTEO | F70: POLITICO COMUNITARIA | G70: =TEXT(I70,"Mmmm") -> febrero | H70: =TEXT(I70,"dddd") -> sábado | I70: 46074
A71: SUR | B71: KENNEDY | F71: POLITICO COMUNITARIA | G71: =TEXT(I71,"Mmmm") -> febrero | H71: =TEXT(I71,"dddd") -> domingo | I71: 46075
A72: SUR | B72: KENNEDY | C72: Kennedy Central | D72: 11:00AM | E72: VOLANTEO | F72: POLITICO COMUNITARIA | G72: =TEXT(I72,"Mmmm") -> febrero | H72: =TEXT(I72,"dddd") -> martes | I72: 46077
A73: SUR | B73: KENNEDY | C73: Patio Bonito | D73: 11:00AM | E73: VOLANTEO | F73: POLITICO COMUNITARIA | G73: =TEXT(I73,"Mmmm") -> febrero | H73: =TEXT(I73,"dddd") -> martes | I73: 46077
A74: SUR | B74: KENNEDY | C74: Class | D74: 2:00 PM | E74: VOLANTEO | F74: POLITICO COMUNITARIA | G74: =TEXT(I74,"Mmmm") -> febrero | H74: =TEXT(I74,"dddd") -> martes | I74: 46077
A75: SUR | B75: KENNEDY | C75: Carvajal | D75: 2:00 PM | E75: VOLANTEO | F75: POLITICO COMUNITARIA | G75: =TEXT(I75,"Mmmm") -> febrero | H75: =TEXT(I75,"dddd") -> martes | I75: 46077
A76: SUR | B76: KENNEDY | F76: POLITICO COMUNITARIA | G76: =TEXT(I76,"Mmmm") -> febrero | H76: =TEXT(I76,"dddd") -> miércoles | I76: 46078
A77: SUR | B77: KENNEDY | F77: POLITICO COMUNITARIA | G77: =TEXT(I77,"Mmmm") -> febrero | H77: =TEXT(I77,"dddd") -> jueves | I77: 46079
A78: SUR | B78: KENNEDY | F78: POLITICO COMUNITARIA | G78: =TEXT(I78,"Mmmm") -> marzo | H78: =TEXT(I78,"dddd") -> domingo | I78: 46082
A79: SUR | B79: KENNEDY | F79: POLITICO COMUNITARIA | G79: =TEXT(I79,"Mmmm") -> marzo | H79: =TEXT(I79,"dddd") -> martes | I79: 46084
A80: SUR | B80: KENNEDY | F80: POLITICO COMUNITARIA | G80: =TEXT(I80,"Mmmm") -> marzo | H80: =TEXT(I80,"dddd") -> miércoles | I80: 46085
A81: SUR | B81: KENNEDY | F81: POLITICO COMUNITARIA | G81: =TEXT(I81,"Mmmm") -> marzo | H81: =TEXT(I81,"dddd") -> jueves | I81: 46086

Sheet Hoja 21
B1: Templo | C1: Total líderes | D1: 0 referidos | E1: 1–4 referidos | F1: 5–9 referidos | G1: 10 o más
B2: Kennedy Central | C2: 960 | D2: 417 | E2: 293 | F2: 134 | G2: 75 | H2: =G2+F2+E2 -> 502 | I2: =H2*60% -> 301.2 | J2: =I2+H2 -> 803.2 | K2: =C2*75% -> 720 | U2: Febrero | AO2: Marzo
B3: Carvajal | C3: 492 | D3: 192 | E3: 149 | F3: 56 | G3: 48 | H3: =G3+F3+E3 -> 253 | I3: =H3*60% -> 151.8 | J3: =I3+H3 -> 404.8 | K3: =C3*75% -> 369 | T3: Actividad | U3: 9 | V3: 10 | W3: 11 | X3: 12 | Y3: 13 | Z3: 14 | AA3: 15 | AB3: 16 | AC3: 17 | AD3: 18 | AE3: 19 | AF3: 20 | AG3: 21 | AH3: 22 | AI3: 23 | AJ3: 24 | AK3: 25 | AL3: 26 | AM3: 27 | AN3: 28 | AO3: 1
B4: Class Roma | C4: 235 | D4: 79 | E4: 53 | F4: 42 | G4: 55 | H4: =G4+F4+E4 -> 150 | I4: =H4*60% -> 90 | J4: =I4+H4 -> 240 | K4: =C4*75% -> 176.25 | T4: Entrega de manillas y convocatoria
B5: Patio Bonito | C5: 511 | D5: 272 | E5: 104 | F5: 48 | G5: 51 | H5: =G5+F5+E5 -> 203 | I5: =H5*60% -> 121.8 | J5: =I5+H5 -> 324.8 | K5: =C5*75% -> 383.25 | T5: Reunión Comité de Logística y Montaje
B6: Bosa Estación | C6: 1080 | D6: 594 | E6: 225 | F6: 115 | G6: 97 | H6: =G6+F6+E6 -> 437 | I6: =H6*60% -> 262.2 | J6: =I6+H6 -> 699.2 | K6: =C6*75% -> 810 | T6: Reunión Comité de Control de Ingreso y Aforo
B7: Bosa Recreo | C7: 849 | D7: 323 | E7: 228 | F7: 104 | G7: 105 | H7: =G7+F7+E7 -> 437 | I7: =H7*60% -> 262.2 | J7: =I7+H7 -> 699.2 | K7: =C7*75% -> 636.75 | T7: Reunión Comité de Acomodación
B8: TOTAL GENERAL | C8: =SUM(C2:C7) -> 4127 | D8: 1877 | E8: 1052 | F8: 499 | G8: 431 | H8: =SUM(H2:H7) -> 1982 | I8: =SUM(I2:I7) -> 1189.2 | J8: =SUM(J2:J7) -> 3171.2 | K8: =C8*75% -> 3095.25 | T8: Reunión Comité de Bienestar y Refrigerios
T9: Reunión Comité de Salud (Primeros Auxilios)
T10: Día D
E14: Comités
B15: Templo | C15: Líder activos | D15: Manillas a entregar | E15: Comité de Control de Ingreso y Aforo | F15: Comité de Logística y Montaje | G15: Comité de Acomodación | H15: Comité de Bienestar y Refrigerios | I15: Comité de Salud (Primeros Auxilios) | J15: Total por templo | K15: Total Líderes + Comités
B16: Kennedy Central | C16: 960 | D16: 700 | E16: 10 | F16: 6.9784347 | G16: 6.9784347 | H16: 3.4892173 | I16: 2 | J16: =I16+H16+G16+F16+E16 -> 29.446087 | K16: =J16+D16 -> 729.44609
B17: Carvajal | C17: 492 | D17: 330 | E17: 4.768597 | F17: 3.5764478 | G17: 3.5764478 | H17: 1.7882239 | I17: 1 | J17: =I17+H17+G17+F17+E17 -> 14.709717 | K17: =J17+D17 -> 344.70972
B18: Patio Bonito | C18: 511 | D18: 350 | E18: 4.9527502 | F18: 3.7145626 | G18: 3.7145626 | H18: 1.8572813 | I18: 1 | J18: =I18+H18+G18+F18+E18 -> 15.239157 | K18: =J18+D18 -> 365.23916
B19: Bosa Estación | C19: 1080 | D19: 700 | E19: 10.467652 | F19: 7.850739 | G19: 7.850739 | H19: 3.9253695 | I19: 2 | J19: =I19+H19+G19+F19+E19 -> 32.0945 | K19: =J19+D19 -> 732.0945 | L19: =D19+D20 -> 1400 | M19: =L19/2 -> 700
B20: Bosa Recreo | C20: 849 | D20: 700 | E20: 10 | F20: 6.1715532 | G20: 6.1715532 | H20: 3.0857766 | I20: 2 | J20: =I20+H20+G20+F20+E20 -> 27.428883 | K20: =J20+D20 -> 727.42888 | L20: 700
B21: Total | C21: =SUM(C16:C20) -> 3892 | D21: =SUM(D16:D20) -> 2780 | E21: =SUM(E16:E20) -> 40.188999 | F21: =SUM(F16:F20) -> 28.291737 | G21: =SUM(G16:G20) -> 28.291737 | H21: =SUM(H16:H20) -> 14.145869 | I21: =SUM(I16:I20) -> 8 | J21: =I21+H21+G21+F21+E21 -> 118.91834 | K21: =J21+D21 -> 2898.9183 | L21: =L19-L20 -> 700
C26: Comité de Control de Ingreso y Aforo | D26: 40
C27: Comité de Logística y Montaje | D27: 30 | L27: =J21+D21 -> 2898.9183
C28: Comité de Acomodación | D28: 30 | H28: =13-45 -> -32
C29: Comité de Bienestar y Refrigerios | D29: 15
C30: Comité de Salud (Primeros Auxilios, uno por templo) | D30: 6
D31: =SUM(D26:D30) -> 121
C36: 9 | D36: 10 | E36: 11 | F36: 12 | G36: 13 | H36: 14 | I36: 15 | J36: 16 | K36: 17 | L36: 18 | M36: 19
B37: Entrega de manillas y convocatoria
B38: Reunión Comité de Logística y Montaje
B39: Reunión Comité de Control de Ingreso y Aforo
B40: Reunión Comité de Acomodación
B41: Reunión Comité de Bienestar y Refrigerios
B42: Reunión Comité de Salud (Primeros Auxilios)

Sheet Cronograma Kennedy enero
A1: BOGOTÁ | B1: LOCALIDAD | C1: SEDE | D1: HORA | E1: ACTIVIDAD | F1: ESTRATEGIA | G1: MES | H1: DIA | I1: FECHA CAMPAÑA | J1: DETALLE DE LA ACTIVIDAD | K1: LOGROS JUSTIFICACION | L1: DIRECCIÓN | M1: LINK DE GOOGLE MAPS | N1: COORDENADAS | O1: BARRIO | P1: BENEFICIARIOS O ASISTENTES | Q1: LÍDER Y CELULAR | R1: LOGISTICA (Vecinos contactados, espacio, sillas, publicidad, refrigerios)
A2: SUR | B2: BOGOTA. D.C. - LOCALIDAD 8 KENNEDY | C2: Kennedy Central | D2: 8:00 AM | E2: ENSEÑANZA | F2: AFINIDAD | G2: Enero | H2: Domingo | I2: 46033 | J2: Punto de InfoMIRA PI - activación de líderes y referidos | K2: Afinidad | L2: AV CR 80 NO 42C 83 SUR KENNEDY | M2: https://maps.app.goo.gl/UiBexu9Axhn6zuEZ6 | N2: 4.621764992515213, -74.16489171361977 | O2: Los Olivos
A3: SUR | B3: BOGOTA. D.C. - LOCALIDAD 8 KENNEDY | C3: Kennedy Central | D3: 11:00 AM | E3: ENSEÑANZA | F3: AFINIDAD | G3: Enero | H3: Domingo | I3: 46033 | J3: Punto de InfoMIRA PI - activación de líderes y referidos | K3: Afinidad | L3: AV CR 80 NO 42C 83 SUR KENNEDY | M3: https://maps.app.goo.gl/UiBexu9Axhn6zuEZ6 | N3: 4.621764992515213, -74.16489171361977 | O3: Los Olivos
A4: SUR | B4: BOGOTA. D.C. - LOCALIDAD 8 KENNEDY | C4: Kennedy Central | D4: 11:00 AM | E4: ALABANZA | F4: AFINIDAD | G4: Enero | H4: Miercoles | I4: 46036 | J4: Punto de InfoMIRA PI - activación de líderes y referidos | K4: Afinidad | L4: AV CR 80 NO 42C 83 SUR KENNEDY | M4: https://maps.app.goo.gl/UiBexu9Axhn6zuEZ6 | N4: 4.621764992515213, -74.16489171361977 | O4: Los Olivos
A5: SUR | B5: BOGOTA. D.C. - LOCALIDAD 8 KENNEDY | C5: Kennedy Central | D5: 11:00 AM | E5: ALABANZA | F5: AFINIDAD | G5: Enero | H5: Miercoles | I5: 46036 | J5: Punto de InfoMIRA PI - activación de líderes y referidos | K5: Afinidad | L5: AV CR 80 NO 42C 83 SUR KENNEDY | M5: https://maps.app.goo.gl/UiBexu9Axhn6zuEZ6 | N5: 4.621764992515213, -74.16489171361977 | O5: Los Olivos
A6: SUR | B6: BOGOTA. D.C. - LOCALIDAD 8 KENNEDY | C6: Kennedy Central | D6: 11:00 AM | E6: ALABANZA | F6: AFINIDAD | G6: Enero | H6: Miercoles | I6: 46036 | J6: Punto de InfoMIRA PI - activación de líderes y referidos | K6: Afinidad | L6: AV CR 80 NO 42C 83 SUR KENNEDY | M6: https://maps.app.goo.gl/UiBexu9Axhn6zuEZ6 | N6: 4.621764992515213, -74.16489171361977 | O6: Los Olivos
A7: SUR | B7: BOGOTA. D.C. - LOCALIDAD 8 KENNEDY | C7: Kennedy Central | D7: 7:00 AM | E7: ENSEÑANZA | F7: AFINIDAD | G7: Enero | H7: Jueves | I7: 46037 | J7: Punto de InfoMIRA PI y Microreunión Focalizada MRF MRF: Líderes activos, con 0 referidos activos, pero con referidos inactivos. | K7: Afinidad | L7: AV CR 80 NO 42C 83 SUR KENNEDY | M7: https://maps.app.goo.gl/UiBexu9Axhn6zuEZ6 | N7: 4.621764992515213, -74.16489171361977 | O7: Los Olivos | Q7: N/A
A8: SUR | B8: BOGOTA. D.C. - LOCALIDAD 8 KENNEDY | C8: Kennedy Central | D8: 10:00 AM | E8: TERRITORIO | F8: POLITICO COMUNITARIA | G8: Enero | H8: Jueves | I8: 46037 | J8: MT - CIUDAD DE CALI AFECTACIÓN POR SEMÁFORO (5109) | K8: 1. Se asignó un auxiliar de tránsito desde el 22 de agosto. 2. Confirmado el retiro del semáforo para el 19 de octubre de 2025 o hasta entregar la obra de la av Cali. | L8: Cra. 86c Bis #42 - 32 | M8: https://maps.app.goo.gl/9j3GGhx4THnQhm1N6 | N8: 4.6318622196069965, -74.16833461172479 | O8: Ciudad de Cali | P8: 25 | Q8: ORLANDO MARULANDA LEON 3045831717
A9: SUR | B9: BOGOTA. D.C. - LOCALIDAD 8 KENNEDY | C9: Kennedy Central | D9: 12:00 M | E9: ALMUERZO | F9: N/A | G9: Enero | H9: Jueves | I9: 46037 | J9: ALMUERZO ALMUERZO | K9: ALMUERZO ALMUERZO
A10: SUR | B10: BOGOTA. D.C. - LOCALIDAD 8 KENNEDY | C10: Kennedy Central | D10: 2:00 PM | E10: TERRITORIO | F10: POLITICO COMUNITARIA | G10: Enero | H10: Jueves | I10: 46037 | J10: MT - CIUDAD KENNEDY OCCIDENTAL INSEGURIDAD POR RETIRO DE REJAS DE INGRESO (6236 | K10: 1. Se esta gestionando con el DADEP la administración de las bahías por parte de la JAC 2. Se realizaron dos mesas de trabajo para fortalecer el frente de seguridad 3. Se esta gestionando con la ALK el arreglo de la bahía, ya que es un segmento local. | L10: Av calle 43 #79d 01 Salón comunal nuevo Kennedy 2 sector | M10: https://maps.app.goo.gl/3r17ZACt9RpwC6Kr7 | N10: 4.619368374284227, -74.16620313683892 | O10: Nuevo Kennedy | P10: 20 | Q10: MIGUEL ADRIEL GUERRERO SANCHEZ 3214929228
A11: SUR | B11: BOGOTA. D.C. - LOCALIDAD 8 KENNEDY | C11: Kennedy Central | D11: 3:30 PM | E11: TERRITORIO | F11: POLITICO COMUNITARIA | G11: Enero | H11: Jueves | I11: 46037 | J11: MT - JORNADA OPAM PARQUE HOLANDA (6172) | K11: Visita empresa INGEPAR 1. Se realizó jornada de salud y bienestar animal con OPAM, se beneficiarion cerca de 40 personas con sus animales de compañía. | L11: Cra. 88b #53 - 51 sur | M11: https://maps.app.goo.gl/B7Vvnj17Ra5gpNUL9 | N11: 4.629549105441344, -74.18311837297175 | O11: Bosa Brasilia | P11: 20 | Q11: NUBIA LILIANA PARRA GUERRERO 3202930363
A12: SUR | B12: BOGOTA. D.C. - LOCALIDAD 8 KENNEDY | C12: Kennedy Central | D12: 5:00 PM | E12: ENSEÑANZA | F12: AFINIDAD | G12: Enero | H12: Jueves | I12: 46037 | J12: Punto de InfoMIRA PI y Microreunión Focalizada MRF MRF: Líderes activos, con 0 referidos activos, pero con referidos inactivos. | K12: Afinidad | L12: AV CR 80 NO 42C 83 SUR KENNEDY | M12: https://maps.app.goo.gl/UiBexu9Axhn6zuEZ6 | N12: 4.621764992515213, -74.16489171361977 | O12: Los Olivos | Q12: N/A
A13: SUR | B13: BOGOTA. D.C. - LOCALIDAD 8 KENNEDY | C13: Kennedy Central | D13: 7:00 PM | E13: ENSEÑANZA | F13: AFINIDAD | G13: Enero | H13: Jueves | I13: 46037 | J13: Punto de InfoMIRA PI y Microreunión Focalizada MRF MRF: Líderes activos, con 0 referidos activos, pero con referidos inactivos. | K13: Afinidad | L13: AV CR 80 NO 42C 83 SUR KENNEDY | M13: https://maps.app.goo.gl/UiBexu9Axhn6zuEZ6 | N13: 4.621764992515213, -74.16489171361977 | O13: Los Olivos
A14: SUR | B14: BOGOTA. D.C. - LOCALIDAD 8 KENNEDY | C14: Kennedy Central | D14: 7:00 AM | E14: ENSEÑANZA | F14: AFINIDAD | G14: Enero | H14: Viernes | I14: 46038 | J14: Punto de InfoMIRA PI y Microreunión Focalizada MRF MRF: Líderes activos, con 0 referidos activos, pero con referidos inactivos. | K14: Afinidad | L14: AV CR 80 NO 42C 83 SUR KENNEDY | M14: https://maps.app.goo.gl/UiBexu9Axhn6zuEZ6 | N14: 4.621764992515213, -74.16489171361977 | O14: Los Olivos | Q14: N/A
A15: SUR | B15: BOGOTA. D.C. - LOCALIDAD 8 KENNEDY | C15: Kennedy Central | D15: 5:00 PM | E15: ENSEÑANZA | F15: AFINIDAD | G15: Enero | H15: Viernes | I15: 46038 | J15: Punto de InfoMIRA PI y Microreunión Focalizada MRF MRF: Líderes activos, con 0 referidos activos, pero con referidos inactivos. | K15: Afinidad | L15: AV CR 80 NO 42C 83 SUR KENNEDY | M15: https://maps.app.goo.gl/UiBexu9Axhn6zuEZ6 | N15: 4.621764992515213, -74.16489171361977 | O15: Los Olivos | Q15: N/A
A16: SUR | B16: BOGOTA. D.C. - LOCALIDAD 8 KENNEDY | C16: Kennedy Central | D16: 7:00 PM | E16: ENSEÑANZA | F16: AFINIDAD | G16: Enero | H16: Viernes | I16: 46038 | J16: Punto de InfoMIRA PI - activación de líderes y referidos | K16: Afinidad | L16: AV CR 80 NO 42C 83 SUR KENNEDY | M16: https://maps.app.goo.gl/UiBexu9Axhn6zuEZ6 | N16: 4.621764992515213, -74.16489171361977 | O16: Los Olivos | Q16: N/A
